<DataTable>
  <!--  #region ULD Type XML Description
  /*
  *****************************************************************************
  XML Name:		  WebFormDefinition ULD Type
  Purpose:		  This XML used to View New Edit ULD Type Details
  Company:		  CargoFlash Infotech Pvt Ltd.
  Author:			  Swati Rastogi.
  Created On:		19 Nov 2015
  Updated By:    
	Updated On:
  Approved By:
  Approved On:
  *****************************************************************************
  */
  #endregion-->
  <!--New ULD Type Details-->
  <WebFormDefinition>
    <DETAIL_ID>1</DETAIL_ID>
    <FORM_ID>731</FORM_ID>
    <HTML_CONTROL_ID>ULDCode</HTML_CONTROL_ID>
    <DISPLAY_ORDER>1</DISPLAY_ORDER>
    <ASSEMBLY_NAME>HTML.TextBox</ASSEMBLY_NAME>
    <LABEL_CELL_TEXT>ULD Code</LABEL_CELL_TEXT>
    <LABEL_CELL_CSSCLASS>formlabel</LABEL_CELL_CSSCLASS>
    <DATA_FIELDNAME>ULDCode</DATA_FIELDNAME>
    <DATA_FIELD_CSSCLASS></DATA_FIELD_CSSCLASS>
    <DATA_CELL_CSSCLASS>formInputcolumn</DATA_CELL_CSSCLASS>
    <ONCLICK_HANDLER></ONCLICK_HANDLER>
    <POSTBACK_URL></POSTBACK_URL>
    <CALLBACK_URL></CALLBACK_URL>
    <SKIN_ID></SKIN_ID>
    <TOOLTIP>Enter ULD Code</TOOLTIP>
    <BTN_USESUBMIT_BEHAVIOUR></BTN_USESUBMIT_BEHAVIOUR>
    <VISIBLE>true</VISIBLE>
    <READONLY>false</READONLY>
    <ENABLE_VIEWSTATE>true</ENABLE_VIEWSTATE>
    <MAXLENGTH>3</MAXLENGTH>
    <MULTILINE></MULTILINE>
    <WIDTH>50</WIDTH>
    <HEIGHT></HEIGHT>
    <SECTION_NAME>ULD Code Information</SECTION_NAME>
    <ONKEY_HANDLER></ONKEY_HANDLER>
    <ONBLUR_HANDLER></ONBLUR_HANDLER>
    <ENABLE_REQUIREVALIDATION>true</ENABLE_REQUIREVALIDATION>
    <REQUIRED_FIELD_MESSAGE>Please Enter Minimum Value 3</REQUIRED_FIELD_MESSAGE>
    <LOOKUP_NAME></LOOKUP_NAME>
    <IMAGE_URL></IMAGE_URL>
    <CONTROL_TOTAL></CONTROL_TOTAL>
    <TAB_INDEX>1</TAB_INDEX>
    <TEXT_TYPE>ALPHANUMERICUPPER</TEXT_TYPE>
    <ALLOWCHAR></ALLOWCHAR>
    <DATA_VALIDATE>required,maxlength[3],minlength[3]</DATA_VALIDATE>
  </WebFormDefinition>

  <WebFormDefinition>
    <DETAIL_ID>17</DETAIL_ID>
    <FORM_ID>731</FORM_ID>
    <HTML_CONTROL_ID>ULDTypeSno</HTML_CONTROL_ID>
    <DISPLAY_ORDER>17</DISPLAY_ORDER>
    <ASSEMBLY_NAME>HTML.AutoCompleteTextBox</ASSEMBLY_NAME>
    <LABEL_CELL_TEXT>ULD Type</LABEL_CELL_TEXT>
    <LABEL_CELL_CSSCLASS>formlabel</LABEL_CELL_CSSCLASS>
    <DATA_FIELDNAME>ULDTypeSno</DATA_FIELDNAME>
    <DATA_FIELD_CSSCLASS></DATA_FIELD_CSSCLASS>
    <DATA_CELL_CSSCLASS>formInputcolumn</DATA_CELL_CSSCLASS>
    <ONCLICK_HANDLER></ONCLICK_HANDLER>
    <POSTBACK_URL></POSTBACK_URL>
    <CALLBACK_URL></CALLBACK_URL>
    <SKIN_ID></SKIN_ID>
    <TOOLTIP>Enter ULD Type</TOOLTIP>
    <BTN_USESUBMIT_BEHAVIOUR></BTN_USESUBMIT_BEHAVIOUR>
    <VISIBLE>true</VISIBLE>
    <READONLY>false</READONLY>
    <ENABLE_VIEWSTATE>false</ENABLE_VIEWSTATE>
    <MAXLENGTH></MAXLENGTH>
    <MULTILINE></MULTILINE>
    <WIDTH>100</WIDTH>
    <HEIGHT></HEIGHT>
    <SECTION_NAME></SECTION_NAME>
    <ONKEY_HANDLER></ONKEY_HANDLER>
    <ONBLUR_HANDLER></ONBLUR_HANDLER>
    <ENABLE_REQUIREVALIDATION>false</ENABLE_REQUIREVALIDATION>
    <REQUIRED_FIELD_MESSAGE>ULDType can not be blank</REQUIRED_FIELD_MESSAGE>
    <LOOKUP_NAME></LOOKUP_NAME>
    <IMAGE_URL></IMAGE_URL>
    <CONTROL_TOTAL></CONTROL_TOTAL>
    <TAB_INDEX>17</TAB_INDEX>
    <TEXT_TYPE>UPPERCASE</TEXT_TYPE>
    <ALLOWCHAR></ALLOWCHAR>
    <DATA_VALIDATE></DATA_VALIDATE>
  </WebFormDefinition>

  <WebFormDefinition>
    <DETAIL_ID>2</DETAIL_ID>
    <FORM_ID>731</FORM_ID>
    <HTML_CONTROL_ID>AirlineSno</HTML_CONTROL_ID>
    <DISPLAY_ORDER>2</DISPLAY_ORDER>
    <ASSEMBLY_NAME>HTML.AutoCompleteTextBox</ASSEMBLY_NAME>
    <LABEL_CELL_TEXT>Airline</LABEL_CELL_TEXT>
    <LABEL_CELL_CSSCLASS>formlabel</LABEL_CELL_CSSCLASS>
    <DATA_FIELDNAME>AirlineSno</DATA_FIELDNAME>
    <DATA_FIELD_CSSCLASS></DATA_FIELD_CSSCLASS>
    <DATA_CELL_CSSCLASS>formInputcolumn</DATA_CELL_CSSCLASS>
    <ONCLICK_HANDLER></ONCLICK_HANDLER>
    <POSTBACK_URL></POSTBACK_URL>
    <CALLBACK_URL></CALLBACK_URL>
    <SKIN_ID></SKIN_ID>
    <TOOLTIP>Enter Airline</TOOLTIP>
    <BTN_USESUBMIT_BEHAVIOUR></BTN_USESUBMIT_BEHAVIOUR>
    <VISIBLE>true</VISIBLE>
    <READONLY>false</READONLY>
    <ENABLE_VIEWSTATE>true</ENABLE_VIEWSTATE>
    <MAXLENGTH></MAXLENGTH>
    <MULTILINE></MULTILINE>
    <WIDTH>200</WIDTH>
    <HEIGHT></HEIGHT>
    <SECTION_NAME></SECTION_NAME>
    <ONKEY_HANDLER></ONKEY_HANDLER>
    <ONBLUR_HANDLER></ONBLUR_HANDLER>
    <ENABLE_REQUIREVALIDATION>true</ENABLE_REQUIREVALIDATION>
    <REQUIRED_FIELD_MESSAGE>Airline can not be blank</REQUIRED_FIELD_MESSAGE>
    <LOOKUP_NAME></LOOKUP_NAME>
    <IMAGE_URL></IMAGE_URL>
    <CONTROL_TOTAL></CONTROL_TOTAL>
    <TAB_INDEX>2</TAB_INDEX>
    <TEXT_TYPE>UPPERCASE</TEXT_TYPE>
    <ALLOWCHAR></ALLOWCHAR>
    <DATA_VALIDATE>required</DATA_VALIDATE>
  </WebFormDefinition>

  <WebFormDefinition>
    <DETAIL_ID>3</DETAIL_ID>
    <FORM_ID>731</FORM_ID>
    <HTML_CONTROL_ID>RateClassSno</HTML_CONTROL_ID>
    <DISPLAY_ORDER>3</DISPLAY_ORDER>
    <ASSEMBLY_NAME>HTML.AutoCompleteTextBox</ASSEMBLY_NAME>
    <LABEL_CELL_TEXT>ULD Class</LABEL_CELL_TEXT>
    <LABEL_CELL_CSSCLASS>formlabel</LABEL_CELL_CSSCLASS>
    <DATA_FIELDNAME>RateClassSno</DATA_FIELDNAME>
    <DATA_FIELD_CSSCLASS></DATA_FIELD_CSSCLASS>
    <DATA_CELL_CSSCLASS>formInputcolumn</DATA_CELL_CSSCLASS>
    <ONCLICK_HANDLER></ONCLICK_HANDLER>
    <POSTBACK_URL></POSTBACK_URL>
    <CALLBACK_URL></CALLBACK_URL>
    <SKIN_ID></SKIN_ID>
    <TOOLTIP>Enter ULD Class</TOOLTIP>
    <BTN_USESUBMIT_BEHAVIOUR></BTN_USESUBMIT_BEHAVIOUR>
    <VISIBLE>true</VISIBLE>
    <READONLY>false</READONLY>
    <ENABLE_VIEWSTATE>true</ENABLE_VIEWSTATE>
    <MAXLENGTH></MAXLENGTH>
    <MULTILINE></MULTILINE>
    <WIDTH>100</WIDTH>
    <HEIGHT></HEIGHT>
    <SECTION_NAME></SECTION_NAME>
    <ONKEY_HANDLER></ONKEY_HANDLER>
    <ONBLUR_HANDLER></ONBLUR_HANDLER>
    <ENABLE_REQUIREVALIDATION>true</ENABLE_REQUIREVALIDATION>
    <REQUIRED_FIELD_MESSAGE>ULD Class can not be blank</REQUIRED_FIELD_MESSAGE>
    <LOOKUP_NAME></LOOKUP_NAME>
    <IMAGE_URL></IMAGE_URL>
    <CONTROL_TOTAL></CONTROL_TOTAL>
    <TAB_INDEX>3</TAB_INDEX>
    <TEXT_TYPE>UPPERCASE</TEXT_TYPE>
    <ALLOWCHAR></ALLOWCHAR>
    <DATA_VALIDATE>required</DATA_VALIDATE>
  </WebFormDefinition>
 <WebFormDefinition>
    <DETAIL_ID>4</DETAIL_ID>
    <FORM_ID>731</FORM_ID>
    <HTML_CONTROL_ID>ULdtype</HTML_CONTROL_ID>
    <DISPLAY_ORDER>4</DISPLAY_ORDER>
    <ASSEMBLY_NAME>HTML.RadioButtonList</ASSEMBLY_NAME>
    <LABEL_CELL_TEXT>ULD Types</LABEL_CELL_TEXT>
    <LABEL_CELL_CSSCLASS>formlabel</LABEL_CELL_CSSCLASS>
    <DATA_FIELDNAME>ULdtype</DATA_FIELDNAME>
    <DATA_FIELD_CSSCLASS></DATA_FIELD_CSSCLASS>
    <DATA_CELL_CSSCLASS>formInputcolumn</DATA_CELL_CSSCLASS>
    <ONCLICK_HANDLER></ONCLICK_HANDLER>
    <POSTBACK_URL></POSTBACK_URL>
    <CALLBACK_URL></CALLBACK_URL>
    <SKIN_ID></SKIN_ID>
    <TOOLTIP>ULD Types</TOOLTIP>
    <BTN_USESUBMIT_BEHAVIOUR>true</BTN_USESUBMIT_BEHAVIOUR>
    <VISIBLE>true</VISIBLE>
    <READONLY>true</READONLY>
    <ENABLE_VIEWSTATE>true</ENABLE_VIEWSTATE>
    <MAXLENGTH></MAXLENGTH>
    <MULTILINE></MULTILINE>
    <WIDTH></WIDTH>
    <HEIGHT></HEIGHT>
    <SECTION_NAME></SECTION_NAME>
    <ONKEY_HANDLER></ONKEY_HANDLER>
    <ONBLUR_HANDLER></ONBLUR_HANDLER>
    <ENABLE_REQUIREVALIDATION>True</ENABLE_REQUIREVALIDATION>
    <REQUIRED_FIELD_MESSAGE>>ULD Types can not be blank</REQUIRED_FIELD_MESSAGE>
    <LOOKUP_NAME></LOOKUP_NAME>
    <IMAGE_URL></IMAGE_URL>
    <CONTROL_TOTAL></CONTROL_TOTAL>
    <TAB_INDEX>4</TAB_INDEX>
    <TEXT_TYPE>ENUM.ULDTYPES</TEXT_TYPE>
    <ALLOWCHAR></ALLOWCHAR>
    <DATA_VALIDATE>required</DATA_VALIDATE>
  </WebFormDefinition>
  <WebFormDefinition>
    <DETAIL_ID>5</DETAIL_ID>
    <FORM_ID>731</FORM_ID>
    <HTML_CONTROL_ID>EmptyWeight</HTML_CONTROL_ID>
    <DISPLAY_ORDER>5</DISPLAY_ORDER>
    <ASSEMBLY_NAME>HTML.TextBox</ASSEMBLY_NAME>
    <LABEL_CELL_TEXT>Tare Weight</LABEL_CELL_TEXT>
    <LABEL_CELL_CSSCLASS>formlabel</LABEL_CELL_CSSCLASS>
    <DATA_FIELDNAME>EmptyWeight</DATA_FIELDNAME>
    <DATA_FIELD_CSSCLASS></DATA_FIELD_CSSCLASS>
    <DATA_CELL_CSSCLASS>formInputcolumn</DATA_CELL_CSSCLASS>
    <ONCLICK_HANDLER></ONCLICK_HANDLER>
    <POSTBACK_URL></POSTBACK_URL>
    <CALLBACK_URL></CALLBACK_URL>
    <SKIN_ID></SKIN_ID>
    <TOOLTIP>Enter Tare Weight</TOOLTIP>
    <BTN_USESUBMIT_BEHAVIOUR></BTN_USESUBMIT_BEHAVIOUR>
    <VISIBLE>true</VISIBLE>
    <READONLY>false</READONLY>
    <ENABLE_VIEWSTATE>true</ENABLE_VIEWSTATE>
    <MAXLENGTH>3</MAXLENGTH>
    <MULTILINE></MULTILINE>
    <WIDTH></WIDTH>
    <HEIGHT></HEIGHT>
    <SECTION_NAME></SECTION_NAME>
    <ONKEY_HANDLER></ONKEY_HANDLER>
    <ONBLUR_HANDLER></ONBLUR_HANDLER>
    <ENABLE_REQUIREVALIDATION>true</ENABLE_REQUIREVALIDATION>
    <REQUIRED_FIELD_MESSAGE>Tare Weight can not be blank and should be greater than or equal to 1.</REQUIRED_FIELD_MESSAGE>
    <LOOKUP_NAME></LOOKUP_NAME>
    <IMAGE_URL></IMAGE_URL>
    <CONTROL_TOTAL></CONTROL_TOTAL>
    <TAB_INDEX>5</TAB_INDEX>
    <TEXT_TYPE>DECIMAL2</TEXT_TYPE>
    <ALLOWCHAR></ALLOWCHAR>
    <DATA_VALIDATE>required,min[1]</DATA_VALIDATE>
  </WebFormDefinition>
   <WebFormDefinition>
    <DETAIL_ID>6</DETAIL_ID>
    <FORM_ID>731</FORM_ID>
    <HTML_CONTROL_ID>PivotWeight</HTML_CONTROL_ID>
    <DISPLAY_ORDER>6</DISPLAY_ORDER>
    <ASSEMBLY_NAME>HTML.TextBox</ASSEMBLY_NAME>
    <LABEL_CELL_TEXT>Pivot Weight</LABEL_CELL_TEXT>
    <LABEL_CELL_CSSCLASS>formlabel</LABEL_CELL_CSSCLASS>
    <DATA_FIELDNAME>PivotWeight</DATA_FIELDNAME>
    <DATA_FIELD_CSSCLASS></DATA_FIELD_CSSCLASS>
    <DATA_CELL_CSSCLASS>formInputcolumn</DATA_CELL_CSSCLASS>
    <ONCLICK_HANDLER></ONCLICK_HANDLER>
    <POSTBACK_URL></POSTBACK_URL>
    <CALLBACK_URL></CALLBACK_URL>
    <SKIN_ID></SKIN_ID>
    <TOOLTIP>Enter Pivot Weight</TOOLTIP>
    <BTN_USESUBMIT_BEHAVIOUR></BTN_USESUBMIT_BEHAVIOUR>
    <VISIBLE>true</VISIBLE>
    <READONLY>false</READONLY>
    <ENABLE_VIEWSTATE>true</ENABLE_VIEWSTATE>
    <MAXLENGTH>5</MAXLENGTH>
    <MULTILINE></MULTILINE>
    <WIDTH></WIDTH>
    <HEIGHT></HEIGHT>
    <SECTION_NAME></SECTION_NAME>
    <ONKEY_HANDLER></ONKEY_HANDLER>
    <ONBLUR_HANDLER></ONBLUR_HANDLER>
    <ENABLE_REQUIREVALIDATION>false</ENABLE_REQUIREVALIDATION>
    <REQUIRED_FIELD_MESSAGE></REQUIRED_FIELD_MESSAGE>
    <LOOKUP_NAME></LOOKUP_NAME>
    <IMAGE_URL></IMAGE_URL>
    <CONTROL_TOTAL></CONTROL_TOTAL>
    <TAB_INDEX>6</TAB_INDEX>
    <TEXT_TYPE>DECIMAL3</TEXT_TYPE>
    <ALLOWCHAR></ALLOWCHAR>
    <DATA_VALIDATE></DATA_VALIDATE>
  </WebFormDefinition>
  

  <WebFormDefinition>
    <DETAIL_ID>7</DETAIL_ID>
    <FORM_ID>731</FORM_ID>
    <HTML_CONTROL_ID>GrossWeight</HTML_CONTROL_ID>
    <DISPLAY_ORDER>7</DISPLAY_ORDER>
    <ASSEMBLY_NAME>HTML.TextBox</ASSEMBLY_NAME>
    <LABEL_CELL_TEXT>Gross Weight</LABEL_CELL_TEXT>
    <LABEL_CELL_CSSCLASS>formlabel</LABEL_CELL_CSSCLASS>
    <DATA_FIELDNAME>GrossWeight</DATA_FIELDNAME>
    <DATA_FIELD_CSSCLASS></DATA_FIELD_CSSCLASS>
    <DATA_CELL_CSSCLASS>formInputcolumn</DATA_CELL_CSSCLASS>
    <ONCLICK_HANDLER></ONCLICK_HANDLER>
    <POSTBACK_URL></POSTBACK_URL>
    <CALLBACK_URL></CALLBACK_URL>
    <SKIN_ID></SKIN_ID>
    <TOOLTIP>Enter Gross Weight</TOOLTIP>
    <BTN_USESUBMIT_BEHAVIOUR></BTN_USESUBMIT_BEHAVIOUR>
    <VISIBLE>true</VISIBLE>
    <READONLY>false</READONLY>
    <ENABLE_VIEWSTATE>true</ENABLE_VIEWSTATE>
    <MAXLENGTH>5</MAXLENGTH>
    <MULTILINE></MULTILINE>
    <WIDTH></WIDTH>
    <HEIGHT></HEIGHT>
    <SECTION_NAME></SECTION_NAME>
    <ONKEY_HANDLER></ONKEY_HANDLER>
    <ONBLUR_HANDLER></ONBLUR_HANDLER>
    <ENABLE_REQUIREVALIDATION>true</ENABLE_REQUIREVALIDATION>
    <REQUIRED_FIELD_MESSAGE>Gross Weight can not be blank and should be greater than or equal to 1.</REQUIRED_FIELD_MESSAGE>
    <LOOKUP_NAME></LOOKUP_NAME>
    <IMAGE_URL></IMAGE_URL>
    <CONTROL_TOTAL></CONTROL_TOTAL>
    <TAB_INDEX>7</TAB_INDEX>
    <TEXT_TYPE>DECIMAL3</TEXT_TYPE>
    <ALLOWCHAR></ALLOWCHAR>
    <DATA_VALIDATE>required,min[1]</DATA_VALIDATE>
  </WebFormDefinition>

  <WebFormDefinition>
    <DETAIL_ID>8</DETAIL_ID>
    <FORM_ID>731</FORM_ID>
    <HTML_CONTROL_ID>VolumeWeight</HTML_CONTROL_ID>
    <DISPLAY_ORDER>8</DISPLAY_ORDER>
    <ASSEMBLY_NAME>HTML.TextBox</ASSEMBLY_NAME>
    <LABEL_CELL_TEXT>Vol(CBM)</LABEL_CELL_TEXT>
    <LABEL_CELL_CSSCLASS>formlabel</LABEL_CELL_CSSCLASS>
    <DATA_FIELDNAME>VolumeWeight</DATA_FIELDNAME>
    <DATA_FIELD_CSSCLASS></DATA_FIELD_CSSCLASS>
    <DATA_CELL_CSSCLASS>formInputcolumn</DATA_CELL_CSSCLASS>
    <ONCLICK_HANDLER></ONCLICK_HANDLER>
    <POSTBACK_URL></POSTBACK_URL>
    <CALLBACK_URL></CALLBACK_URL>
    <SKIN_ID></SKIN_ID>
    <TOOLTIP>Enter Volume</TOOLTIP>
    <BTN_USESUBMIT_BEHAVIOUR></BTN_USESUBMIT_BEHAVIOUR>
    <VISIBLE>true</VISIBLE>
    <READONLY>false</READONLY>
    <ENABLE_VIEWSTATE>true</ENABLE_VIEWSTATE>
    <MAXLENGTH>5</MAXLENGTH>
    <MULTILINE></MULTILINE>
    <WIDTH></WIDTH>
    <HEIGHT></HEIGHT>
    <SECTION_NAME></SECTION_NAME>
    <ONKEY_HANDLER></ONKEY_HANDLER>
    <ONBLUR_HANDLER></ONBLUR_HANDLER>
    <ENABLE_REQUIREVALIDATION>TRUE</ENABLE_REQUIREVALIDATION>
    <REQUIRED_FIELD_MESSAGE>Volume can not be blank and should be greater than or equal to 1.</REQUIRED_FIELD_MESSAGE>
    <LOOKUP_NAME></LOOKUP_NAME>
    <IMAGE_URL></IMAGE_URL>
    <CONTROL_TOTAL></CONTROL_TOTAL>
    <TAB_INDEX>8</TAB_INDEX>
    <TEXT_TYPE>DECIMAL3</TEXT_TYPE>
    <ALLOWCHAR></ALLOWCHAR>
    <DATA_VALIDATE>required,min[1]</DATA_VALIDATE>
  </WebFormDefinition>



  <WebFormDefinition>
    <DETAIL_ID>9</DETAIL_ID>
    <FORM_ID>731</FORM_ID>
    <HTML_CONTROL_ID>Unit</HTML_CONTROL_ID>
    <DISPLAY_ORDER>9</DISPLAY_ORDER>
    <ASSEMBLY_NAME>HTML.RadioButtonList</ASSEMBLY_NAME>
    <LABEL_CELL_TEXT>Measurement Unit</LABEL_CELL_TEXT>
    <LABEL_CELL_CSSCLASS>formlabel</LABEL_CELL_CSSCLASS>
    <DATA_FIELDNAME>Unit</DATA_FIELDNAME>
    <DATA_FIELD_CSSCLASS></DATA_FIELD_CSSCLASS>
    <DATA_CELL_CSSCLASS>formInputcolumn</DATA_CELL_CSSCLASS>
    <ONCLICK_HANDLER></ONCLICK_HANDLER>
    <POSTBACK_URL></POSTBACK_URL>
    <CALLBACK_URL></CALLBACK_URL>
    <SKIN_ID></SKIN_ID>
    <TOOLTIP>Select Measurement Unit</TOOLTIP>
    <BTN_USESUBMIT_BEHAVIOUR></BTN_USESUBMIT_BEHAVIOUR>
    <VISIBLE>true</VISIBLE>
    <READONLY>false</READONLY>
    <ENABLE_VIEWSTATE>true</ENABLE_VIEWSTATE>
    <MAXLENGTH>100</MAXLENGTH>
    <MULTILINE></MULTILINE>
    <WIDTH>175</WIDTH>
    <HEIGHT></HEIGHT>
    <SECTION_NAME></SECTION_NAME>
    <ONKEY_HANDLER></ONKEY_HANDLER>
    <ONBLUR_HANDLER></ONBLUR_HANDLER>
    <ENABLE_REQUIREVALIDATION></ENABLE_REQUIREVALIDATION>
    <REQUIRED_FIELD_MESSAGE>Measurement Unit can not be blank</REQUIRED_FIELD_MESSAGE>
    <LOOKUP_NAME></LOOKUP_NAME>
    <IMAGE_URL></IMAGE_URL>
    <CONTROL_TOTAL></CONTROL_TOTAL>
    <TAB_INDEX>9</TAB_INDEX>
    <DATA_VALIDATE></DATA_VALIDATE>
    <TEXT_TYPE>ENUM.MEASUREMENTUNIT</TEXT_TYPE>
    <ALLOWCHAR></ALLOWCHAR>
  </WebFormDefinition>

  <WebFormDefinition>
    <DETAIL_ID>10</DETAIL_ID>
    <FORM_ID>731</FORM_ID>
    <HTML_CONTROL_ID>Length</HTML_CONTROL_ID>
    <DISPLAY_ORDER>10</DISPLAY_ORDER>
    <ASSEMBLY_NAME>HTML.TextBox</ASSEMBLY_NAME>
    <LABEL_CELL_TEXT>Length</LABEL_CELL_TEXT>
    <LABEL_CELL_CSSCLASS>formlabel</LABEL_CELL_CSSCLASS>
    <DATA_FIELDNAME>Length</DATA_FIELDNAME>
    <DATA_FIELD_CSSCLASS></DATA_FIELD_CSSCLASS>
    <DATA_CELL_CSSCLASS>formInputcolumn</DATA_CELL_CSSCLASS>
    <ONCLICK_HANDLER></ONCLICK_HANDLER>
    <POSTBACK_URL></POSTBACK_URL>
    <CALLBACK_URL></CALLBACK_URL>
    <SKIN_ID></SKIN_ID>
    <TOOLTIP>Enter Length</TOOLTIP>
    <BTN_USESUBMIT_BEHAVIOUR></BTN_USESUBMIT_BEHAVIOUR>
    <VISIBLE>true</VISIBLE>
    <READONLY>false</READONLY>
    <ENABLE_VIEWSTATE>true</ENABLE_VIEWSTATE>
    <MAXLENGTH>5</MAXLENGTH>
    <MULTILINE></MULTILINE>
    <WIDTH></WIDTH>
    <HEIGHT></HEIGHT>
    <SECTION_NAME></SECTION_NAME>
    <ONKEY_HANDLER></ONKEY_HANDLER>
    <ONBLUR_HANDLER></ONBLUR_HANDLER>
    <ENABLE_REQUIREVALIDATION>true</ENABLE_REQUIREVALIDATION>
    <REQUIRED_FIELD_MESSAGE>Length can not be blank and should be greater than or equal to 1.</REQUIRED_FIELD_MESSAGE>
    <LOOKUP_NAME></LOOKUP_NAME>
    <IMAGE_URL></IMAGE_URL>
    <CONTROL_TOTAL></CONTROL_TOTAL>
    <TAB_INDEX>10</TAB_INDEX>
    <TEXT_TYPE>DECIMAL3</TEXT_TYPE>
    <ALLOWCHAR></ALLOWCHAR>
    <DATA_VALIDATE>required,min[1]</DATA_VALIDATE>
  </WebFormDefinition>

  <WebFormDefinition>
    <DETAIL_ID>11</DETAIL_ID>
    <FORM_ID>731</FORM_ID>
    <HTML_CONTROL_ID>Width</HTML_CONTROL_ID>
    <DISPLAY_ORDER>11</DISPLAY_ORDER>
    <ASSEMBLY_NAME>HTML.TextBox</ASSEMBLY_NAME>
    <LABEL_CELL_TEXT>Width</LABEL_CELL_TEXT>
    <LABEL_CELL_CSSCLASS>formlabel</LABEL_CELL_CSSCLASS>
    <DATA_FIELDNAME>Width</DATA_FIELDNAME>
    <DATA_FIELD_CSSCLASS></DATA_FIELD_CSSCLASS>
    <DATA_CELL_CSSCLASS>formInputcolumn</DATA_CELL_CSSCLASS>
    <ONCLICK_HANDLER></ONCLICK_HANDLER>
    <POSTBACK_URL></POSTBACK_URL>
    <CALLBACK_URL></CALLBACK_URL>
    <SKIN_ID></SKIN_ID>
    <TOOLTIP>Enter Width</TOOLTIP>
    <BTN_USESUBMIT_BEHAVIOUR></BTN_USESUBMIT_BEHAVIOUR>
    <VISIBLE>true</VISIBLE>
    <READONLY>false</READONLY>
    <ENABLE_VIEWSTATE>true</ENABLE_VIEWSTATE>
    <MAXLENGTH>5</MAXLENGTH>
    <MULTILINE></MULTILINE>
    <WIDTH></WIDTH>
    <HEIGHT></HEIGHT>
    <SECTION_NAME></SECTION_NAME>
    <ONKEY_HANDLER></ONKEY_HANDLER>
    <ONBLUR_HANDLER></ONBLUR_HANDLER>
    <ENABLE_REQUIREVALIDATION>true</ENABLE_REQUIREVALIDATION>
    <REQUIRED_FIELD_MESSAGE>Width can not be blank and should be greater than or equal to 1.</REQUIRED_FIELD_MESSAGE>
    <LOOKUP_NAME></LOOKUP_NAME>
    <IMAGE_URL></IMAGE_URL>
    <CONTROL_TOTAL></CONTROL_TOTAL>
    <TAB_INDEX>11</TAB_INDEX>
    <TEXT_TYPE>DECIMAL3</TEXT_TYPE>
    <ALLOWCHAR></ALLOWCHAR>
    <DATA_VALIDATE>required,min[1]</DATA_VALIDATE>
  </WebFormDefinition>

  <WebFormDefinition>
    <DETAIL_ID>12</DETAIL_ID>
    <FORM_ID>731</FORM_ID>
    <HTML_CONTROL_ID>Height</HTML_CONTROL_ID>
    <DISPLAY_ORDER>12</DISPLAY_ORDER>
    <ASSEMBLY_NAME>HTML.TextBox</ASSEMBLY_NAME>
    <LABEL_CELL_TEXT>Height</LABEL_CELL_TEXT>
    <LABEL_CELL_CSSCLASS>formlabel</LABEL_CELL_CSSCLASS>
    <DATA_FIELDNAME>Height</DATA_FIELDNAME>
    <DATA_FIELD_CSSCLASS></DATA_FIELD_CSSCLASS>
    <DATA_CELL_CSSCLASS>formInputcolumn</DATA_CELL_CSSCLASS>
    <ONCLICK_HANDLER></ONCLICK_HANDLER>
    <POSTBACK_URL></POSTBACK_URL>
    <CALLBACK_URL></CALLBACK_URL>
    <SKIN_ID></SKIN_ID>
    <TOOLTIP>Height</TOOLTIP>
    <BTN_USESUBMIT_BEHAVIOUR></BTN_USESUBMIT_BEHAVIOUR>
    <VISIBLE>true</VISIBLE>
    <READONLY>false</READONLY>
    <ENABLE_VIEWSTATE>true</ENABLE_VIEWSTATE>
    <MAXLENGTH>5</MAXLENGTH>
    <MULTILINE></MULTILINE>
    <WIDTH></WIDTH>
    <HEIGHT></HEIGHT>
    <SECTION_NAME></SECTION_NAME>
    <ONKEY_HANDLER></ONKEY_HANDLER>
    <ONBLUR_HANDLER></ONBLUR_HANDLER>
    <ENABLE_REQUIREVALIDATION>false</ENABLE_REQUIREVALIDATION>
    <REQUIRED_FIELD_MESSAGE>Height should be greater than or equal to 1.</REQUIRED_FIELD_MESSAGE>
    <LOOKUP_NAME></LOOKUP_NAME>
    <IMAGE_URL></IMAGE_URL>
    <CONTROL_TOTAL></CONTROL_TOTAL>
    <TAB_INDEX>12</TAB_INDEX>
    <TEXT_TYPE>DECIMAL2</TEXT_TYPE>
    <ALLOWCHAR></ALLOWCHAR>
    <DATA_VALIDATE>min[1]</DATA_VALIDATE>
  </WebFormDefinition>

  <WebFormDefinition>
    <DETAIL_ID>13</DETAIL_ID>
    <FORM_ID>731</FORM_ID>
    <HTML_CONTROL_ID>ULDDescription</HTML_CONTROL_ID>
    <DISPLAY_ORDER>13</DISPLAY_ORDER>
    <ASSEMBLY_NAME>HTML.TextBox</ASSEMBLY_NAME>
    <LABEL_CELL_TEXT>ULD Description</LABEL_CELL_TEXT>
    <LABEL_CELL_CSSCLASS>formlabel</LABEL_CELL_CSSCLASS>
    <DATA_FIELDNAME>ULDdescription</DATA_FIELDNAME>
    <DATA_FIELD_CSSCLASS></DATA_FIELD_CSSCLASS>
    <DATA_CELL_CSSCLASS>formInputcolumn</DATA_CELL_CSSCLASS>
    <ONCLICK_HANDLER></ONCLICK_HANDLER>
    <POSTBACK_URL></POSTBACK_URL>
    <CALLBACK_URL></CALLBACK_URL>
    <SKIN_ID></SKIN_ID>
    <TOOLTIP>Enter ULD Description</TOOLTIP>
    <BTN_USESUBMIT_BEHAVIOUR></BTN_USESUBMIT_BEHAVIOUR>
    <VISIBLE>true</VISIBLE>
    <READONLY>false</READONLY>
    <ENABLE_VIEWSTATE>true</ENABLE_VIEWSTATE>
    <MAXLENGTH>200</MAXLENGTH>
    <MULTILINE>YES</MULTILINE>
    <WIDTH>200</WIDTH>
    <HEIGHT></HEIGHT>
    <SECTION_NAME></SECTION_NAME>
    <ONKEY_HANDLER></ONKEY_HANDLER>
    <ONBLUR_HANDLER></ONBLUR_HANDLER>
    <ENABLE_REQUIREVALIDATION>false</ENABLE_REQUIREVALIDATION>
    <REQUIRED_FIELD_MESSAGE>ULD Description can not be blank</REQUIRED_FIELD_MESSAGE>
    <LOOKUP_NAME></LOOKUP_NAME>
    <IMAGE_URL></IMAGE_URL>
    <CONTROL_TOTAL></CONTROL_TOTAL>
    <TAB_INDEX>13</TAB_INDEX>
    <TEXT_TYPE>ALPHANUMERICUPPER</TEXT_TYPE>
    <ALLOWCHAR></ALLOWCHAR>
    <DATA_VALIDATE></DATA_VALIDATE>
  </WebFormDefinition>

  <WebFormDefinition>
    <DETAIL_ID>14</DETAIL_ID>
    <FORM_ID>731</FORM_ID>
    <HTML_CONTROL_ID>IsActive</HTML_CONTROL_ID>
    <DISPLAY_ORDER>14</DISPLAY_ORDER>
    <ASSEMBLY_NAME>HTML.RadioButtonList</ASSEMBLY_NAME>
    <LABEL_CELL_TEXT>Active</LABEL_CELL_TEXT>
    <LABEL_CELL_CSSCLASS>formlabel</LABEL_CELL_CSSCLASS>
    <DATA_FIELDNAME>IsActive</DATA_FIELDNAME>
    <DATA_FIELD_CSSCLASS></DATA_FIELD_CSSCLASS>
    <DATA_CELL_CSSCLASS>formInputcolumn</DATA_CELL_CSSCLASS>
    <ONCLICK_HANDLER></ONCLICK_HANDLER>
    <POSTBACK_URL></POSTBACK_URL>
    <CALLBACK_URL></CALLBACK_URL>
    <SKIN_ID></SKIN_ID>
    <TOOLTIP>Select Active</TOOLTIP>
    <BTN_USESUBMIT_BEHAVIOUR></BTN_USESUBMIT_BEHAVIOUR>
    <VISIBLE>true</VISIBLE>
    <READONLY>false</READONLY>
    <ENABLE_VIEWSTATE>true</ENABLE_VIEWSTATE>
    <MAXLENGTH></MAXLENGTH>
    <MULTILINE></MULTILINE>
    <WIDTH></WIDTH>
    <HEIGHT></HEIGHT>
    <SECTION_NAME></SECTION_NAME>
    <ONKEY_HANDLER></ONKEY_HANDLER>
    <ONBLUR_HANDLER></ONBLUR_HANDLER>
    <ENABLE_REQUIREVALIDATION>false</ENABLE_REQUIREVALIDATION>
    <REQUIRED_FIELD_MESSAGE>Active can not be blank</REQUIRED_FIELD_MESSAGE>
    <LOOKUP_NAME></LOOKUP_NAME>
    <IMAGE_URL></IMAGE_URL>
    <CONTROL_TOTAL></CONTROL_TOTAL>
    <TAB_INDEX>14</TAB_INDEX>
    <TEXT_TYPE>ENUM.ACTIVE</TEXT_TYPE>
    <ALLOWCHAR></ALLOWCHAR>
    <DATA_VALIDATE></DATA_VALIDATE>
  </WebFormDefinition>

  <WebFormDefinition>
    <DETAIL_ID>15</DETAIL_ID>
    <FORM_ID>731</FORM_ID>
    <HTML_CONTROL_ID>CommonDesignation</HTML_CONTROL_ID>
    <DISPLAY_ORDER>15</DISPLAY_ORDER>
    <ASSEMBLY_NAME>HTML.TextBox</ASSEMBLY_NAME>
    <LABEL_CELL_TEXT>Common Designation</LABEL_CELL_TEXT>
    <LABEL_CELL_CSSCLASS>formlabel</LABEL_CELL_CSSCLASS>
    <DATA_FIELDNAME>CommonDesignation</DATA_FIELDNAME>
    <DATA_FIELD_CSSCLASS></DATA_FIELD_CSSCLASS>
    <DATA_CELL_CSSCLASS>formInputcolumn</DATA_CELL_CSSCLASS>
    <ONCLICK_HANDLER></ONCLICK_HANDLER>
    <POSTBACK_URL></POSTBACK_URL>
    <CALLBACK_URL></CALLBACK_URL>
    <SKIN_ID></SKIN_ID>
    <TOOLTIP>Enter Common Designation</TOOLTIP>
    <BTN_USESUBMIT_BEHAVIOUR></BTN_USESUBMIT_BEHAVIOUR>
    <VISIBLE>true</VISIBLE>
    <READONLY>false</READONLY>
    <ENABLE_VIEWSTATE>true</ENABLE_VIEWSTATE>
    <MAXLENGTH>49</MAXLENGTH>
    <MULTILINE>YES</MULTILINE>
    <WIDTH>200</WIDTH>
    <HEIGHT></HEIGHT>
    <SECTION_NAME></SECTION_NAME>
    <ONKEY_HANDLER></ONKEY_HANDLER>
    <ONBLUR_HANDLER></ONBLUR_HANDLER>
    <ENABLE_REQUIREVALIDATION>false</ENABLE_REQUIREVALIDATION>
    <REQUIRED_FIELD_MESSAGE>Common Designation can not be blank</REQUIRED_FIELD_MESSAGE>
    <LOOKUP_NAME></LOOKUP_NAME>
    <IMAGE_URL></IMAGE_URL>
    <CONTROL_TOTAL></CONTROL_TOTAL>
    <TAB_INDEX>15</TAB_INDEX>
    <TEXT_TYPE>UPPERCASE</TEXT_TYPE>
    <ALLOWCHAR></ALLOWCHAR>
    <DATA_VALIDATE></DATA_VALIDATE>
  </WebFormDefinition>

  <!--END-->

  <!--Edit ULD Type Details-->

  <WebFormDefinition>
    <DETAIL_ID>1</DETAIL_ID>
    <FORM_ID>732</FORM_ID>
    <HTML_CONTROL_ID>ULDCode</HTML_CONTROL_ID>
    <DISPLAY_ORDER>1</DISPLAY_ORDER>
    <ASSEMBLY_NAME>HTML.Label</ASSEMBLY_NAME>
    <LABEL_CELL_TEXT>ULD Code</LABEL_CELL_TEXT>
    <LABEL_CELL_CSSCLASS>formlabel</LABEL_CELL_CSSCLASS>
    <DATA_FIELDNAME>ULDCode</DATA_FIELDNAME>
    <DATA_FIELD_CSSCLASS></DATA_FIELD_CSSCLASS>
    <DATA_CELL_CSSCLASS>formInputcolumn</DATA_CELL_CSSCLASS>
    <ONCLICK_HANDLER></ONCLICK_HANDLER>
    <POSTBACK_URL></POSTBACK_URL>
    <CALLBACK_URL></CALLBACK_URL>
    <SKIN_ID></SKIN_ID>
    <TOOLTIP>ULD Code</TOOLTIP>
    <BTN_USESUBMIT_BEHAVIOUR></BTN_USESUBMIT_BEHAVIOUR>
    <VISIBLE>true</VISIBLE>
    <READONLY>true</READONLY>
    <ENABLE_VIEWSTATE>true</ENABLE_VIEWSTATE>
    <MAXLENGTH></MAXLENGTH>
    <MULTILINE></MULTILINE>
    <WIDTH></WIDTH>
    <HEIGHT></HEIGHT>
    <SECTION_NAME>ULD Code Information</SECTION_NAME>
    <ONKEY_HANDLER></ONKEY_HANDLER>
    <ONBLUR_HANDLER></ONBLUR_HANDLER>
    <ENABLE_REQUIREVALIDATION>false</ENABLE_REQUIREVALIDATION>
    <REQUIRED_FIELD_MESSAGE></REQUIRED_FIELD_MESSAGE>
    <LOOKUP_NAME></LOOKUP_NAME>
    <IMAGE_URL></IMAGE_URL>
    <CONTROL_TOTAL></CONTROL_TOTAL>
    <TAB_INDEX>1</TAB_INDEX>
    <TEXT_TYPE>UPPERCASE</TEXT_TYPE>
    <ALLOWCHAR></ALLOWCHAR>
    <DATA_VALIDATE></DATA_VALIDATE>
  </WebFormDefinition>



  <WebFormDefinition>
    <DETAIL_ID>2</DETAIL_ID>
    <FORM_ID>732</FORM_ID>
    <HTML_CONTROL_ID>AirlineSno</HTML_CONTROL_ID>
    <DISPLAY_ORDER>2</DISPLAY_ORDER>
    <ASSEMBLY_NAME>HTML.AutoCompleteTextBox</ASSEMBLY_NAME>
    <LABEL_CELL_TEXT>Airline</LABEL_CELL_TEXT>
    <LABEL_CELL_CSSCLASS>formlabel</LABEL_CELL_CSSCLASS>
    <DATA_FIELDNAME>AirlineSno</DATA_FIELDNAME>
    <DATA_FIELD_CSSCLASS></DATA_FIELD_CSSCLASS>
    <DATA_CELL_CSSCLASS>formInputcolumn</DATA_CELL_CSSCLASS>
    <ONCLICK_HANDLER></ONCLICK_HANDLER>
    <POSTBACK_URL></POSTBACK_URL>
    <CALLBACK_URL></CALLBACK_URL>
    <SKIN_ID></SKIN_ID>
    <TOOLTIP>Enter Airline</TOOLTIP>
    <BTN_USESUBMIT_BEHAVIOUR></BTN_USESUBMIT_BEHAVIOUR>
    <VISIBLE>true</VISIBLE>
    <READONLY>false</READONLY>
    <ENABLE_VIEWSTATE>true</ENABLE_VIEWSTATE>
    <MAXLENGTH></MAXLENGTH>
    <MULTILINE></MULTILINE>
    <WIDTH>200</WIDTH>
    <HEIGHT></HEIGHT>
    <SECTION_NAME></SECTION_NAME>
    <ONKEY_HANDLER></ONKEY_HANDLER>
    <ONBLUR_HANDLER></ONBLUR_HANDLER>
    <ENABLE_REQUIREVALIDATION>true</ENABLE_REQUIREVALIDATION>
    <REQUIRED_FIELD_MESSAGE>Airline can not be blank</REQUIRED_FIELD_MESSAGE>
    <LOOKUP_NAME></LOOKUP_NAME>
    <IMAGE_URL></IMAGE_URL>
    <CONTROL_TOTAL></CONTROL_TOTAL>
    <TAB_INDEX>2</TAB_INDEX>
    <TEXT_TYPE>UPPERCASE</TEXT_TYPE>
    <ALLOWCHAR></ALLOWCHAR>
    <DATA_VALIDATE>required</DATA_VALIDATE>
  </WebFormDefinition>

  <WebFormDefinition>
    <DETAIL_ID>3</DETAIL_ID>
    <FORM_ID>732</FORM_ID>
    <HTML_CONTROL_ID>RateClassSno</HTML_CONTROL_ID>
    <DISPLAY_ORDER>3</DISPLAY_ORDER>
    <ASSEMBLY_NAME>HTML.AutoCompleteTextBox</ASSEMBLY_NAME>
    <LABEL_CELL_TEXT>ULD Class</LABEL_CELL_TEXT>
    <LABEL_CELL_CSSCLASS>formlabel</LABEL_CELL_CSSCLASS>
    <DATA_FIELDNAME>RateClassSno</DATA_FIELDNAME>
    <DATA_FIELD_CSSCLASS></DATA_FIELD_CSSCLASS>
    <DATA_CELL_CSSCLASS>formInputcolumn</DATA_CELL_CSSCLASS>
    <ONCLICK_HANDLER></ONCLICK_HANDLER>
    <POSTBACK_URL></POSTBACK_URL>
    <CALLBACK_URL></CALLBACK_URL>
    <SKIN_ID></SKIN_ID>
    <TOOLTIP>Ente ULD Class</TOOLTIP>
    <BTN_USESUBMIT_BEHAVIOUR></BTN_USESUBMIT_BEHAVIOUR>
    <VISIBLE>true</VISIBLE>
    <READONLY>false</READONLY>
    <ENABLE_VIEWSTATE>true</ENABLE_VIEWSTATE>
    <MAXLENGTH></MAXLENGTH>
    <MULTILINE></MULTILINE>
    <WIDTH>100</WIDTH>
    <HEIGHT></HEIGHT>
    <SECTION_NAME></SECTION_NAME>
    <ONKEY_HANDLER></ONKEY_HANDLER>
    <ONBLUR_HANDLER></ONBLUR_HANDLER>
    <ENABLE_REQUIREVALIDATION>true</ENABLE_REQUIREVALIDATION>
    <REQUIRED_FIELD_MESSAGE>ULD Class can not be blank</REQUIRED_FIELD_MESSAGE>
    <LOOKUP_NAME></LOOKUP_NAME>
    <IMAGE_URL></IMAGE_URL>
    <CONTROL_TOTAL></CONTROL_TOTAL>
    <TAB_INDEX>3</TAB_INDEX>
    <TEXT_TYPE>UPPERCASE</TEXT_TYPE>
    <ALLOWCHAR></ALLOWCHAR>
    <DATA_VALIDATE>required</DATA_VALIDATE>
  </WebFormDefinition>


  <WebFormDefinition>
    <DETAIL_ID>4</DETAIL_ID>
    <FORM_ID>732</FORM_ID>
    <HTML_CONTROL_ID>IsULdtype</HTML_CONTROL_ID>
    <DISPLAY_ORDER>4</DISPLAY_ORDER>
    <ASSEMBLY_NAME>HTML.RadioButtonList</ASSEMBLY_NAME>
    <LABEL_CELL_TEXT>ULD Types</LABEL_CELL_TEXT>
    <LABEL_CELL_CSSCLASS>formlabel</LABEL_CELL_CSSCLASS>
    <DATA_FIELDNAME>IsULdtype</DATA_FIELDNAME>
    <DATA_FIELD_CSSCLASS></DATA_FIELD_CSSCLASS>
    <DATA_CELL_CSSCLASS>formInputcolumn</DATA_CELL_CSSCLASS>
    <ONCLICK_HANDLER></ONCLICK_HANDLER>
    <POSTBACK_URL></POSTBACK_URL>
    <CALLBACK_URL></CALLBACK_URL>
    <SKIN_ID></SKIN_ID>
    <TOOLTIP>ULD Types</TOOLTIP>
    <BTN_USESUBMIT_BEHAVIOUR>true</BTN_USESUBMIT_BEHAVIOUR>
    <VISIBLE>true</VISIBLE>
    <READONLY>true</READONLY>
    <ENABLE_VIEWSTATE>true</ENABLE_VIEWSTATE>
    <MAXLENGTH></MAXLENGTH>
    <MULTILINE></MULTILINE>
    <WIDTH></WIDTH>
    <HEIGHT></HEIGHT>
    <SECTION_NAME></SECTION_NAME>
    <ONKEY_HANDLER></ONKEY_HANDLER>
    <ONBLUR_HANDLER></ONBLUR_HANDLER>
    <ENABLE_REQUIREVALIDATION>True</ENABLE_REQUIREVALIDATION>
    <REQUIRED_FIELD_MESSAGE>>ULD Types can not be blank</REQUIRED_FIELD_MESSAGE>
    <LOOKUP_NAME></LOOKUP_NAME>
    <IMAGE_URL></IMAGE_URL>
    <CONTROL_TOTAL></CONTROL_TOTAL>
    <TAB_INDEX>4</TAB_INDEX>
    <TEXT_TYPE>ENUM.ULDTYPES</TEXT_TYPE>
    <ALLOWCHAR></ALLOWCHAR>
    <DATA_VALIDATE>required</DATA_VALIDATE>
  </WebFormDefinition>

  <WebFormDefinition>
    <DETAIL_ID>5</DETAIL_ID>
    <FORM_ID>732</FORM_ID>
    <HTML_CONTROL_ID>EmptyWeight</HTML_CONTROL_ID>
    <DISPLAY_ORDER>5</DISPLAY_ORDER>
    <ASSEMBLY_NAME>HTML.TextBox</ASSEMBLY_NAME>
    <LABEL_CELL_TEXT>Tare Weight</LABEL_CELL_TEXT>
    <LABEL_CELL_CSSCLASS>formlabel</LABEL_CELL_CSSCLASS>
    <DATA_FIELDNAME>EmptyWeight</DATA_FIELDNAME>
    <DATA_FIELD_CSSCLASS></DATA_FIELD_CSSCLASS>
    <DATA_CELL_CSSCLASS>formInputcolumn</DATA_CELL_CSSCLASS>
    <ONCLICK_HANDLER></ONCLICK_HANDLER>
    <POSTBACK_URL></POSTBACK_URL>
    <CALLBACK_URL></CALLBACK_URL>
    <SKIN_ID></SKIN_ID>
    <TOOLTIP>Enter Tare Weight</TOOLTIP>
    <BTN_USESUBMIT_BEHAVIOUR></BTN_USESUBMIT_BEHAVIOUR>
    <VISIBLE>true</VISIBLE>
    <READONLY>false</READONLY>
    <ENABLE_VIEWSTATE>true</ENABLE_VIEWSTATE>
    <MAXLENGTH>3</MAXLENGTH>
    <MULTILINE></MULTILINE>
    <WIDTH></WIDTH>
    <HEIGHT></HEIGHT>
    <SECTION_NAME></SECTION_NAME>
    <ONKEY_HANDLER></ONKEY_HANDLER>
    <ONBLUR_HANDLER></ONBLUR_HANDLER>
    <ENABLE_REQUIREVALIDATION>true</ENABLE_REQUIREVALIDATION>
    <REQUIRED_FIELD_MESSAGE>Tare Weight can not be blank and should be greater than or equal to 1.</REQUIRED_FIELD_MESSAGE>
    <LOOKUP_NAME></LOOKUP_NAME>
    <IMAGE_URL></IMAGE_URL>
    <CONTROL_TOTAL></CONTROL_TOTAL>
    <TAB_INDEX>5</TAB_INDEX>
    <TEXT_TYPE>DECIMAL2</TEXT_TYPE>
    <ALLOWCHAR></ALLOWCHAR>
    <DATA_VALIDATE>required,min[1]</DATA_VALIDATE>
  </WebFormDefinition>


  <WebFormDefinition>
    <DETAIL_ID>6</DETAIL_ID>
    <FORM_ID>732</FORM_ID>
    <HTML_CONTROL_ID>PivotWeight</HTML_CONTROL_ID>
    <DISPLAY_ORDER>6</DISPLAY_ORDER>
    <ASSEMBLY_NAME>HTML.TextBox</ASSEMBLY_NAME>
    <LABEL_CELL_TEXT>Pivot Weight</LABEL_CELL_TEXT>
    <LABEL_CELL_CSSCLASS>formlabel</LABEL_CELL_CSSCLASS>
    <DATA_FIELDNAME>PivotWeight</DATA_FIELDNAME>
    <DATA_FIELD_CSSCLASS></DATA_FIELD_CSSCLASS>
    <DATA_CELL_CSSCLASS>formInputcolumn</DATA_CELL_CSSCLASS>
    <ONCLICK_HANDLER></ONCLICK_HANDLER>
    <POSTBACK_URL></POSTBACK_URL>
    <CALLBACK_URL></CALLBACK_URL>
    <SKIN_ID></SKIN_ID>
    <TOOLTIP>Enter Pivot Weight</TOOLTIP>
    <BTN_USESUBMIT_BEHAVIOUR></BTN_USESUBMIT_BEHAVIOUR>
    <VISIBLE>true</VISIBLE>
    <READONLY>false</READONLY>
    <ENABLE_VIEWSTATE>true</ENABLE_VIEWSTATE>
    <MAXLENGTH>5</MAXLENGTH>
    <MULTILINE></MULTILINE>
    <WIDTH></WIDTH>
    <HEIGHT></HEIGHT>
    <SECTION_NAME></SECTION_NAME>
    <ONKEY_HANDLER></ONKEY_HANDLER>
    <ONBLUR_HANDLER></ONBLUR_HANDLER>
    <ENABLE_REQUIREVALIDATION>false</ENABLE_REQUIREVALIDATION>
    <REQUIRED_FIELD_MESSAGE></REQUIRED_FIELD_MESSAGE>
    <LOOKUP_NAME></LOOKUP_NAME>
    <IMAGE_URL></IMAGE_URL>
    <CONTROL_TOTAL></CONTROL_TOTAL>
    <TAB_INDEX>6</TAB_INDEX>
    <TEXT_TYPE>DECIMAL3</TEXT_TYPE>
    <ALLOWCHAR></ALLOWCHAR>
    <DATA_VALIDATE></DATA_VALIDATE>
  </WebFormDefinition>
  
  <WebFormDefinition>
    <DETAIL_ID>7</DETAIL_ID>
    <FORM_ID>732</FORM_ID>
    <HTML_CONTROL_ID>GrossWeight</HTML_CONTROL_ID>
    <DISPLAY_ORDER>7</DISPLAY_ORDER>
    <ASSEMBLY_NAME>HTML.TextBox</ASSEMBLY_NAME>
    <LABEL_CELL_TEXT>Gross Weight</LABEL_CELL_TEXT>
    <LABEL_CELL_CSSCLASS>formlabel</LABEL_CELL_CSSCLASS>
    <DATA_FIELDNAME>GrossWeight</DATA_FIELDNAME>
    <DATA_FIELD_CSSCLASS></DATA_FIELD_CSSCLASS>
    <DATA_CELL_CSSCLASS>formInputcolumn</DATA_CELL_CSSCLASS>
    <ONCLICK_HANDLER></ONCLICK_HANDLER>
    <POSTBACK_URL></POSTBACK_URL>
    <CALLBACK_URL></CALLBACK_URL>
    <SKIN_ID></SKIN_ID>
    <TOOLTIP>Enter Gross Weight</TOOLTIP>
    <BTN_USESUBMIT_BEHAVIOUR></BTN_USESUBMIT_BEHAVIOUR>
    <VISIBLE>true</VISIBLE>
    <READONLY>false</READONLY>
    <ENABLE_VIEWSTATE>true</ENABLE_VIEWSTATE>
    <MAXLENGTH>5</MAXLENGTH>
    <MULTILINE></MULTILINE>
    <WIDTH></WIDTH>
    <HEIGHT></HEIGHT>
    <SECTION_NAME></SECTION_NAME>
    <ONKEY_HANDLER></ONKEY_HANDLER>
    <ONBLUR_HANDLER></ONBLUR_HANDLER>
    <ENABLE_REQUIREVALIDATION>true</ENABLE_REQUIREVALIDATION>
    <REQUIRED_FIELD_MESSAGE>Gross Weight can not be blank and should be greater than or equal to 1.</REQUIRED_FIELD_MESSAGE>
    <LOOKUP_NAME></LOOKUP_NAME>
    <IMAGE_URL></IMAGE_URL>
    <CONTROL_TOTAL></CONTROL_TOTAL>
    <TAB_INDEX>7</TAB_INDEX>
    <TEXT_TYPE>DECIMAL3</TEXT_TYPE>
    <ALLOWCHAR></ALLOWCHAR>
    <DATA_VALIDATE>required,min[1]</DATA_VALIDATE>
  </WebFormDefinition>

  <WebFormDefinition>
    <DETAIL_ID>8</DETAIL_ID>
    <FORM_ID>732</FORM_ID>
    <HTML_CONTROL_ID>VolumeWeight</HTML_CONTROL_ID>
    <DISPLAY_ORDER>8</DISPLAY_ORDER>
    <ASSEMBLY_NAME>HTML.TextBox</ASSEMBLY_NAME>
    <LABEL_CELL_TEXT>Volume</LABEL_CELL_TEXT>
    <LABEL_CELL_CSSCLASS>formlabel</LABEL_CELL_CSSCLASS>
    <DATA_FIELDNAME>VolumeWeight</DATA_FIELDNAME>
    <DATA_FIELD_CSSCLASS></DATA_FIELD_CSSCLASS>
    <DATA_CELL_CSSCLASS>formInputcolumn</DATA_CELL_CSSCLASS>
    <ONCLICK_HANDLER></ONCLICK_HANDLER>
    <POSTBACK_URL></POSTBACK_URL>
    <CALLBACK_URL></CALLBACK_URL>
    <SKIN_ID></SKIN_ID>
    <TOOLTIP>Enter Volume</TOOLTIP>
    <BTN_USESUBMIT_BEHAVIOUR></BTN_USESUBMIT_BEHAVIOUR>
    <VISIBLE>true</VISIBLE>
    <READONLY>false</READONLY>
    <ENABLE_VIEWSTATE>true</ENABLE_VIEWSTATE>
    <MAXLENGTH>5</MAXLENGTH>
    <MULTILINE></MULTILINE>
    <WIDTH></WIDTH>
    <HEIGHT></HEIGHT>
    <SECTION_NAME></SECTION_NAME>
    <ONKEY_HANDLER></ONKEY_HANDLER>
    <ONBLUR_HANDLER></ONBLUR_HANDLER>
    <ENABLE_REQUIREVALIDATION>true</ENABLE_REQUIREVALIDATION>
    <REQUIRED_FIELD_MESSAGE>Volume can not be blank and should be greater than or equal to 1.</REQUIRED_FIELD_MESSAGE>
    <LOOKUP_NAME></LOOKUP_NAME>
    <IMAGE_URL></IMAGE_URL>
    <CONTROL_TOTAL></CONTROL_TOTAL>
    <TAB_INDEX>8</TAB_INDEX>
    <TEXT_TYPE>DECIMAL3</TEXT_TYPE>
    <ALLOWCHAR></ALLOWCHAR>
    <DATA_VALIDATE>required,min[1]</DATA_VALIDATE>
  </WebFormDefinition>



  <WebFormDefinition>
    <DETAIL_ID>9</DETAIL_ID>
    <FORM_ID>732</FORM_ID>
    <HTML_CONTROL_ID>Unit</HTML_CONTROL_ID>
    <DISPLAY_ORDER>9</DISPLAY_ORDER>
    <ASSEMBLY_NAME>HTML.RadioButtonList</ASSEMBLY_NAME>
    <LABEL_CELL_TEXT>Measurement Unit</LABEL_CELL_TEXT>
    <LABEL_CELL_CSSCLASS>formlabel</LABEL_CELL_CSSCLASS>
    <DATA_FIELDNAME>Unit</DATA_FIELDNAME>
    <DATA_FIELD_CSSCLASS></DATA_FIELD_CSSCLASS>
    <DATA_CELL_CSSCLASS>formInputcolumn</DATA_CELL_CSSCLASS>
    <ONCLICK_HANDLER></ONCLICK_HANDLER>
    <POSTBACK_URL></POSTBACK_URL>
    <CALLBACK_URL></CALLBACK_URL>
    <SKIN_ID></SKIN_ID>
    <TOOLTIP>Enter Measurement Unit</TOOLTIP>
    <BTN_USESUBMIT_BEHAVIOUR></BTN_USESUBMIT_BEHAVIOUR>
    <VISIBLE>true</VISIBLE>
    <READONLY>false</READONLY>
    <ENABLE_VIEWSTATE>true</ENABLE_VIEWSTATE>
    <MAXLENGTH>100</MAXLENGTH>
    <MULTILINE></MULTILINE>
    <WIDTH>175</WIDTH>
    <HEIGHT></HEIGHT>
    <SECTION_NAME></SECTION_NAME>
    <ONKEY_HANDLER></ONKEY_HANDLER>
    <ONBLUR_HANDLER></ONBLUR_HANDLER>
    <ENABLE_REQUIREVALIDATION></ENABLE_REQUIREVALIDATION>
    <REQUIRED_FIELD_MESSAGE>Measurement Unit can not be blank</REQUIRED_FIELD_MESSAGE>
    <LOOKUP_NAME></LOOKUP_NAME>
    <IMAGE_URL></IMAGE_URL>
    <CONTROL_TOTAL></CONTROL_TOTAL>
    <TAB_INDEX>9</TAB_INDEX>
    <DATA_VALIDATE></DATA_VALIDATE>
    <TEXT_TYPE>ENUM.MEASUREMENTUNIT</TEXT_TYPE>
    <ALLOWCHAR></ALLOWCHAR>
  </WebFormDefinition>

  <WebFormDefinition>
    <DETAIL_ID>10</DETAIL_ID>
    <FORM_ID>732</FORM_ID>
    <HTML_CONTROL_ID>Length</HTML_CONTROL_ID>
    <DISPLAY_ORDER>10</DISPLAY_ORDER>
    <ASSEMBLY_NAME>HTML.TextBox</ASSEMBLY_NAME>
    <LABEL_CELL_TEXT>Length</LABEL_CELL_TEXT>
    <LABEL_CELL_CSSCLASS>formlabel</LABEL_CELL_CSSCLASS>
    <DATA_FIELDNAME>Length</DATA_FIELDNAME>
    <DATA_FIELD_CSSCLASS></DATA_FIELD_CSSCLASS>
    <DATA_CELL_CSSCLASS>formInputcolumn</DATA_CELL_CSSCLASS>
    <ONCLICK_HANDLER></ONCLICK_HANDLER>
    <POSTBACK_URL></POSTBACK_URL>
    <CALLBACK_URL></CALLBACK_URL>
    <SKIN_ID></SKIN_ID>
    <TOOLTIP>Enter Length</TOOLTIP>
    <BTN_USESUBMIT_BEHAVIOUR></BTN_USESUBMIT_BEHAVIOUR>
    <VISIBLE>true</VISIBLE>
    <READONLY>false</READONLY>
    <ENABLE_VIEWSTATE>true</ENABLE_VIEWSTATE>
    <MAXLENGTH>5</MAXLENGTH>
    <MULTILINE></MULTILINE>
    <WIDTH></WIDTH>
    <HEIGHT></HEIGHT>
    <SECTION_NAME></SECTION_NAME>
    <ONKEY_HANDLER></ONKEY_HANDLER>
    <ONBLUR_HANDLER></ONBLUR_HANDLER>
    <ENABLE_REQUIREVALIDATION>true</ENABLE_REQUIREVALIDATION>
    <REQUIRED_FIELD_MESSAGE>Length can not be blank and should be greater than or equal to 1.</REQUIRED_FIELD_MESSAGE>
    <LOOKUP_NAME></LOOKUP_NAME>
    <IMAGE_URL></IMAGE_URL>
    <CONTROL_TOTAL></CONTROL_TOTAL>
    <TAB_INDEX>10</TAB_INDEX>
    <TEXT_TYPE>DECIMAL3</TEXT_TYPE>
    <ALLOWCHAR></ALLOWCHAR>
    <DATA_VALIDATE>required,min[1]</DATA_VALIDATE>
  </WebFormDefinition>

  <WebFormDefinition>
    <DETAIL_ID>11</DETAIL_ID>
    <FORM_ID>732</FORM_ID>
    <HTML_CONTROL_ID>Width</HTML_CONTROL_ID>
    <DISPLAY_ORDER>11</DISPLAY_ORDER>
    <ASSEMBLY_NAME>HTML.TextBox</ASSEMBLY_NAME>
    <LABEL_CELL_TEXT>Width</LABEL_CELL_TEXT>
    <LABEL_CELL_CSSCLASS>formlabel</LABEL_CELL_CSSCLASS>
    <DATA_FIELDNAME>Width</DATA_FIELDNAME>
    <DATA_FIELD_CSSCLASS></DATA_FIELD_CSSCLASS>
    <DATA_CELL_CSSCLASS>formInputcolumn</DATA_CELL_CSSCLASS>
    <ONCLICK_HANDLER></ONCLICK_HANDLER>
    <POSTBACK_URL></POSTBACK_URL>
    <CALLBACK_URL></CALLBACK_URL>
    <SKIN_ID></SKIN_ID>
    <TOOLTIP>Enter Width</TOOLTIP>
    <BTN_USESUBMIT_BEHAVIOUR></BTN_USESUBMIT_BEHAVIOUR>
    <VISIBLE>true</VISIBLE>
    <READONLY>false</READONLY>
    <ENABLE_VIEWSTATE>true</ENABLE_VIEWSTATE>
    <MAXLENGTH>5</MAXLENGTH>
    <MULTILINE></MULTILINE>
    <WIDTH></WIDTH>
    <HEIGHT></HEIGHT>
    <SECTION_NAME></SECTION_NAME>
    <ONKEY_HANDLER></ONKEY_HANDLER>
    <ONBLUR_HANDLER></ONBLUR_HANDLER>
    <ENABLE_REQUIREVALIDATION>true</ENABLE_REQUIREVALIDATION>
    <REQUIRED_FIELD_MESSAGE>Width can not be blank and should be greater than or equal to 1.</REQUIRED_FIELD_MESSAGE>
    <LOOKUP_NAME></LOOKUP_NAME>
    <IMAGE_URL></IMAGE_URL>
    <CONTROL_TOTAL></CONTROL_TOTAL>
    <TAB_INDEX>11</TAB_INDEX>
    <TEXT_TYPE>DECIMAL3</TEXT_TYPE>
    <ALLOWCHAR></ALLOWCHAR>
    <DATA_VALIDATE>required,min[1]</DATA_VALIDATE>
  </WebFormDefinition>

  <WebFormDefinition>
    <DETAIL_ID>12</DETAIL_ID>
    <FORM_ID>732</FORM_ID>
    <HTML_CONTROL_ID>Height</HTML_CONTROL_ID>
    <DISPLAY_ORDER>12</DISPLAY_ORDER>
    <ASSEMBLY_NAME>HTML.TextBox</ASSEMBLY_NAME>
    <LABEL_CELL_TEXT>Height</LABEL_CELL_TEXT>
    <LABEL_CELL_CSSCLASS>formlabel</LABEL_CELL_CSSCLASS>
    <DATA_FIELDNAME>Height</DATA_FIELDNAME>
    <DATA_FIELD_CSSCLASS></DATA_FIELD_CSSCLASS>
    <DATA_CELL_CSSCLASS>formInputcolumn</DATA_CELL_CSSCLASS>
    <ONCLICK_HANDLER></ONCLICK_HANDLER>
    <POSTBACK_URL></POSTBACK_URL>
    <CALLBACK_URL></CALLBACK_URL>
    <SKIN_ID></SKIN_ID>
    <TOOLTIP>Height</TOOLTIP>
    <BTN_USESUBMIT_BEHAVIOUR></BTN_USESUBMIT_BEHAVIOUR>
    <VISIBLE>true</VISIBLE>
    <READONLY>false</READONLY>
    <ENABLE_VIEWSTATE>true</ENABLE_VIEWSTATE>
    <MAXLENGTH>5</MAXLENGTH>
    <MULTILINE></MULTILINE>
    <WIDTH></WIDTH>
    <HEIGHT></HEIGHT>
    <SECTION_NAME></SECTION_NAME>
    <ONKEY_HANDLER></ONKEY_HANDLER>
    <ONBLUR_HANDLER></ONBLUR_HANDLER>
    <ENABLE_REQUIREVALIDATION>false</ENABLE_REQUIREVALIDATION>
    <REQUIRED_FIELD_MESSAGE>Height should be greater than or equal to 1.</REQUIRED_FIELD_MESSAGE>
    <LOOKUP_NAME></LOOKUP_NAME>
    <IMAGE_URL></IMAGE_URL>
    <CONTROL_TOTAL></CONTROL_TOTAL>
    <TAB_INDEX>12</TAB_INDEX>
    <TEXT_TYPE>DECIMAL3</TEXT_TYPE>
    <ALLOWCHAR></ALLOWCHAR>
    <DATA_VALIDATE>min[1]</DATA_VALIDATE>
  </WebFormDefinition>

  <WebFormDefinition>
    <DETAIL_ID>13</DETAIL_ID>
    <FORM_ID>732</FORM_ID>
    <HTML_CONTROL_ID>ULDDescription</HTML_CONTROL_ID>
    <DISPLAY_ORDER>13</DISPLAY_ORDER>
    <ASSEMBLY_NAME>HTML.TextBox</ASSEMBLY_NAME>
    <LABEL_CELL_TEXT>ULD Description</LABEL_CELL_TEXT>
    <LABEL_CELL_CSSCLASS>formlabel</LABEL_CELL_CSSCLASS>
    <DATA_FIELDNAME>ULDdescription</DATA_FIELDNAME>
    <DATA_FIELD_CSSCLASS></DATA_FIELD_CSSCLASS>
    <DATA_CELL_CSSCLASS>formInputcolumn</DATA_CELL_CSSCLASS>
    <ONCLICK_HANDLER></ONCLICK_HANDLER>
    <POSTBACK_URL></POSTBACK_URL>
    <CALLBACK_URL></CALLBACK_URL>
    <SKIN_ID></SKIN_ID>
    <TOOLTIP>Enter ULD Description</TOOLTIP>
    <BTN_USESUBMIT_BEHAVIOUR></BTN_USESUBMIT_BEHAVIOUR>
    <VISIBLE>true</VISIBLE>
    <READONLY>false</READONLY>
    <ENABLE_VIEWSTATE>true</ENABLE_VIEWSTATE>
    <MAXLENGTH>200</MAXLENGTH>
    <MULTILINE>YES</MULTILINE>
    <WIDTH>200</WIDTH>
    <HEIGHT></HEIGHT>
    <SECTION_NAME></SECTION_NAME>
    <ONKEY_HANDLER></ONKEY_HANDLER>
    <ONBLUR_HANDLER></ONBLUR_HANDLER>
    <ENABLE_REQUIREVALIDATION>false</ENABLE_REQUIREVALIDATION>
    <REQUIRED_FIELD_MESSAGE></REQUIRED_FIELD_MESSAGE>
    <LOOKUP_NAME></LOOKUP_NAME>
    <IMAGE_URL></IMAGE_URL>
    <CONTROL_TOTAL></CONTROL_TOTAL>
    <TAB_INDEX>13</TAB_INDEX>
    <TEXT_TYPE>ALPHANUMERICUPPER</TEXT_TYPE>
    <ALLOWCHAR></ALLOWCHAR>
    <DATA_VALIDATE></DATA_VALIDATE>
  </WebFormDefinition>

  <WebFormDefinition>
    <DETAIL_ID>14</DETAIL_ID>
    <FORM_ID>732</FORM_ID>
    <HTML_CONTROL_ID>IsActive</HTML_CONTROL_ID>
    <DISPLAY_ORDER>14</DISPLAY_ORDER>
    <ASSEMBLY_NAME>HTML.RadioButtonList</ASSEMBLY_NAME>
    <LABEL_CELL_TEXT>Active</LABEL_CELL_TEXT>
    <LABEL_CELL_CSSCLASS>formlabel</LABEL_CELL_CSSCLASS>
    <DATA_FIELDNAME>IsActive</DATA_FIELDNAME>
    <DATA_FIELD_CSSCLASS></DATA_FIELD_CSSCLASS>
    <DATA_CELL_CSSCLASS>formInputcolumn</DATA_CELL_CSSCLASS>
    <ONCLICK_HANDLER></ONCLICK_HANDLER>
    <POSTBACK_URL></POSTBACK_URL>
    <CALLBACK_URL></CALLBACK_URL>
    <SKIN_ID></SKIN_ID>
    <TOOLTIP>Selct Active</TOOLTIP>
    <BTN_USESUBMIT_BEHAVIOUR></BTN_USESUBMIT_BEHAVIOUR>
    <VISIBLE>true</VISIBLE>
    <READONLY>false</READONLY>
    <ENABLE_VIEWSTATE>true</ENABLE_VIEWSTATE>
    <MAXLENGTH></MAXLENGTH>
    <MULTILINE></MULTILINE>
    <WIDTH></WIDTH>
    <HEIGHT></HEIGHT>
    <SECTION_NAME></SECTION_NAME>
    <ONKEY_HANDLER></ONKEY_HANDLER>
    <ONBLUR_HANDLER></ONBLUR_HANDLER>
    <ENABLE_REQUIREVALIDATION>false</ENABLE_REQUIREVALIDATION>
    <REQUIRED_FIELD_MESSAGE>Active is required.</REQUIRED_FIELD_MESSAGE>
    <LOOKUP_NAME></LOOKUP_NAME>
    <IMAGE_URL></IMAGE_URL>
    <CONTROL_TOTAL></CONTROL_TOTAL>
    <TAB_INDEX>14</TAB_INDEX>
    <TEXT_TYPE>ENUM.ACTIVE</TEXT_TYPE>
    <ALLOWCHAR></ALLOWCHAR>
    <DATA_VALIDATE></DATA_VALIDATE>
  </WebFormDefinition>

  <WebFormDefinition>
    <DETAIL_ID>15</DETAIL_ID>
    <FORM_ID>732</FORM_ID>
    <HTML_CONTROL_ID></HTML_CONTROL_ID>
    <DISPLAY_ORDER>15</DISPLAY_ORDER>
    <ASSEMBLY_NAME>HTML.Label</ASSEMBLY_NAME>
    <LABEL_CELL_TEXT></LABEL_CELL_TEXT>
    <LABEL_CELL_CSSCLASS>formlabel</LABEL_CELL_CSSCLASS>
    <DATA_FIELDNAME></DATA_FIELDNAME>
    <DATA_FIELD_CSSCLASS></DATA_FIELD_CSSCLASS>
    <DATA_CELL_CSSCLASS>formInputcolumn</DATA_CELL_CSSCLASS>
    <ONCLICK_HANDLER></ONCLICK_HANDLER>
    <POSTBACK_URL></POSTBACK_URL>
    <CALLBACK_URL></CALLBACK_URL>
    <SKIN_ID></SKIN_ID>
    <TOOLTIP></TOOLTIP>
    <BTN_USESUBMIT_BEHAVIOUR></BTN_USESUBMIT_BEHAVIOUR>
    <VISIBLE>true</VISIBLE>
    <READONLY>false</READONLY>
    <ENABLE_VIEWSTATE>true</ENABLE_VIEWSTATE>
    <MAXLENGTH>50</MAXLENGTH>
    <MULTILINE>YES</MULTILINE>
    <WIDTH>200</WIDTH>
    <HEIGHT></HEIGHT>
    <SECTION_NAME></SECTION_NAME>
    <ONKEY_HANDLER></ONKEY_HANDLER>
    <ONBLUR_HANDLER></ONBLUR_HANDLER>
    <ENABLE_REQUIREVALIDATION>false</ENABLE_REQUIREVALIDATION>
    <REQUIRED_FIELD_MESSAGE></REQUIRED_FIELD_MESSAGE>
    <LOOKUP_NAME></LOOKUP_NAME>
    <IMAGE_URL></IMAGE_URL>
    <CONTROL_TOTAL></CONTROL_TOTAL>
    <TAB_INDEX>15</TAB_INDEX>
    <TEXT_TYPE>UPPERCASE</TEXT_TYPE>
    <ALLOWCHAR></ALLOWCHAR>
    <DATA_VALIDATE></DATA_VALIDATE>
  </WebFormDefinition>
  <WebFormDefinition>
    <DETAIL_ID>16</DETAIL_ID>
    <FORM_ID>732</FORM_ID>
    <HTML_CONTROL_ID>CommonDesignation</HTML_CONTROL_ID>
    <DISPLAY_ORDER>16</DISPLAY_ORDER>
    <ASSEMBLY_NAME>HTML.TextBox</ASSEMBLY_NAME>
    <LABEL_CELL_TEXT>Common Designation</LABEL_CELL_TEXT>
    <LABEL_CELL_CSSCLASS>formlabel</LABEL_CELL_CSSCLASS>
    <DATA_FIELDNAME>CommonDesignation</DATA_FIELDNAME>
    <DATA_FIELD_CSSCLASS></DATA_FIELD_CSSCLASS>
    <DATA_CELL_CSSCLASS>formInputcolumn</DATA_CELL_CSSCLASS>
    <ONCLICK_HANDLER></ONCLICK_HANDLER>
    <POSTBACK_URL></POSTBACK_URL>
    <CALLBACK_URL></CALLBACK_URL>
    <SKIN_ID></SKIN_ID>
    <TOOLTIP>Enter Common Designation</TOOLTIP>
    <BTN_USESUBMIT_BEHAVIOUR></BTN_USESUBMIT_BEHAVIOUR>
    <VISIBLE>true</VISIBLE>
    <READONLY>false</READONLY>
    <ENABLE_VIEWSTATE>true</ENABLE_VIEWSTATE>
    <MAXLENGTH>50</MAXLENGTH>
    <MULTILINE>YES</MULTILINE>
    <WIDTH>200</WIDTH>
    <HEIGHT></HEIGHT>
    <SECTION_NAME></SECTION_NAME>
    <ONKEY_HANDLER></ONKEY_HANDLER>
    <ONBLUR_HANDLER></ONBLUR_HANDLER>
    <ENABLE_REQUIREVALIDATION>false</ENABLE_REQUIREVALIDATION>
    <REQUIRED_FIELD_MESSAGE></REQUIRED_FIELD_MESSAGE>
    <LOOKUP_NAME></LOOKUP_NAME>
    <IMAGE_URL></IMAGE_URL>
    <CONTROL_TOTAL></CONTROL_TOTAL>
    <TAB_INDEX>16</TAB_INDEX>
    <TEXT_TYPE>UPPERCASE</TEXT_TYPE>
    <ALLOWCHAR></ALLOWCHAR>
    <DATA_VALIDATE></DATA_VALIDATE>
  </WebFormDefinition>
  <!--<WebFormDefinition>
    <DETAIL_ID>15</DETAIL_ID>
    <FORM_ID>732</FORM_ID>
    <HTML_CONTROL_ID>ULDTypeSno</HTML_CONTROL_ID>
    <DISPLAY_ORDER>15</DISPLAY_ORDER>
    <ASSEMBLY_NAME>HTML.AutoCompleteTextBox</ASSEMBLY_NAME>
    <LABEL_CELL_TEXT>ULD Type</LABEL_CELL_TEXT>
    <LABEL_CELL_CSSCLASS>formlabel</LABEL_CELL_CSSCLASS>
    <DATA_FIELDNAME>ULDTypeSno</DATA_FIELDNAME>
    <DATA_FIELD_CSSCLASS></DATA_FIELD_CSSCLASS>
    <DATA_CELL_CSSCLASS>formInputcolumn</DATA_CELL_CSSCLASS>
    <ONCLICK_HANDLER></ONCLICK_HANDLER>
    <POSTBACK_URL></POSTBACK_URL>
    <CALLBACK_URL></CALLBACK_URL>
    <SKIN_ID></SKIN_ID>
    <TOOLTIP>Enter ULD Type</TOOLTIP>
    <BTN_USESUBMIT_BEHAVIOUR></BTN_USESUBMIT_BEHAVIOUR>
    <VISIBLE>true</VISIBLE>
    <READONLY>false</READONLY>
    <ENABLE_VIEWSTATE>true</ENABLE_VIEWSTATE>
    <MAXLENGTH></MAXLENGTH>
    <MULTILINE></MULTILINE>
    <WIDTH>100</WIDTH>
    <HEIGHT></HEIGHT>
    <SECTION_NAME></SECTION_NAME>
    <ONKEY_HANDLER></ONKEY_HANDLER>
    <ONBLUR_HANDLER></ONBLUR_HANDLER>
    <ENABLE_REQUIREVALIDATION>false</ENABLE_REQUIREVALIDATION>
    <REQUIRED_FIELD_MESSAGE>ULD Type can not be blank</REQUIRED_FIELD_MESSAGE>
    <LOOKUP_NAME></LOOKUP_NAME>
    <IMAGE_URL></IMAGE_URL>
    <CONTROL_TOTAL></CONTROL_TOTAL>
    <TAB_INDEX>15</TAB_INDEX>
    <TEXT_TYPE>UPPERCASE</TEXT_TYPE>
    <ALLOWCHAR></ALLOWCHAR>
    <DATA_VALIDATE></DATA_VALIDATE>
  </WebFormDefinition>-->

  <WebFormDefinition>
    <DETAIL_ID>17</DETAIL_ID>
    <FORM_ID>732</FORM_ID>
    <HTML_CONTROL_ID>CreatedBy</HTML_CONTROL_ID>
    <DISPLAY_ORDER>17</DISPLAY_ORDER>
    <ASSEMBLY_NAME>HTML.Label</ASSEMBLY_NAME>
    <LABEL_CELL_TEXT>Created By</LABEL_CELL_TEXT>
    <LABEL_CELL_CSSCLASS>formlabel</LABEL_CELL_CSSCLASS>
    <DATA_FIELDNAME>CreatedBy</DATA_FIELDNAME>
    <DATA_FIELD_CSSCLASS></DATA_FIELD_CSSCLASS>
    <DATA_CELL_CSSCLASS>formInputcolumn</DATA_CELL_CSSCLASS>
    <ONCLICK_HANDLER></ONCLICK_HANDLER>
    <POSTBACK_URL></POSTBACK_URL>
    <CALLBACK_URL></CALLBACK_URL>
    <SKIN_ID></SKIN_ID>
    <TOOLTIP></TOOLTIP>
    <BTN_USESUBMIT_BEHAVIOUR>true</BTN_USESUBMIT_BEHAVIOUR>
    <VISIBLE>true</VISIBLE>
    <READONLY>true</READONLY>
    <ENABLE_VIEWSTATE>true</ENABLE_VIEWSTATE>
    <MAXLENGTH></MAXLENGTH>
    <MULTILINE></MULTILINE>
    <WIDTH></WIDTH>
    <HEIGHT></HEIGHT>
    <SECTION_NAME>User Action Information</SECTION_NAME>
    <ONKEY_HANDLER></ONKEY_HANDLER>
    <ONBLUR_HANDLER></ONBLUR_HANDLER>
    <ENABLE_REQUIREVALIDATION>false</ENABLE_REQUIREVALIDATION>
    <REQUIRED_FIELD_MESSAGE></REQUIRED_FIELD_MESSAGE>
    <LOOKUP_NAME></LOOKUP_NAME>
    <IMAGE_URL></IMAGE_URL>
    <CONTROL_TOTAL></CONTROL_TOTAL>
    <TEXT_TYPE></TEXT_TYPE>
    <ALLOWCHAR></ALLOWCHAR>
    <TAB_INDEX>17</TAB_INDEX>
    <DATA_VALIDATE></DATA_VALIDATE>
  </WebFormDefinition>
  <WebFormDefinition>
    <DETAIL_ID>18</DETAIL_ID>
    <FORM_ID>732</FORM_ID>
    <HTML_CONTROL_ID>UpdatedBy</HTML_CONTROL_ID>
    <DISPLAY_ORDER>18</DISPLAY_ORDER>
    <ASSEMBLY_NAME>HTML.Label</ASSEMBLY_NAME>
    <LABEL_CELL_TEXT>Updated By</LABEL_CELL_TEXT>
    <LABEL_CELL_CSSCLASS>formlabel</LABEL_CELL_CSSCLASS>
    <DATA_FIELDNAME>UpdatedBy</DATA_FIELDNAME>
    <DATA_FIELD_CSSCLASS></DATA_FIELD_CSSCLASS>
    <DATA_CELL_CSSCLASS>formInputcolumn</DATA_CELL_CSSCLASS>
    <ONCLICK_HANDLER></ONCLICK_HANDLER>
    <POSTBACK_URL></POSTBACK_URL>
    <CALLBACK_URL></CALLBACK_URL>
    <SKIN_ID></SKIN_ID>
    <TOOLTIP></TOOLTIP>
    <BTN_USESUBMIT_BEHAVIOUR>true</BTN_USESUBMIT_BEHAVIOUR>
    <VISIBLE>true</VISIBLE>
    <READONLY>true</READONLY>
    <ENABLE_VIEWSTATE>true</ENABLE_VIEWSTATE>
    <MAXLENGTH></MAXLENGTH>
    <MULTILINE></MULTILINE>
    <WIDTH></WIDTH>
    <HEIGHT></HEIGHT>
    <SECTION_NAME></SECTION_NAME>
    <ONKEY_HANDLER></ONKEY_HANDLER>
    <ONBLUR_HANDLER></ONBLUR_HANDLER>
    <ENABLE_REQUIREVALIDATION></ENABLE_REQUIREVALIDATION>
    <REQUIRED_FIELD_MESSAGE></REQUIRED_FIELD_MESSAGE>
    <LOOKUP_NAME></LOOKUP_NAME>
    <IMAGE_URL></IMAGE_URL>
    <CONTROL_TOTAL></CONTROL_TOTAL>
    <TEXT_TYPE></TEXT_TYPE>
    <ALLOWCHAR></ALLOWCHAR>
    <TAB_INDEX>18</TAB_INDEX>
    <DATA_VALIDATE></DATA_VALIDATE>
  </WebFormDefinition>






  <!--END-->

  <!--<WebFormDefinition>
    <DETAIL_ID>1</DETAIL_ID>
    <FORM_ID>732</FORM_ID>
    <HTML_CONTROL_ID>ULDCode</HTML_CONTROL_ID>
    <DISPLAY_ORDER>1</DISPLAY_ORDER>
    <ASSEMBLY_NAME>HTML.TextBox</ASSEMBLY_NAME>
    <LABEL_CELL_TEXT>ULD Code</LABEL_CELL_TEXT>
    <LABEL_CELL_CSSCLASS>formlabel</LABEL_CELL_CSSCLASS>
    <DATA_FIELDNAME>ULDCode</DATA_FIELDNAME>
    <DATA_FIELD_CSSCLASS></DATA_FIELD_CSSCLASS>
    <DATA_CELL_CSSCLASS>formInputcolumn</DATA_CELL_CSSCLASS>
    <ONCLICK_HANDLER></ONCLICK_HANDLER>
    <POSTBACK_URL></POSTBACK_URL>
    <CALLBACK_URL></CALLBACK_URL>
    <SKIN_ID></SKIN_ID>
    <TOOLTIP>ULD Code</TOOLTIP>
    <BTN_USESUBMIT_BEHAVIOUR></BTN_USESUBMIT_BEHAVIOUR>
    <VISIBLE>true</VISIBLE>
    <READONLY>false</READONLY>
    <ENABLE_VIEWSTATE>true</ENABLE_VIEWSTATE>
    <MAXLENGTH>5</MAXLENGTH>
    <MULTILINE></MULTILINE>
    <WIDTH>50</WIDTH>
    <HEIGHT></HEIGHT>
    <SECTION_NAME>ULD Code Information</SECTION_NAME>
    <ONKEY_HANDLER></ONKEY_HANDLER>
    <ONBLUR_HANDLER></ONBLUR_HANDLER>
    <ENABLE_REQUIREVALIDATION>true</ENABLE_REQUIREVALIDATION>
    <REQUIRED_FIELD_MESSAGE>ULD Code can not be blank</REQUIRED_FIELD_MESSAGE>
    <LOOKUP_NAME></LOOKUP_NAME>
    <IMAGE_URL></IMAGE_URL>
    <CONTROL_TOTAL></CONTROL_TOTAL>
    <TAB_INDEX>1</TAB_INDEX>
    <TEXT_TYPE>UPPERCASE</TEXT_TYPE>
    <ALLOWCHAR></ALLOWCHAR>
    <DATA_VALIDATE>required</DATA_VALIDATE>
  </WebFormDefinition>

  <WebFormDefinition>
    <DETAIL_ID>2</DETAIL_ID>
    <FORM_ID>732</FORM_ID>
    <HTML_CONTROL_ID>EmptyWeight</HTML_CONTROL_ID>
    <DISPLAY_ORDER>2</DISPLAY_ORDER>
    <ASSEMBLY_NAME>HTML.TextBox</ASSEMBLY_NAME>
    <LABEL_CELL_TEXT>Tare Weight</LABEL_CELL_TEXT>
    <LABEL_CELL_CSSCLASS>formlabel</LABEL_CELL_CSSCLASS>
    <DATA_FIELDNAME>EmptyWeight</DATA_FIELDNAME>
    <DATA_FIELD_CSSCLASS></DATA_FIELD_CSSCLASS>
    <DATA_CELL_CSSCLASS>formInputcolumn</DATA_CELL_CSSCLASS>
    <ONCLICK_HANDLER></ONCLICK_HANDLER>
    <POSTBACK_URL></POSTBACK_URL>
    <CALLBACK_URL></CALLBACK_URL>
    <SKIN_ID></SKIN_ID>
    <TOOLTIP>Tare Weight</TOOLTIP>
    <BTN_USESUBMIT_BEHAVIOUR></BTN_USESUBMIT_BEHAVIOUR>
    <VISIBLE>true</VISIBLE>
    <READONLY>false</READONLY>
    <ENABLE_VIEWSTATE>true</ENABLE_VIEWSTATE>
    <MAXLENGTH>7</MAXLENGTH>
    <MULTILINE></MULTILINE>
    <WIDTH></WIDTH>
    <HEIGHT></HEIGHT>
    <SECTION_NAME></SECTION_NAME>
    <ONKEY_HANDLER></ONKEY_HANDLER>
    <ONBLUR_HANDLER></ONBLUR_HANDLER>
    <ENABLE_REQUIREVALIDATION>true</ENABLE_REQUIREVALIDATION>
    <REQUIRED_FIELD_MESSAGE>Tare Weight can not be blank</REQUIRED_FIELD_MESSAGE>
    <LOOKUP_NAME></LOOKUP_NAME>
    <IMAGE_URL></IMAGE_URL>
    <CONTROL_TOTAL></CONTROL_TOTAL>
    <TAB_INDEX>2</TAB_INDEX>
    <TEXT_TYPE>DECIMAL2</TEXT_TYPE>
    <ALLOWCHAR></ALLOWCHAR>
    <DATA_VALIDATE>required</DATA_VALIDATE>
  </WebFormDefinition>


  <WebFormDefinition>
    <DETAIL_ID>3</DETAIL_ID>
    <FORM_ID>732</FORM_ID>
    <HTML_CONTROL_ID>GrossWeight</HTML_CONTROL_ID>
    <DISPLAY_ORDER>3</DISPLAY_ORDER>
    <ASSEMBLY_NAME>HTML.TextBox</ASSEMBLY_NAME>
    <LABEL_CELL_TEXT>Gross Weight</LABEL_CELL_TEXT>
    <LABEL_CELL_CSSCLASS>formlabel</LABEL_CELL_CSSCLASS>
    <DATA_FIELDNAME>GrossWeight</DATA_FIELDNAME>
    <DATA_FIELD_CSSCLASS></DATA_FIELD_CSSCLASS>
    <DATA_CELL_CSSCLASS>formInputcolumn</DATA_CELL_CSSCLASS>
    <ONCLICK_HANDLER></ONCLICK_HANDLER>
    <POSTBACK_URL></POSTBACK_URL>
    <CALLBACK_URL></CALLBACK_URL>
    <SKIN_ID></SKIN_ID>
    <TOOLTIP>Gross Weight</TOOLTIP>
    <BTN_USESUBMIT_BEHAVIOUR></BTN_USESUBMIT_BEHAVIOUR>
    <VISIBLE>true</VISIBLE>
    <READONLY>false</READONLY>
    <ENABLE_VIEWSTATE>true</ENABLE_VIEWSTATE>
    <MAXLENGTH>7</MAXLENGTH>
    <MULTILINE></MULTILINE>
    <WIDTH></WIDTH>
    <HEIGHT></HEIGHT>
    <SECTION_NAME></SECTION_NAME>
    <ONKEY_HANDLER></ONKEY_HANDLER>
    <ONBLUR_HANDLER></ONBLUR_HANDLER>
    <ENABLE_REQUIREVALIDATION>true</ENABLE_REQUIREVALIDATION>
    <REQUIRED_FIELD_MESSAGE>Gross Weight can not be blank</REQUIRED_FIELD_MESSAGE>
    <LOOKUP_NAME></LOOKUP_NAME>
    <IMAGE_URL></IMAGE_URL>
    <CONTROL_TOTAL></CONTROL_TOTAL>
    <TAB_INDEX>3</TAB_INDEX>
    <TEXT_TYPE>DECIMAL2</TEXT_TYPE>
    <ALLOWCHAR></ALLOWCHAR>
    <DATA_VALIDATE>required</DATA_VALIDATE>
  </WebFormDefinition>

  <WebFormDefinition>
    <DETAIL_ID>4</DETAIL_ID>
    <FORM_ID>732</FORM_ID>
    <HTML_CONTROL_ID>VolumeWeight</HTML_CONTROL_ID>
    <DISPLAY_ORDER>4</DISPLAY_ORDER>
    <ASSEMBLY_NAME>HTML.TextBox</ASSEMBLY_NAME>
    <LABEL_CELL_TEXT>Volume Weight</LABEL_CELL_TEXT>
    <LABEL_CELL_CSSCLASS>formlabel</LABEL_CELL_CSSCLASS>
    <DATA_FIELDNAME>VolumeWeight</DATA_FIELDNAME>
    <DATA_FIELD_CSSCLASS></DATA_FIELD_CSSCLASS>
    <DATA_CELL_CSSCLASS>formInputcolumn</DATA_CELL_CSSCLASS>
    <ONCLICK_HANDLER></ONCLICK_HANDLER>
    <POSTBACK_URL></POSTBACK_URL>
    <CALLBACK_URL></CALLBACK_URL>
    <SKIN_ID></SKIN_ID>
    <TOOLTIP>Volume Weight</TOOLTIP>
    <BTN_USESUBMIT_BEHAVIOUR></BTN_USESUBMIT_BEHAVIOUR>
    <VISIBLE>true</VISIBLE>
    <READONLY>false</READONLY>
    <ENABLE_VIEWSTATE>true</ENABLE_VIEWSTATE>
    <MAXLENGTH>7</MAXLENGTH>
    <MULTILINE></MULTILINE>
    <WIDTH></WIDTH>
    <HEIGHT></HEIGHT>
    <SECTION_NAME></SECTION_NAME>
    <ONKEY_HANDLER></ONKEY_HANDLER>
    <ONBLUR_HANDLER></ONBLUR_HANDLER>
    <ENABLE_REQUIREVALIDATION>true</ENABLE_REQUIREVALIDATION>
    <REQUIRED_FIELD_MESSAGE>Volume Weight can not be blank</REQUIRED_FIELD_MESSAGE>
    <LOOKUP_NAME></LOOKUP_NAME>
    <IMAGE_URL></IMAGE_URL>
    <CONTROL_TOTAL></CONTROL_TOTAL>
    <TAB_INDEX>4</TAB_INDEX>
    <TEXT_TYPE>DECIMAL2</TEXT_TYPE>
    <ALLOWCHAR></ALLOWCHAR>
    <DATA_VALIDATE>required</DATA_VALIDATE>
  </WebFormDefinition>


  <WebFormDefinition>
    <DETAIL_ID>5</DETAIL_ID>
    <FORM_ID>732</FORM_ID>
    <HTML_CONTROL_ID>Length</HTML_CONTROL_ID>
    <DISPLAY_ORDER>5</DISPLAY_ORDER>
    <ASSEMBLY_NAME>HTML.TextBox</ASSEMBLY_NAME>
    <LABEL_CELL_TEXT>Length</LABEL_CELL_TEXT>
    <LABEL_CELL_CSSCLASS>formlabel</LABEL_CELL_CSSCLASS>
    <DATA_FIELDNAME>Length</DATA_FIELDNAME>
    <DATA_FIELD_CSSCLASS></DATA_FIELD_CSSCLASS>
    <DATA_CELL_CSSCLASS>formInputcolumn</DATA_CELL_CSSCLASS>
    <ONCLICK_HANDLER></ONCLICK_HANDLER>
    <POSTBACK_URL></POSTBACK_URL>
    <CALLBACK_URL></CALLBACK_URL>
    <SKIN_ID></SKIN_ID>
    <TOOLTIP>Length</TOOLTIP>
    <BTN_USESUBMIT_BEHAVIOUR></BTN_USESUBMIT_BEHAVIOUR>
    <VISIBLE>true</VISIBLE>
    <READONLY>false</READONLY>
    <ENABLE_VIEWSTATE>true</ENABLE_VIEWSTATE>
    <MAXLENGTH>14</MAXLENGTH>
    <MULTILINE></MULTILINE>
    <WIDTH></WIDTH>
    <HEIGHT></HEIGHT>
    <SECTION_NAME></SECTION_NAME>
    <ONKEY_HANDLER></ONKEY_HANDLER>
    <ONBLUR_HANDLER></ONBLUR_HANDLER>
    <ENABLE_REQUIREVALIDATION>true</ENABLE_REQUIREVALIDATION>
    <REQUIRED_FIELD_MESSAGE>Length can not be blank</REQUIRED_FIELD_MESSAGE>
    <LOOKUP_NAME></LOOKUP_NAME>
    <IMAGE_URL></IMAGE_URL>
    <CONTROL_TOTAL></CONTROL_TOTAL>
    <TAB_INDEX>5</TAB_INDEX>
    <TEXT_TYPE>DECIMAL2</TEXT_TYPE>
    <ALLOWCHAR></ALLOWCHAR>
    <DATA_VALIDATE>required</DATA_VALIDATE>
  </WebFormDefinition>

  <WebFormDefinition>
    <DETAIL_ID>6</DETAIL_ID>
    <FORM_ID>732</FORM_ID>
    <HTML_CONTROL_ID>Width</HTML_CONTROL_ID>
    <DISPLAY_ORDER>6</DISPLAY_ORDER>
    <ASSEMBLY_NAME>HTML.TextBox</ASSEMBLY_NAME>
    <LABEL_CELL_TEXT>Width</LABEL_CELL_TEXT>
    <LABEL_CELL_CSSCLASS>formlabel</LABEL_CELL_CSSCLASS>
    <DATA_FIELDNAME>Width</DATA_FIELDNAME>
    <DATA_FIELD_CSSCLASS></DATA_FIELD_CSSCLASS>
    <DATA_CELL_CSSCLASS>formInputcolumn</DATA_CELL_CSSCLASS>
    <ONCLICK_HANDLER></ONCLICK_HANDLER>
    <POSTBACK_URL></POSTBACK_URL>
    <CALLBACK_URL></CALLBACK_URL>
    <SKIN_ID></SKIN_ID>
    <TOOLTIP>Width</TOOLTIP>
    <BTN_USESUBMIT_BEHAVIOUR></BTN_USESUBMIT_BEHAVIOUR>
    <VISIBLE>true</VISIBLE>
    <READONLY>false</READONLY>
    <ENABLE_VIEWSTATE>true</ENABLE_VIEWSTATE>
    <MAXLENGTH>14</MAXLENGTH>
    <MULTILINE></MULTILINE>
    <WIDTH></WIDTH>
    <HEIGHT></HEIGHT>
    <SECTION_NAME></SECTION_NAME>
    <ONKEY_HANDLER></ONKEY_HANDLER>
    <ONBLUR_HANDLER></ONBLUR_HANDLER>
    <ENABLE_REQUIREVALIDATION>true</ENABLE_REQUIREVALIDATION>
    <REQUIRED_FIELD_MESSAGE>Width can not be blank</REQUIRED_FIELD_MESSAGE>
    <LOOKUP_NAME></LOOKUP_NAME>
    <IMAGE_URL></IMAGE_URL>
    <CONTROL_TOTAL></CONTROL_TOTAL>
    <TAB_INDEX>6</TAB_INDEX>
    <TEXT_TYPE>DECIMAL2</TEXT_TYPE>
    <ALLOWCHAR></ALLOWCHAR>
    <DATA_VALIDATE>required</DATA_VALIDATE>
  </WebFormDefinition>


  -->
  <!--<WebFormDefinition>
    <DETAIL_ID>7</DETAIL_ID>
    <FORM_ID>732</FORM_ID>
    <HTML_CONTROL_ID>Height</HTML_CONTROL_ID>
    <DISPLAY_ORDER>7</DISPLAY_ORDER>
    <ASSEMBLY_NAME>HTML.TextBox</ASSEMBLY_NAME>
    <LABEL_CELL_TEXT>Height</LABEL_CELL_TEXT>
    <LABEL_CELL_CSSCLASS>formlabel</LABEL_CELL_CSSCLASS>
    <DATA_FIELDNAME>Height</DATA_FIELDNAME>
    <DATA_FIELD_CSSCLASS></DATA_FIELD_CSSCLASS>
    <DATA_CELL_CSSCLASS>formInputcolumn</DATA_CELL_CSSCLASS>
    <ONCLICK_HANDLER></ONCLICK_HANDLER>
    <POSTBACK_URL></POSTBACK_URL>
    <CALLBACK_URL></CALLBACK_URL>
    <SKIN_ID></SKIN_ID>
    <TOOLTIP>Height</TOOLTIP>
    <BTN_USESUBMIT_BEHAVIOUR></BTN_USESUBMIT_BEHAVIOUR>
    <VISIBLE>true</VISIBLE>
    <READONLY>false</READONLY>
    <ENABLE_VIEWSTATE>true</ENABLE_VIEWSTATE>
    <MAXLENGTH>14</MAXLENGTH>
    <MULTILINE></MULTILINE>
    <WIDTH></WIDTH>
    <HEIGHT></HEIGHT>
    <SECTION_NAME></SECTION_NAME>
    <ONKEY_HANDLER></ONKEY_HANDLER>
    <ONBLUR_HANDLER></ONBLUR_HANDLER>
    <ENABLE_REQUIREVALIDATION>true</ENABLE_REQUIREVALIDATION>
    <REQUIRED_FIELD_MESSAGE>Height can not be blank</REQUIRED_FIELD_MESSAGE>
    <LOOKUP_NAME></LOOKUP_NAME>
    <IMAGE_URL></IMAGE_URL>
    <CONTROL_TOTAL></CONTROL_TOTAL>
    <TAB_INDEX>7</TAB_INDEX>
    <TEXT_TYPE>DECIMAL2</TEXT_TYPE>
    <ALLOWCHAR></ALLOWCHAR>
    <DATA_VALIDATE>required</DATA_VALIDATE>
  </WebFormDefinition>-->
  <!--

  <WebFormDefinition>
    <DETAIL_ID>8</DETAIL_ID>
    <FORM_ID>732</FORM_ID>
    <HTML_CONTROL_ID>Unit</HTML_CONTROL_ID>
    <DISPLAY_ORDER>8</DISPLAY_ORDER>
    <ASSEMBLY_NAME>HTML.RadioButtonList</ASSEMBLY_NAME>
    <LABEL_CELL_TEXT>Unit</LABEL_CELL_TEXT>
    <LABEL_CELL_CSSCLASS>formlabel</LABEL_CELL_CSSCLASS>
    <DATA_FIELDNAME>Unit</DATA_FIELDNAME>
    <DATA_FIELD_CSSCLASS></DATA_FIELD_CSSCLASS>
    <DATA_CELL_CSSCLASS>formInputcolumn</DATA_CELL_CSSCLASS>
    <ONCLICK_HANDLER></ONCLICK_HANDLER>
    <POSTBACK_URL></POSTBACK_URL>
    <CALLBACK_URL></CALLBACK_URL>
    <SKIN_ID></SKIN_ID>
    <TOOLTIP>Unit</TOOLTIP>
    <BTN_USESUBMIT_BEHAVIOUR></BTN_USESUBMIT_BEHAVIOUR>
    <VISIBLE>true</VISIBLE>
    <READONLY>false</READONLY>
    <ENABLE_VIEWSTATE>true</ENABLE_VIEWSTATE>
    <MAXLENGTH></MAXLENGTH>
    <MULTILINE></MULTILINE>
    <WIDTH></WIDTH>
    <HEIGHT></HEIGHT>
    <SECTION_NAME></SECTION_NAME>
    <ONKEY_HANDLER></ONKEY_HANDLER>
    <ONBLUR_HANDLER></ONBLUR_HANDLER>
    <ENABLE_REQUIREVALIDATION>false</ENABLE_REQUIREVALIDATION>
    <REQUIRED_FIELD_MESSAGE>Unit can not be blank</REQUIRED_FIELD_MESSAGE>
    <LOOKUP_NAME></LOOKUP_NAME>
    <IMAGE_URL></IMAGE_URL>
    <CONTROL_TOTAL></CONTROL_TOTAL>
    <TAB_INDEX>11</TAB_INDEX>
    <TEXT_TYPE>ENUM.ACTIVE</TEXT_TYPE>
    <ALLOWCHAR></ALLOWCHAR>
    <DATA_VALIDATE></DATA_VALIDATE>
  </WebFormDefinition>

  <WebFormDefinition>
    <DETAIL_ID>9</DETAIL_ID>
    <FORM_ID>732</FORM_ID>
    <HTML_CONTROL_ID>AirlineSno</HTML_CONTROL_ID>
    <DISPLAY_ORDER>9</DISPLAY_ORDER>
    <ASSEMBLY_NAME>HTML.AutoCompleteTextBox</ASSEMBLY_NAME>
    <LABEL_CELL_TEXT>Airline</LABEL_CELL_TEXT>
    <LABEL_CELL_CSSCLASS>formlabel</LABEL_CELL_CSSCLASS>
    <DATA_FIELDNAME>AirlineSno</DATA_FIELDNAME>
    <DATA_FIELD_CSSCLASS></DATA_FIELD_CSSCLASS>
    <DATA_CELL_CSSCLASS>formInputcolumn</DATA_CELL_CSSCLASS>
    <ONCLICK_HANDLER></ONCLICK_HANDLER>
    <POSTBACK_URL></POSTBACK_URL>
    <CALLBACK_URL></CALLBACK_URL>
    <SKIN_ID></SKIN_ID>
    <TOOLTIP>Airline</TOOLTIP>
    <BTN_USESUBMIT_BEHAVIOUR></BTN_USESUBMIT_BEHAVIOUR>
    <VISIBLE>true</VISIBLE>
    <READONLY>false</READONLY>
    <ENABLE_VIEWSTATE>true</ENABLE_VIEWSTATE>
    <MAXLENGTH></MAXLENGTH>
    <MULTILINE></MULTILINE>
    <WIDTH>200</WIDTH>
    <HEIGHT></HEIGHT>
    <SECTION_NAME></SECTION_NAME>
    <ONKEY_HANDLER></ONKEY_HANDLER>
    <ONBLUR_HANDLER></ONBLUR_HANDLER>
    <ENABLE_REQUIREVALIDATION>true</ENABLE_REQUIREVALIDATION>
    <REQUIRED_FIELD_MESSAGE>Airline can not be blank</REQUIRED_FIELD_MESSAGE>
    <LOOKUP_NAME></LOOKUP_NAME>
    <IMAGE_URL></IMAGE_URL>
    <CONTROL_TOTAL></CONTROL_TOTAL>
    <TAB_INDEX>9</TAB_INDEX>
    <TEXT_TYPE>UPPERCASE</TEXT_TYPE>
    <ALLOWCHAR></ALLOWCHAR>
    <DATA_VALIDATE>required</DATA_VALIDATE>
  </WebFormDefinition>


  <WebFormDefinition>
    <DETAIL_ID>10</DETAIL_ID>
    <FORM_ID>732</FORM_ID>
    <HTML_CONTROL_ID>CommonDesignation</HTML_CONTROL_ID>
    <DISPLAY_ORDER>10</DISPLAY_ORDER>
    <ASSEMBLY_NAME>HTML.TextBox</ASSEMBLY_NAME>
    <LABEL_CELL_TEXT>Common Designation</LABEL_CELL_TEXT>
    <LABEL_CELL_CSSCLASS>formlabel</LABEL_CELL_CSSCLASS>
    <DATA_FIELDNAME>CommonDesignation</DATA_FIELDNAME>
    <DATA_FIELD_CSSCLASS></DATA_FIELD_CSSCLASS>
    <DATA_CELL_CSSCLASS>formInputcolumn</DATA_CELL_CSSCLASS>
    <ONCLICK_HANDLER></ONCLICK_HANDLER>
    <POSTBACK_URL></POSTBACK_URL>
    <CALLBACK_URL></CALLBACK_URL>
    <SKIN_ID></SKIN_ID>
    <TOOLTIP>Common Designation</TOOLTIP>
    <BTN_USESUBMIT_BEHAVIOUR></BTN_USESUBMIT_BEHAVIOUR>
    <VISIBLE>true</VISIBLE>
    <READONLY>false</READONLY>
    <ENABLE_VIEWSTATE>true</ENABLE_VIEWSTATE>
    <MAXLENGTH>49</MAXLENGTH>
    <MULTILINE>YES</MULTILINE>
    <WIDTH>200</WIDTH>
    <HEIGHT></HEIGHT>
    <SECTION_NAME></SECTION_NAME>
    <ONKEY_HANDLER></ONKEY_HANDLER>
    <ONBLUR_HANDLER></ONBLUR_HANDLER>
    <ENABLE_REQUIREVALIDATION>false</ENABLE_REQUIREVALIDATION>
    <REQUIRED_FIELD_MESSAGE>Common Designation can not be blank</REQUIRED_FIELD_MESSAGE>
    <LOOKUP_NAME></LOOKUP_NAME>
    <IMAGE_URL></IMAGE_URL>
    <CONTROL_TOTAL></CONTROL_TOTAL>
    <TAB_INDEX>10</TAB_INDEX>
    <TEXT_TYPE>UPPERCASE</TEXT_TYPE>
    <ALLOWCHAR></ALLOWCHAR>
    <DATA_VALIDATE></DATA_VALIDATE>
  </WebFormDefinition>


  <WebFormDefinition>
    <DETAIL_ID>11</DETAIL_ID>
    <FORM_ID>732</FORM_ID>
    <HTML_CONTROL_ID>IsActive</HTML_CONTROL_ID>
    <DISPLAY_ORDER>11</DISPLAY_ORDER>
    <ASSEMBLY_NAME>HTML.RadioButtonList</ASSEMBLY_NAME>
    <LABEL_CELL_TEXT>Active</LABEL_CELL_TEXT>
    <LABEL_CELL_CSSCLASS>formlabel</LABEL_CELL_CSSCLASS>
    <DATA_FIELDNAME>IsActive</DATA_FIELDNAME>
    <DATA_FIELD_CSSCLASS></DATA_FIELD_CSSCLASS>
    <DATA_CELL_CSSCLASS>formInputcolumn</DATA_CELL_CSSCLASS>
    <ONCLICK_HANDLER></ONCLICK_HANDLER>
    <POSTBACK_URL></POSTBACK_URL>
    <CALLBACK_URL></CALLBACK_URL>
    <SKIN_ID></SKIN_ID>
    <TOOLTIP>Active</TOOLTIP>
    <BTN_USESUBMIT_BEHAVIOUR></BTN_USESUBMIT_BEHAVIOUR>
    <VISIBLE>true</VISIBLE>
    <READONLY>false</READONLY>
    <ENABLE_VIEWSTATE>true</ENABLE_VIEWSTATE>
    <MAXLENGTH></MAXLENGTH>
    <MULTILINE></MULTILINE>
    <WIDTH></WIDTH>
    <HEIGHT></HEIGHT>
    <SECTION_NAME></SECTION_NAME>
    <ONKEY_HANDLER></ONKEY_HANDLER>
    <ONBLUR_HANDLER></ONBLUR_HANDLER>
    <ENABLE_REQUIREVALIDATION>false</ENABLE_REQUIREVALIDATION>
    <REQUIRED_FIELD_MESSAGE>Active can not be blank</REQUIRED_FIELD_MESSAGE>
    <LOOKUP_NAME></LOOKUP_NAME>
    <IMAGE_URL></IMAGE_URL>
    <CONTROL_TOTAL></CONTROL_TOTAL>
    <TAB_INDEX>11</TAB_INDEX>
    <TEXT_TYPE>ENUM.ACTIVE</TEXT_TYPE>
    <ALLOWCHAR></ALLOWCHAR>
    <DATA_VALIDATE></DATA_VALIDATE>
  </WebFormDefinition>
  <WebFormDefinition>
    <DETAIL_ID>12</DETAIL_ID>
    <FORM_ID>732</FORM_ID>
    <HTML_CONTROL_ID></HTML_CONTROL_ID>
    <DISPLAY_ORDER>12</DISPLAY_ORDER>
    <ASSEMBLY_NAME>HTML.Label</ASSEMBLY_NAME>
    <LABEL_CELL_TEXT></LABEL_CELL_TEXT>
    <LABEL_CELL_CSSCLASS>formlabel</LABEL_CELL_CSSCLASS>
    <DATA_FIELDNAME></DATA_FIELDNAME>
    <DATA_FIELD_CSSCLASS></DATA_FIELD_CSSCLASS>
    <DATA_CELL_CSSCLASS>formInputcolumn</DATA_CELL_CSSCLASS>
    <ONCLICK_HANDLER></ONCLICK_HANDLER>
    <POSTBACK_URL></POSTBACK_URL>
    <CALLBACK_URL></CALLBACK_URL>
    <SKIN_ID></SKIN_ID>
    <TOOLTIP></TOOLTIP>
    <BTN_USESUBMIT_BEHAVIOUR></BTN_USESUBMIT_BEHAVIOUR>
    <VISIBLE>true</VISIBLE>
    <READONLY>true</READONLY>
    <ENABLE_VIEWSTATE>true</ENABLE_VIEWSTATE>
    <MAXLENGTH></MAXLENGTH>
    <MULTILINE></MULTILINE>
    <WIDTH></WIDTH>
    <HEIGHT></HEIGHT>
    <SECTION_NAME></SECTION_NAME>
    <ONKEY_HANDLER></ONKEY_HANDLER>
    <ONBLUR_HANDLER></ONBLUR_HANDLER>
    <ENABLE_REQUIREVALIDATION>false</ENABLE_REQUIREVALIDATION>
    <REQUIRED_FIELD_MESSAGE></REQUIRED_FIELD_MESSAGE>
    <LOOKUP_NAME></LOOKUP_NAME>
    <IMAGE_URL></IMAGE_URL>
    <CONTROL_TOTAL></CONTROL_TOTAL>
    <TAB_INDEX>12</TAB_INDEX>
    <TEXT_TYPE></TEXT_TYPE>
    <ALLOWCHAR></ALLOWCHAR>
    <DATA_VALIDATE></DATA_VALIDATE>
  </WebFormDefinition>

   
  <WebFormDefinition>
    <DETAIL_ID>13</DETAIL_ID>
    <FORM_ID>732</FORM_ID>
    <HTML_CONTROL_ID>LabelUpdateBy</HTML_CONTROL_ID>
    <DISPLAY_ORDER>13</DISPLAY_ORDER>
    <ASSEMBLY_NAME>HTML.Label</ASSEMBLY_NAME>
    <LABEL_CELL_TEXT> Updated By</LABEL_CELL_TEXT>
    <LABEL_CELL_CSSCLASS>formlabel</LABEL_CELL_CSSCLASS>
    <DATA_FIELDNAME>UpdatedBy</DATA_FIELDNAME>
    <DATA_FIELD_CSSCLASS></DATA_FIELD_CSSCLASS>
    <DATA_CELL_CSSCLASS>formInputcolumn</DATA_CELL_CSSCLASS>
    <ONCLICK_HANDLER></ONCLICK_HANDLER>
    <POSTBACK_URL></POSTBACK_URL>
    <CALLBACK_URL></CALLBACK_URL>
    <SKIN_ID></SKIN_ID>
    <TOOLTIP></TOOLTIP>
    <BTN_USESUBMIT_BEHAVIOUR>true</BTN_USESUBMIT_BEHAVIOUR>
    <VISIBLE>true</VISIBLE>
    <READONLY>true</READONLY>
    <ENABLE_VIEWSTATE>true</ENABLE_VIEWSTATE>
    <MAXLENGTH></MAXLENGTH>
    <MULTILINE></MULTILINE>
    <WIDTH></WIDTH>
    <HEIGHT></HEIGHT>
    <SECTION_NAME>User Action Information</SECTION_NAME>
    <ONKEY_HANDLER></ONKEY_HANDLER>
    <ONBLUR_HANDLER></ONBLUR_HANDLER>
    <ENABLE_REQUIREVALIDATION>false</ENABLE_REQUIREVALIDATION>
    <REQUIRED_FIELD_MESSAGE></REQUIRED_FIELD_MESSAGE>
    <LOOKUP_NAME></LOOKUP_NAME>
    <IMAGE_URL></IMAGE_URL>
    <CONTROL_TOTAL></CONTROL_TOTAL>
    <TAB_INDEX>13</TAB_INDEX>
    <TEXT_TYPE></TEXT_TYPE>
    <ALLOWCHAR></ALLOWCHAR>
    <DATA_VALIDATE></DATA_VALIDATE>

  </WebFormDefinition>

  <WebFormDefinition>
    <DETAIL_ID>14</DETAIL_ID>
    <FORM_ID>732</FORM_ID>
    <HTML_CONTROL_ID></HTML_CONTROL_ID>
    <DISPLAY_ORDER>14</DISPLAY_ORDER>
    <ASSEMBLY_NAME>HTML.Label</ASSEMBLY_NAME>
    <LABEL_CELL_TEXT></LABEL_CELL_TEXT>
    <LABEL_CELL_CSSCLASS>formlabel</LABEL_CELL_CSSCLASS>
    <DATA_FIELDNAME></DATA_FIELDNAME>
    <DATA_FIELD_CSSCLASS></DATA_FIELD_CSSCLASS>
    <DATA_CELL_CSSCLASS>formInputcolumn</DATA_CELL_CSSCLASS>
    <ONCLICK_HANDLER></ONCLICK_HANDLER>
    <POSTBACK_URL></POSTBACK_URL>
    <CALLBACK_URL></CALLBACK_URL>
    <SKIN_ID></SKIN_ID>
    <TOOLTIP></TOOLTIP>
    <BTN_USESUBMIT_BEHAVIOUR></BTN_USESUBMIT_BEHAVIOUR>
    <VISIBLE>true</VISIBLE>
    <READONLY>true</READONLY>
    <ENABLE_VIEWSTATE>true</ENABLE_VIEWSTATE>
    <MAXLENGTH></MAXLENGTH>
    <MULTILINE></MULTILINE>
    <WIDTH></WIDTH>
    <HEIGHT></HEIGHT>
    <SECTION_NAME></SECTION_NAME>
    <ONKEY_HANDLER></ONKEY_HANDLER>
    <ONBLUR_HANDLER></ONBLUR_HANDLER>
    <ENABLE_REQUIREVALIDATION>false</ENABLE_REQUIREVALIDATION>
    <REQUIRED_FIELD_MESSAGE></REQUIRED_FIELD_MESSAGE>
    <LOOKUP_NAME></LOOKUP_NAME>
    <IMAGE_URL></IMAGE_URL>
    <CONTROL_TOTAL></CONTROL_TOTAL>
    <TAB_INDEX>14</TAB_INDEX>
    <TEXT_TYPE></TEXT_TYPE>
    <ALLOWCHAR></ALLOWCHAR>
    <DATA_VALIDATE></DATA_VALIDATE>
  </WebFormDefinition>-->

  <!--END-->

  <!--View ULD Type Details-->

  <WebFormDefinition>
    <DETAIL_ID>1</DETAIL_ID>
    <FORM_ID>733</FORM_ID>
    <HTML_CONTROL_ID>ULDCode</HTML_CONTROL_ID>
    <DISPLAY_ORDER>1</DISPLAY_ORDER>
    <ASSEMBLY_NAME>HTML.Label</ASSEMBLY_NAME>
    <LABEL_CELL_TEXT>ULD Code</LABEL_CELL_TEXT>
    <LABEL_CELL_CSSCLASS>formlabel</LABEL_CELL_CSSCLASS>
    <DATA_FIELDNAME>ULDCode</DATA_FIELDNAME>
    <DATA_FIELD_CSSCLASS></DATA_FIELD_CSSCLASS>
    <DATA_CELL_CSSCLASS>formInputcolumn</DATA_CELL_CSSCLASS>
    <ONCLICK_HANDLER></ONCLICK_HANDLER>
    <POSTBACK_URL></POSTBACK_URL>
    <CALLBACK_URL></CALLBACK_URL>
    <SKIN_ID></SKIN_ID>
    <TOOLTIP>ULD Code</TOOLTIP>
    <BTN_USESUBMIT_BEHAVIOUR></BTN_USESUBMIT_BEHAVIOUR>
    <VISIBLE>true</VISIBLE>
    <READONLY>true</READONLY>
    <ENABLE_VIEWSTATE>true</ENABLE_VIEWSTATE>
    <MAXLENGTH></MAXLENGTH>
    <MULTILINE></MULTILINE>
    <WIDTH></WIDTH>
    <HEIGHT></HEIGHT>
    <SECTION_NAME>ULD Code Information</SECTION_NAME>
    <ONKEY_HANDLER></ONKEY_HANDLER>
    <ONBLUR_HANDLER></ONBLUR_HANDLER>
    <ENABLE_REQUIREVALIDATION>false</ENABLE_REQUIREVALIDATION>
    <REQUIRED_FIELD_MESSAGE></REQUIRED_FIELD_MESSAGE>
    <LOOKUP_NAME></LOOKUP_NAME>
    <IMAGE_URL></IMAGE_URL>
    <CONTROL_TOTAL></CONTROL_TOTAL>
    <TAB_INDEX>1</TAB_INDEX>
    <TEXT_TYPE>UPPERCASE</TEXT_TYPE>
    <ALLOWCHAR></ALLOWCHAR>
    <DATA_VALIDATE></DATA_VALIDATE>
  </WebFormDefinition>

 

  <WebFormDefinition>
    <DETAIL_ID>2</DETAIL_ID>
    <FORM_ID>733</FORM_ID>
    <HTML_CONTROL_ID>AirlineSno</HTML_CONTROL_ID>
    <DISPLAY_ORDER>2</DISPLAY_ORDER>
    <ASSEMBLY_NAME>HTML.Label</ASSEMBLY_NAME>
    <LABEL_CELL_TEXT>Airline</LABEL_CELL_TEXT>
    <LABEL_CELL_CSSCLASS>formlabel</LABEL_CELL_CSSCLASS>
    <DATA_FIELDNAME>Text_AirlineSno</DATA_FIELDNAME>
    <DATA_FIELD_CSSCLASS></DATA_FIELD_CSSCLASS>
    <DATA_CELL_CSSCLASS>formInputcolumn</DATA_CELL_CSSCLASS>
    <ONCLICK_HANDLER></ONCLICK_HANDLER>
    <POSTBACK_URL></POSTBACK_URL>
    <CALLBACK_URL></CALLBACK_URL>
    <SKIN_ID></SKIN_ID>
    <TOOLTIP>Airline</TOOLTIP>
    <BTN_USESUBMIT_BEHAVIOUR></BTN_USESUBMIT_BEHAVIOUR>
    <VISIBLE>true</VISIBLE>
    <READONLY>true</READONLY>
    <ENABLE_VIEWSTATE>true</ENABLE_VIEWSTATE>
    <MAXLENGTH></MAXLENGTH>
    <MULTILINE></MULTILINE>
    <WIDTH></WIDTH>
    <HEIGHT></HEIGHT>
    <SECTION_NAME></SECTION_NAME>
    <ONKEY_HANDLER></ONKEY_HANDLER>
    <ONBLUR_HANDLER></ONBLUR_HANDLER>
    <ENABLE_REQUIREVALIDATION>false</ENABLE_REQUIREVALIDATION>
    <REQUIRED_FIELD_MESSAGE></REQUIRED_FIELD_MESSAGE>
    <LOOKUP_NAME></LOOKUP_NAME>
    <IMAGE_URL></IMAGE_URL>
    <CONTROL_TOTAL></CONTROL_TOTAL>
    <TAB_INDEX>2</TAB_INDEX>
    <TEXT_TYPE></TEXT_TYPE>
    <ALLOWCHAR></ALLOWCHAR>
    <DATA_VALIDATE></DATA_VALIDATE>
  </WebFormDefinition>

  <WebFormDefinition>
    <DETAIL_ID>3</DETAIL_ID>
    <FORM_ID>733</FORM_ID>
    <HTML_CONTROL_ID>RateClass</HTML_CONTROL_ID>
    <DISPLAY_ORDER>3</DISPLAY_ORDER>
    <ASSEMBLY_NAME>HTML.Label</ASSEMBLY_NAME>
    <LABEL_CELL_TEXT>ULD Class</LABEL_CELL_TEXT>
    <LABEL_CELL_CSSCLASS>formlabel</LABEL_CELL_CSSCLASS>
    <DATA_FIELDNAME>Text_RateClassSno</DATA_FIELDNAME>
    <DATA_FIELD_CSSCLASS></DATA_FIELD_CSSCLASS>
    <DATA_CELL_CSSCLASS>formInputcolumn</DATA_CELL_CSSCLASS>
    <ONCLICK_HANDLER></ONCLICK_HANDLER>
    <POSTBACK_URL></POSTBACK_URL>
    <CALLBACK_URL></CALLBACK_URL>
    <SKIN_ID></SKIN_ID>
    <TOOLTIP>Enter ULD Class</TOOLTIP>
    <BTN_USESUBMIT_BEHAVIOUR></BTN_USESUBMIT_BEHAVIOUR>
    <VISIBLE>true</VISIBLE>
    <READONLY>true</READONLY>
    <ENABLE_VIEWSTATE>true</ENABLE_VIEWSTATE>
    <MAXLENGTH></MAXLENGTH>
    <MULTILINE></MULTILINE>
    <WIDTH>50</WIDTH>
    <HEIGHT></HEIGHT>
    <SECTION_NAME></SECTION_NAME>
    <ONKEY_HANDLER></ONKEY_HANDLER>
    <ONBLUR_HANDLER></ONBLUR_HANDLER>
    <ENABLE_REQUIREVALIDATION>false</ENABLE_REQUIREVALIDATION>
    <REQUIRED_FIELD_MESSAGE></REQUIRED_FIELD_MESSAGE>
    <LOOKUP_NAME></LOOKUP_NAME>
    <IMAGE_URL></IMAGE_URL>
    <CONTROL_TOTAL></CONTROL_TOTAL>
    <TAB_INDEX>3</TAB_INDEX>
    <TEXT_TYPE>UPPERCASE</TEXT_TYPE>
    <ALLOWCHAR></ALLOWCHAR>
    <DATA_VALIDATE></DATA_VALIDATE>
  </WebFormDefinition>

  <WebFormDefinition>
    <DETAIL_ID>4</DETAIL_ID>
    <FORM_ID>733</FORM_ID>
    <HTML_CONTROL_ID>EmptyWeight</HTML_CONTROL_ID>
    <DISPLAY_ORDER>4</DISPLAY_ORDER>
    <ASSEMBLY_NAME>HTML.Label</ASSEMBLY_NAME>
    <LABEL_CELL_TEXT>Tare Weight</LABEL_CELL_TEXT>
    <LABEL_CELL_CSSCLASS>formlabel</LABEL_CELL_CSSCLASS>
    <DATA_FIELDNAME>EmptyWeight</DATA_FIELDNAME>
    <DATA_FIELD_CSSCLASS></DATA_FIELD_CSSCLASS>
    <DATA_CELL_CSSCLASS>formInputcolumn</DATA_CELL_CSSCLASS>
    <ONCLICK_HANDLER></ONCLICK_HANDLER>
    <POSTBACK_URL></POSTBACK_URL>
    <CALLBACK_URL></CALLBACK_URL>
    <SKIN_ID></SKIN_ID>
    <TOOLTIP>Tare Weight</TOOLTIP>
    <BTN_USESUBMIT_BEHAVIOUR></BTN_USESUBMIT_BEHAVIOUR>
    <VISIBLE>true</VISIBLE>
    <READONLY>true</READONLY>
    <ENABLE_VIEWSTATE>true</ENABLE_VIEWSTATE>
    <MAXLENGTH></MAXLENGTH>
    <MULTILINE></MULTILINE>
    <WIDTH></WIDTH>
    <HEIGHT></HEIGHT>
    <SECTION_NAME></SECTION_NAME>
    <ONKEY_HANDLER></ONKEY_HANDLER>
    <ONBLUR_HANDLER></ONBLUR_HANDLER>
    <ENABLE_REQUIREVALIDATION>false</ENABLE_REQUIREVALIDATION>
    <REQUIRED_FIELD_MESSAGE></REQUIRED_FIELD_MESSAGE>
    <LOOKUP_NAME></LOOKUP_NAME>
    <IMAGE_URL></IMAGE_URL>
    <CONTROL_TOTAL></CONTROL_TOTAL>
    <TAB_INDEX>4</TAB_INDEX>
    <TEXT_TYPE></TEXT_TYPE>
    <ALLOWCHAR></ALLOWCHAR>
    <DATA_VALIDATE></DATA_VALIDATE>
  </WebFormDefinition>

  <WebFormDefinition>
    <DETAIL_ID>5</DETAIL_ID>
    <FORM_ID>733</FORM_ID>
    <HTML_CONTROL_ID>PivotWeight</HTML_CONTROL_ID>
    <DISPLAY_ORDER>5</DISPLAY_ORDER>
    <ASSEMBLY_NAME>HTML.Label</ASSEMBLY_NAME>
    <LABEL_CELL_TEXT>Pivot Weight</LABEL_CELL_TEXT>
    <LABEL_CELL_CSSCLASS>formlabel</LABEL_CELL_CSSCLASS>
    <DATA_FIELDNAME>PivotWeight</DATA_FIELDNAME>
    <DATA_FIELD_CSSCLASS></DATA_FIELD_CSSCLASS>
    <DATA_CELL_CSSCLASS>formInputcolumn</DATA_CELL_CSSCLASS>
    <ONCLICK_HANDLER></ONCLICK_HANDLER>
    <POSTBACK_URL></POSTBACK_URL>
    <CALLBACK_URL></CALLBACK_URL>
    <SKIN_ID></SKIN_ID>
    <TOOLTIP>Pivot Weight</TOOLTIP>
    <BTN_USESUBMIT_BEHAVIOUR></BTN_USESUBMIT_BEHAVIOUR>
    <VISIBLE>true</VISIBLE>
    <READONLY>true</READONLY>
    <ENABLE_VIEWSTATE>true</ENABLE_VIEWSTATE>
    <MAXLENGTH></MAXLENGTH>
    <MULTILINE></MULTILINE>
    <WIDTH></WIDTH>
    <HEIGHT></HEIGHT>
    <SECTION_NAME></SECTION_NAME>
    <ONKEY_HANDLER></ONKEY_HANDLER>
    <ONBLUR_HANDLER></ONBLUR_HANDLER>
    <ENABLE_REQUIREVALIDATION>false</ENABLE_REQUIREVALIDATION>
    <REQUIRED_FIELD_MESSAGE></REQUIRED_FIELD_MESSAGE>
    <LOOKUP_NAME></LOOKUP_NAME>
    <IMAGE_URL></IMAGE_URL>
    <CONTROL_TOTAL></CONTROL_TOTAL>
    <TAB_INDEX>5</TAB_INDEX>
    <TEXT_TYPE></TEXT_TYPE>
    <ALLOWCHAR></ALLOWCHAR>
    <DATA_VALIDATE></DATA_VALIDATE>
  </WebFormDefinition>
  
  <WebFormDefinition>
    <DETAIL_ID>6</DETAIL_ID>
    <FORM_ID>733</FORM_ID>
    <HTML_CONTROL_ID>GrossWeight</HTML_CONTROL_ID>
    <DISPLAY_ORDER>6</DISPLAY_ORDER>
    <ASSEMBLY_NAME>HTML.Label</ASSEMBLY_NAME>
    <LABEL_CELL_TEXT>Gross Weight</LABEL_CELL_TEXT>
    <LABEL_CELL_CSSCLASS>formlabel</LABEL_CELL_CSSCLASS>
    <DATA_FIELDNAME>GrossWeight</DATA_FIELDNAME>
    <DATA_FIELD_CSSCLASS></DATA_FIELD_CSSCLASS>
    <DATA_CELL_CSSCLASS>formInputcolumn</DATA_CELL_CSSCLASS>
    <ONCLICK_HANDLER></ONCLICK_HANDLER>
    <POSTBACK_URL></POSTBACK_URL>
    <CALLBACK_URL></CALLBACK_URL>
    <SKIN_ID></SKIN_ID>
    <TOOLTIP>Gross Weight</TOOLTIP>
    <BTN_USESUBMIT_BEHAVIOUR></BTN_USESUBMIT_BEHAVIOUR>
    <VISIBLE>true</VISIBLE>
    <READONLY>true</READONLY>
    <ENABLE_VIEWSTATE>true</ENABLE_VIEWSTATE>
    <MAXLENGTH></MAXLENGTH>
    <MULTILINE></MULTILINE>
    <WIDTH></WIDTH>
    <HEIGHT></HEIGHT>
    <SECTION_NAME></SECTION_NAME>
    <ONKEY_HANDLER></ONKEY_HANDLER>
    <ONBLUR_HANDLER></ONBLUR_HANDLER>
    <ENABLE_REQUIREVALIDATION>false</ENABLE_REQUIREVALIDATION>
    <REQUIRED_FIELD_MESSAGE></REQUIRED_FIELD_MESSAGE>
    <LOOKUP_NAME></LOOKUP_NAME>
    <IMAGE_URL></IMAGE_URL>
    <CONTROL_TOTAL></CONTROL_TOTAL>
    <TAB_INDEX>6</TAB_INDEX>
    <TEXT_TYPE></TEXT_TYPE>
    <ALLOWCHAR></ALLOWCHAR>
    <DATA_VALIDATE></DATA_VALIDATE>
  </WebFormDefinition>

  <WebFormDefinition>
    <DETAIL_ID>7</DETAIL_ID>
    <FORM_ID>733</FORM_ID>
    <HTML_CONTROL_ID>VolumeWeight</HTML_CONTROL_ID>
    <DISPLAY_ORDER>7</DISPLAY_ORDER>
    <ASSEMBLY_NAME>HTML.Label</ASSEMBLY_NAME>
    <LABEL_CELL_TEXT>Volume</LABEL_CELL_TEXT>
    <LABEL_CELL_CSSCLASS>formlabel</LABEL_CELL_CSSCLASS>
    <DATA_FIELDNAME>VolumeWeight</DATA_FIELDNAME>
    <DATA_FIELD_CSSCLASS></DATA_FIELD_CSSCLASS>
    <DATA_CELL_CSSCLASS>formInputcolumn</DATA_CELL_CSSCLASS>
    <ONCLICK_HANDLER></ONCLICK_HANDLER>
    <POSTBACK_URL></POSTBACK_URL>
    <CALLBACK_URL></CALLBACK_URL>
    <SKIN_ID></SKIN_ID>
    <TOOLTIP>Volume Weight</TOOLTIP>
    <BTN_USESUBMIT_BEHAVIOUR></BTN_USESUBMIT_BEHAVIOUR>
    <VISIBLE>true</VISIBLE>
    <READONLY>true</READONLY>
    <ENABLE_VIEWSTATE>true</ENABLE_VIEWSTATE>
    <MAXLENGTH></MAXLENGTH>
    <MULTILINE></MULTILINE>
    <WIDTH></WIDTH>
    <HEIGHT></HEIGHT>
    <SECTION_NAME></SECTION_NAME>
    <ONKEY_HANDLER></ONKEY_HANDLER>
    <ONBLUR_HANDLER></ONBLUR_HANDLER>
    <ENABLE_REQUIREVALIDATION>false</ENABLE_REQUIREVALIDATION>
    <REQUIRED_FIELD_MESSAGE></REQUIRED_FIELD_MESSAGE>
    <LOOKUP_NAME></LOOKUP_NAME>
    <IMAGE_URL></IMAGE_URL>
    <CONTROL_TOTAL></CONTROL_TOTAL>
    <TAB_INDEX>7</TAB_INDEX>
    <TEXT_TYPE></TEXT_TYPE>
    <ALLOWCHAR></ALLOWCHAR>
    <DATA_VALIDATE></DATA_VALIDATE>
  </WebFormDefinition>



  <WebFormDefinition>
    <DETAIL_ID>9</DETAIL_ID>
    <FORM_ID>733</FORM_ID>
    <HTML_CONTROL_ID>Text_Units</HTML_CONTROL_ID>
    <DISPLAY_ORDER>9</DISPLAY_ORDER>
    <ASSEMBLY_NAME>HTML.Label</ASSEMBLY_NAME>
    <LABEL_CELL_TEXT>Measurement Unit</LABEL_CELL_TEXT>
    <LABEL_CELL_CSSCLASS>formlabel</LABEL_CELL_CSSCLASS>
    <DATA_FIELDNAME>Text_Units</DATA_FIELDNAME>
    <DATA_FIELD_CSSCLASS></DATA_FIELD_CSSCLASS>
    <DATA_CELL_CSSCLASS>formInputcolumn</DATA_CELL_CSSCLASS>
    <ONCLICK_HANDLER></ONCLICK_HANDLER>
    <POSTBACK_URL></POSTBACK_URL>
    <CALLBACK_URL></CALLBACK_URL>
    <SKIN_ID></SKIN_ID>
    <TOOLTIP>Measurement Unit</TOOLTIP>
    <BTN_USESUBMIT_BEHAVIOUR></BTN_USESUBMIT_BEHAVIOUR>
    <VISIBLE>true</VISIBLE>
    <READONLY>true</READONLY>
    <ENABLE_VIEWSTATE>true</ENABLE_VIEWSTATE>
    <MAXLENGTH></MAXLENGTH>
    <MULTILINE></MULTILINE>
    <WIDTH></WIDTH>
    <HEIGHT></HEIGHT>
    <SECTION_NAME></SECTION_NAME>
    <ONKEY_HANDLER></ONKEY_HANDLER>
    <ONBLUR_HANDLER></ONBLUR_HANDLER>
    <ENABLE_REQUIREVALIDATION>false</ENABLE_REQUIREVALIDATION>
    <REQUIRED_FIELD_MESSAGE></REQUIRED_FIELD_MESSAGE>
    <LOOKUP_NAME></LOOKUP_NAME>
    <IMAGE_URL></IMAGE_URL>
    <CONTROL_TOTAL></CONTROL_TOTAL>
    <TAB_INDEX>9</TAB_INDEX>
    <TEXT_TYPE></TEXT_TYPE>
    <ALLOWCHAR></ALLOWCHAR>
    <DATA_VALIDATE></DATA_VALIDATE>
  </WebFormDefinition>

  <WebFormDefinition>
    <DETAIL_ID>10</DETAIL_ID>
    <FORM_ID>733</FORM_ID>
    <HTML_CONTROL_ID>Length</HTML_CONTROL_ID>
    <DISPLAY_ORDER>10</DISPLAY_ORDER>
    <ASSEMBLY_NAME>HTML.Label</ASSEMBLY_NAME>
    <LABEL_CELL_TEXT>Length</LABEL_CELL_TEXT>
    <LABEL_CELL_CSSCLASS>formlabel</LABEL_CELL_CSSCLASS>
    <DATA_FIELDNAME>Length</DATA_FIELDNAME>
    <DATA_FIELD_CSSCLASS></DATA_FIELD_CSSCLASS>
    <DATA_CELL_CSSCLASS>formInputcolumn</DATA_CELL_CSSCLASS>
    <ONCLICK_HANDLER></ONCLICK_HANDLER>
    <POSTBACK_URL></POSTBACK_URL>
    <CALLBACK_URL></CALLBACK_URL>
    <SKIN_ID></SKIN_ID>
    <TOOLTIP>Length</TOOLTIP>
    <BTN_USESUBMIT_BEHAVIOUR></BTN_USESUBMIT_BEHAVIOUR>
    <VISIBLE>true</VISIBLE>
    <READONLY>true</READONLY>
    <ENABLE_VIEWSTATE>true</ENABLE_VIEWSTATE>
    <MAXLENGTH></MAXLENGTH>
    <MULTILINE></MULTILINE>
    <WIDTH></WIDTH>
    <HEIGHT></HEIGHT>
    <SECTION_NAME></SECTION_NAME>
    <ONKEY_HANDLER></ONKEY_HANDLER>
    <ONBLUR_HANDLER></ONBLUR_HANDLER>
    <ENABLE_REQUIREVALIDATION>false</ENABLE_REQUIREVALIDATION>
    <REQUIRED_FIELD_MESSAGE></REQUIRED_FIELD_MESSAGE>
    <LOOKUP_NAME></LOOKUP_NAME>
    <IMAGE_URL></IMAGE_URL>
    <CONTROL_TOTAL></CONTROL_TOTAL>
    <TAB_INDEX>10</TAB_INDEX>
    <TEXT_TYPE></TEXT_TYPE>
    <ALLOWCHAR></ALLOWCHAR>
    <DATA_VALIDATE></DATA_VALIDATE>
  </WebFormDefinition>

  <WebFormDefinition>
    <DETAIL_ID>11</DETAIL_ID>
    <FORM_ID>733</FORM_ID>
    <HTML_CONTROL_ID>Width</HTML_CONTROL_ID>
    <DISPLAY_ORDER>11</DISPLAY_ORDER>
    <ASSEMBLY_NAME>HTML.Label</ASSEMBLY_NAME>
    <LABEL_CELL_TEXT>Width</LABEL_CELL_TEXT>
    <LABEL_CELL_CSSCLASS>formlabel</LABEL_CELL_CSSCLASS>
    <DATA_FIELDNAME>Width</DATA_FIELDNAME>
    <DATA_FIELD_CSSCLASS></DATA_FIELD_CSSCLASS>
    <DATA_CELL_CSSCLASS>formInputcolumn</DATA_CELL_CSSCLASS>
    <ONCLICK_HANDLER></ONCLICK_HANDLER>
    <POSTBACK_URL></POSTBACK_URL>
    <CALLBACK_URL></CALLBACK_URL>
    <SKIN_ID></SKIN_ID>
    <TOOLTIP>Width</TOOLTIP>
    <BTN_USESUBMIT_BEHAVIOUR></BTN_USESUBMIT_BEHAVIOUR>
    <VISIBLE>true</VISIBLE>
    <READONLY>true</READONLY>
    <ENABLE_VIEWSTATE>true</ENABLE_VIEWSTATE>
    <MAXLENGTH></MAXLENGTH>
    <MULTILINE></MULTILINE>
    <WIDTH></WIDTH>
    <HEIGHT></HEIGHT>
    <SECTION_NAME></SECTION_NAME>
    <ONKEY_HANDLER></ONKEY_HANDLER>
    <ONBLUR_HANDLER></ONBLUR_HANDLER>
    <ENABLE_REQUIREVALIDATION>false</ENABLE_REQUIREVALIDATION>
    <REQUIRED_FIELD_MESSAGE></REQUIRED_FIELD_MESSAGE>
    <LOOKUP_NAME></LOOKUP_NAME>
    <IMAGE_URL></IMAGE_URL>
    <CONTROL_TOTAL></CONTROL_TOTAL>
    <TAB_INDEX>11</TAB_INDEX>
    <TEXT_TYPE></TEXT_TYPE>
    <ALLOWCHAR></ALLOWCHAR>
    <DATA_VALIDATE></DATA_VALIDATE>
  </WebFormDefinition>

  <WebFormDefinition>
    <DETAIL_ID>12</DETAIL_ID>
    <FORM_ID>733</FORM_ID>
    <HTML_CONTROL_ID>Height</HTML_CONTROL_ID>
    <DISPLAY_ORDER>12</DISPLAY_ORDER>
    <ASSEMBLY_NAME>HTML.Label</ASSEMBLY_NAME>
    <LABEL_CELL_TEXT>Height</LABEL_CELL_TEXT>
    <LABEL_CELL_CSSCLASS>formlabel</LABEL_CELL_CSSCLASS>
    <DATA_FIELDNAME>Height</DATA_FIELDNAME>
    <DATA_FIELD_CSSCLASS></DATA_FIELD_CSSCLASS>
    <DATA_CELL_CSSCLASS>formInputcolumn</DATA_CELL_CSSCLASS>
    <ONCLICK_HANDLER></ONCLICK_HANDLER>
    <POSTBACK_URL></POSTBACK_URL>
    <CALLBACK_URL></CALLBACK_URL>
    <SKIN_ID></SKIN_ID>
    <TOOLTIP>Height</TOOLTIP>
    <BTN_USESUBMIT_BEHAVIOUR></BTN_USESUBMIT_BEHAVIOUR>
    <VISIBLE>true</VISIBLE>
    <READONLY>false</READONLY>
    <ENABLE_VIEWSTATE>true</ENABLE_VIEWSTATE>
    <MAXLENGTH></MAXLENGTH>
    <MULTILINE></MULTILINE>
    <WIDTH></WIDTH>
    <HEIGHT></HEIGHT>
    <SECTION_NAME></SECTION_NAME>
    <ONKEY_HANDLER></ONKEY_HANDLER>
    <ONBLUR_HANDLER></ONBLUR_HANDLER>
    <ENABLE_REQUIREVALIDATION>false</ENABLE_REQUIREVALIDATION>
    <REQUIRED_FIELD_MESSAGE></REQUIRED_FIELD_MESSAGE>
    <LOOKUP_NAME></LOOKUP_NAME>
    <IMAGE_URL></IMAGE_URL>
    <CONTROL_TOTAL></CONTROL_TOTAL>
    <TAB_INDEX>12</TAB_INDEX>
    <TEXT_TYPE></TEXT_TYPE>
    <ALLOWCHAR></ALLOWCHAR>
    <DATA_VALIDATE></DATA_VALIDATE>
  </WebFormDefinition>

  <WebFormDefinition>
    <DETAIL_ID>13</DETAIL_ID>
    <FORM_ID>733</FORM_ID>
    <HTML_CONTROL_ID>ULDdescription</HTML_CONTROL_ID>
    <DISPLAY_ORDER>13</DISPLAY_ORDER>
    <ASSEMBLY_NAME>HTML.Label</ASSEMBLY_NAME>
    <LABEL_CELL_TEXT>ULD Description</LABEL_CELL_TEXT>
    <LABEL_CELL_CSSCLASS>formlabel</LABEL_CELL_CSSCLASS>
    <DATA_FIELDNAME>ULDdescription</DATA_FIELDNAME>
    <DATA_FIELD_CSSCLASS></DATA_FIELD_CSSCLASS>
    <DATA_CELL_CSSCLASS>formInputcolumn</DATA_CELL_CSSCLASS>
    <ONCLICK_HANDLER></ONCLICK_HANDLER>
    <POSTBACK_URL></POSTBACK_URL>
    <CALLBACK_URL></CALLBACK_URL>
    <SKIN_ID></SKIN_ID>
    <TOOLTIP>ULD Description</TOOLTIP>
    <BTN_USESUBMIT_BEHAVIOUR></BTN_USESUBMIT_BEHAVIOUR>
    <VISIBLE>true</VISIBLE>
    <READONLY>true</READONLY>
    <ENABLE_VIEWSTATE>true</ENABLE_VIEWSTATE>
    <MAXLENGTH></MAXLENGTH>
    <MULTILINE></MULTILINE>
    <WIDTH></WIDTH>
    <HEIGHT></HEIGHT>
    <SECTION_NAME></SECTION_NAME>
    <ONKEY_HANDLER></ONKEY_HANDLER>
    <ONBLUR_HANDLER></ONBLUR_HANDLER>
    <ENABLE_REQUIREVALIDATION></ENABLE_REQUIREVALIDATION>
    <REQUIRED_FIELD_MESSAGE></REQUIRED_FIELD_MESSAGE>
    <LOOKUP_NAME></LOOKUP_NAME>
    <IMAGE_URL></IMAGE_URL>
    <CONTROL_TOTAL></CONTROL_TOTAL>
    <TAB_INDEX>13</TAB_INDEX>
    <TEXT_TYPE></TEXT_TYPE>
    <ALLOWCHAR></ALLOWCHAR>
    <DATA_VALIDATE></DATA_VALIDATE>
  </WebFormDefinition>

  <WebFormDefinition>
    <DETAIL_ID>14</DETAIL_ID>
    <FORM_ID>733</FORM_ID>
    <HTML_CONTROL_ID>Text_IsActive</HTML_CONTROL_ID>
    <DISPLAY_ORDER>14</DISPLAY_ORDER>
    <ASSEMBLY_NAME>HTML.Label</ASSEMBLY_NAME>
    <LABEL_CELL_TEXT>Active</LABEL_CELL_TEXT>
    <LABEL_CELL_CSSCLASS>formlabel</LABEL_CELL_CSSCLASS>
    <DATA_FIELDNAME>Text_IsActive</DATA_FIELDNAME>
    <DATA_FIELD_CSSCLASS></DATA_FIELD_CSSCLASS>
    <DATA_CELL_CSSCLASS>formInputcolumn</DATA_CELL_CSSCLASS>
    <ONCLICK_HANDLER></ONCLICK_HANDLER>
    <POSTBACK_URL></POSTBACK_URL>
    <CALLBACK_URL></CALLBACK_URL>
    <SKIN_ID></SKIN_ID>
    <TOOLTIP>Active</TOOLTIP>
    <BTN_USESUBMIT_BEHAVIOUR></BTN_USESUBMIT_BEHAVIOUR>
    <VISIBLE>true</VISIBLE>
    <READONLY>true</READONLY>
    <ENABLE_VIEWSTATE>true</ENABLE_VIEWSTATE>
    <MAXLENGTH></MAXLENGTH>
    <MULTILINE></MULTILINE>
    <WIDTH></WIDTH>
    <HEIGHT></HEIGHT>
    <SECTION_NAME></SECTION_NAME>
    <ONKEY_HANDLER></ONKEY_HANDLER>
    <ONBLUR_HANDLER></ONBLUR_HANDLER>
    <ENABLE_REQUIREVALIDATION>false</ENABLE_REQUIREVALIDATION>
    <REQUIRED_FIELD_MESSAGE>Active can not be blank</REQUIRED_FIELD_MESSAGE>
    <LOOKUP_NAME></LOOKUP_NAME>
    <IMAGE_URL></IMAGE_URL>
    <CONTROL_TOTAL></CONTROL_TOTAL>
    <TAB_INDEX>14</TAB_INDEX>
    <TEXT_TYPE>ENUM.ACTIVE</TEXT_TYPE>
    <ALLOWCHAR></ALLOWCHAR>
    <DATA_VALIDATE></DATA_VALIDATE>
  </WebFormDefinition>

  <WebFormDefinition>
    <DETAIL_ID>15</DETAIL_ID>
    <FORM_ID>733</FORM_ID>
    <HTML_CONTROL_ID></HTML_CONTROL_ID>
    <DISPLAY_ORDER>15</DISPLAY_ORDER>
    <ASSEMBLY_NAME>HTML.Label</ASSEMBLY_NAME>
    <LABEL_CELL_TEXT></LABEL_CELL_TEXT>
    <LABEL_CELL_CSSCLASS>formlabel</LABEL_CELL_CSSCLASS>
    <DATA_FIELDNAME></DATA_FIELDNAME>
    <DATA_FIELD_CSSCLASS></DATA_FIELD_CSSCLASS>
    <DATA_CELL_CSSCLASS>formInputcolumn</DATA_CELL_CSSCLASS>
    <ONCLICK_HANDLER></ONCLICK_HANDLER>
    <POSTBACK_URL></POSTBACK_URL>
    <CALLBACK_URL></CALLBACK_URL>
    <SKIN_ID></SKIN_ID>
    <TOOLTIP></TOOLTIP>
    <BTN_USESUBMIT_BEHAVIOUR></BTN_USESUBMIT_BEHAVIOUR>
    <VISIBLE>true</VISIBLE>
    <READONLY>true</READONLY>
    <ENABLE_VIEWSTATE>true</ENABLE_VIEWSTATE>
    <MAXLENGTH></MAXLENGTH>
    <MULTILINE></MULTILINE>
    <WIDTH></WIDTH>
    <HEIGHT></HEIGHT>
    <SECTION_NAME></SECTION_NAME>
    <ONKEY_HANDLER></ONKEY_HANDLER>
    <ONBLUR_HANDLER></ONBLUR_HANDLER>
    <ENABLE_REQUIREVALIDATION>false</ENABLE_REQUIREVALIDATION>
    <REQUIRED_FIELD_MESSAGE></REQUIRED_FIELD_MESSAGE>
    <LOOKUP_NAME></LOOKUP_NAME>
    <IMAGE_URL></IMAGE_URL>
    <CONTROL_TOTAL></CONTROL_TOTAL>
    <TAB_INDEX>15</TAB_INDEX>
    <TEXT_TYPE>UPPERCASE</TEXT_TYPE>
    <ALLOWCHAR></ALLOWCHAR>
    <DATA_VALIDATE></DATA_VALIDATE>
  </WebFormDefinition>
  
  
  
  <WebFormDefinition>
    <DETAIL_ID>16</DETAIL_ID>
    <FORM_ID>733</FORM_ID>
    <HTML_CONTROL_ID>ULDType</HTML_CONTROL_ID>
    <DISPLAY_ORDER>16</DISPLAY_ORDER>
    <ASSEMBLY_NAME>HTML.Label</ASSEMBLY_NAME>
    <LABEL_CELL_TEXT></LABEL_CELL_TEXT>
    <LABEL_CELL_CSSCLASS>formlabel</LABEL_CELL_CSSCLASS>
    <DATA_FIELDNAME>Text_ULDTypeSno</DATA_FIELDNAME>
    <DATA_FIELD_CSSCLASS></DATA_FIELD_CSSCLASS>
    <DATA_CELL_CSSCLASS>formInputcolumn</DATA_CELL_CSSCLASS>
    <ONCLICK_HANDLER></ONCLICK_HANDLER>
    <POSTBACK_URL></POSTBACK_URL>
    <CALLBACK_URL></CALLBACK_URL>
    <SKIN_ID></SKIN_ID>
    <TOOLTIP>ULD Type</TOOLTIP>
    <BTN_USESUBMIT_BEHAVIOUR></BTN_USESUBMIT_BEHAVIOUR>
    <VISIBLE>true</VISIBLE>
    <READONLY>true</READONLY>
    <ENABLE_VIEWSTATE>true</ENABLE_VIEWSTATE>
    <MAXLENGTH></MAXLENGTH>
    <MULTILINE></MULTILINE>
    <WIDTH></WIDTH>
    <HEIGHT></HEIGHT>
    <SECTION_NAME></SECTION_NAME>
    <ONKEY_HANDLER></ONKEY_HANDLER>
    <ONBLUR_HANDLER></ONBLUR_HANDLER>
    <ENABLE_REQUIREVALIDATION>false</ENABLE_REQUIREVALIDATION>
    <REQUIRED_FIELD_MESSAGE></REQUIRED_FIELD_MESSAGE>
    <LOOKUP_NAME></LOOKUP_NAME>
    <IMAGE_URL></IMAGE_URL>
    <CONTROL_TOTAL></CONTROL_TOTAL>
    <TAB_INDEX>16</TAB_INDEX>
    <TEXT_TYPE>UPPERCASE</TEXT_TYPE>
    <ALLOWCHAR></ALLOWCHAR>
    <DATA_VALIDATE></DATA_VALIDATE>
  </WebFormDefinition>
  
  
  <WebFormDefinition>
    <DETAIL_ID>17</DETAIL_ID>
    <FORM_ID>733</FORM_ID>
    <HTML_CONTROL_ID>CommonDesignation</HTML_CONTROL_ID>
    <DISPLAY_ORDER>17</DISPLAY_ORDER>
    <ASSEMBLY_NAME>HTML.Label</ASSEMBLY_NAME>
    <LABEL_CELL_TEXT>Common Designation</LABEL_CELL_TEXT>
    <LABEL_CELL_CSSCLASS>formlabel</LABEL_CELL_CSSCLASS>
    <DATA_FIELDNAME>CommonDesignation</DATA_FIELDNAME>
    <DATA_FIELD_CSSCLASS></DATA_FIELD_CSSCLASS>
    <DATA_CELL_CSSCLASS>formInputcolumn</DATA_CELL_CSSCLASS>
    <ONCLICK_HANDLER></ONCLICK_HANDLER>
    <POSTBACK_URL></POSTBACK_URL>
    <CALLBACK_URL></CALLBACK_URL>
    <SKIN_ID></SKIN_ID>
    <TOOLTIP>Common Designation</TOOLTIP>
    <BTN_USESUBMIT_BEHAVIOUR></BTN_USESUBMIT_BEHAVIOUR>
    <VISIBLE>true</VISIBLE>
    <READONLY>true</READONLY>
    <ENABLE_VIEWSTATE>true</ENABLE_VIEWSTATE>
    <MAXLENGTH></MAXLENGTH>
    <MULTILINE></MULTILINE>
    <WIDTH></WIDTH>
    <HEIGHT></HEIGHT>
    <SECTION_NAME></SECTION_NAME>
    <ONKEY_HANDLER></ONKEY_HANDLER>
    <ONBLUR_HANDLER></ONBLUR_HANDLER>
    <ENABLE_REQUIREVALIDATION>false</ENABLE_REQUIREVALIDATION>
    <REQUIRED_FIELD_MESSAGE></REQUIRED_FIELD_MESSAGE>
    <LOOKUP_NAME></LOOKUP_NAME>
    <IMAGE_URL></IMAGE_URL>
    <CONTROL_TOTAL></CONTROL_TOTAL>
    <TAB_INDEX>17</TAB_INDEX>
    <TEXT_TYPE>UPPERCASE</TEXT_TYPE>
    <ALLOWCHAR></ALLOWCHAR>
    <DATA_VALIDATE></DATA_VALIDATE>
  </WebFormDefinition>

  <WebFormDefinition>
    <DETAIL_ID>18</DETAIL_ID>
    <FORM_ID>733</FORM_ID>
    <HTML_CONTROL_ID>CreatedBy</HTML_CONTROL_ID>
    <DISPLAY_ORDER>18</DISPLAY_ORDER>
    <ASSEMBLY_NAME>HTML.Label</ASSEMBLY_NAME>
    <LABEL_CELL_TEXT>Created By</LABEL_CELL_TEXT>
    <LABEL_CELL_CSSCLASS>formlabel</LABEL_CELL_CSSCLASS>
    <DATA_FIELDNAME>CreatedBy</DATA_FIELDNAME>
    <DATA_FIELD_CSSCLASS></DATA_FIELD_CSSCLASS>
    <DATA_CELL_CSSCLASS>formInputcolumn</DATA_CELL_CSSCLASS>
    <ONCLICK_HANDLER></ONCLICK_HANDLER>
    <POSTBACK_URL></POSTBACK_URL>
    <CALLBACK_URL></CALLBACK_URL>
    <SKIN_ID></SKIN_ID>
    <TOOLTIP></TOOLTIP>
    <BTN_USESUBMIT_BEHAVIOUR>true</BTN_USESUBMIT_BEHAVIOUR>
    <VISIBLE>true</VISIBLE>
    <READONLY>true</READONLY>
    <ENABLE_VIEWSTATE>true</ENABLE_VIEWSTATE>
    <MAXLENGTH></MAXLENGTH>
    <MULTILINE></MULTILINE>
    <WIDTH></WIDTH>
    <HEIGHT></HEIGHT>
    <SECTION_NAME>User Action Information</SECTION_NAME>
    <ONKEY_HANDLER></ONKEY_HANDLER>
    <ONBLUR_HANDLER></ONBLUR_HANDLER>
    <ENABLE_REQUIREVALIDATION>false</ENABLE_REQUIREVALIDATION>
    <REQUIRED_FIELD_MESSAGE></REQUIRED_FIELD_MESSAGE>
    <LOOKUP_NAME></LOOKUP_NAME>
    <IMAGE_URL></IMAGE_URL>
    <CONTROL_TOTAL></CONTROL_TOTAL>
    <TEXT_TYPE></TEXT_TYPE>
    <ALLOWCHAR></ALLOWCHAR>
    <TAB_INDEX>18</TAB_INDEX>
    <DATA_VALIDATE></DATA_VALIDATE>
  </WebFormDefinition>
  <WebFormDefinition>
    <DETAIL_ID>19</DETAIL_ID>
    <FORM_ID>733</FORM_ID>
    <HTML_CONTROL_ID>LabelUpdateBy</HTML_CONTROL_ID>
    <DISPLAY_ORDER>19</DISPLAY_ORDER>
    <ASSEMBLY_NAME>HTML.Label</ASSEMBLY_NAME>
    <LABEL_CELL_TEXT> Updated By</LABEL_CELL_TEXT>
    <LABEL_CELL_CSSCLASS>formlabel</LABEL_CELL_CSSCLASS>
    <DATA_FIELDNAME>UpdatedBy</DATA_FIELDNAME>
    <DATA_FIELD_CSSCLASS></DATA_FIELD_CSSCLASS>
    <DATA_CELL_CSSCLASS>formInputcolumn</DATA_CELL_CSSCLASS>
    <ONCLICK_HANDLER></ONCLICK_HANDLER>
    <POSTBACK_URL></POSTBACK_URL>
    <CALLBACK_URL></CALLBACK_URL>
    <SKIN_ID></SKIN_ID>
    <TOOLTIP></TOOLTIP>
    <BTN_USESUBMIT_BEHAVIOUR>true</BTN_USESUBMIT_BEHAVIOUR>
    <VISIBLE>true</VISIBLE>
    <READONLY>true</READONLY>
    <ENABLE_VIEWSTATE>true</ENABLE_VIEWSTATE>
    <MAXLENGTH></MAXLENGTH>
    <MULTILINE></MULTILINE>
    <WIDTH></WIDTH>
    <HEIGHT></HEIGHT>
    <SECTION_NAME></SECTION_NAME>
    <ONKEY_HANDLER></ONKEY_HANDLER>
    <ONBLUR_HANDLER></ONBLUR_HANDLER>
    <ENABLE_REQUIREVALIDATION>false</ENABLE_REQUIREVALIDATION>
    <REQUIRED_FIELD_MESSAGE></REQUIRED_FIELD_MESSAGE>
    <LOOKUP_NAME></LOOKUP_NAME>
    <IMAGE_URL></IMAGE_URL>
    <CONTROL_TOTAL></CONTROL_TOTAL>
    <TAB_INDEX>19</TAB_INDEX>
    <TEXT_TYPE></TEXT_TYPE>
    <ALLOWCHAR></ALLOWCHAR>
    <DATA_VALIDATE></DATA_VALIDATE>

  </WebFormDefinition>

  <!-- <WebFormDefinition>
    <DETAIL_ID>16</DETAIL_ID>
    <FORM_ID>733</FORM_ID>
    <HTML_CONTROL_ID></HTML_CONTROL_ID>
    <DISPLAY_ORDER>16</DISPLAY_ORDER>
    <ASSEMBLY_NAME>HTML.Label</ASSEMBLY_NAME>
    <LABEL_CELL_TEXT></LABEL_CELL_TEXT>
    <LABEL_CELL_CSSCLASS>formlabel</LABEL_CELL_CSSCLASS>
    <DATA_FIELDNAME></DATA_FIELDNAME>
    <DATA_FIELD_CSSCLASS></DATA_FIELD_CSSCLASS>
    <DATA_CELL_CSSCLASS>formInputcolumn</DATA_CELL_CSSCLASS>
    <ONCLICK_HANDLER></ONCLICK_HANDLER>
    <POSTBACK_URL></POSTBACK_URL>
    <CALLBACK_URL></CALLBACK_URL>
    <SKIN_ID></SKIN_ID>
    <TOOLTIP></TOOLTIP>
    <BTN_USESUBMIT_BEHAVIOUR></BTN_USESUBMIT_BEHAVIOUR>
    <VISIBLE>true</VISIBLE>
    <READONLY>true</READONLY>
    <ENABLE_VIEWSTATE>true</ENABLE_VIEWSTATE>
    <MAXLENGTH></MAXLENGTH>
    <MULTILINE></MULTILINE>
    <WIDTH></WIDTH>
    <HEIGHT></HEIGHT>
    <SECTION_NAME></SECTION_NAME>
    <ONKEY_HANDLER></ONKEY_HANDLER>
    <ONBLUR_HANDLER></ONBLUR_HANDLER>
    <ENABLE_REQUIREVALIDATION>false</ENABLE_REQUIREVALIDATION>
    <REQUIRED_FIELD_MESSAGE></REQUIRED_FIELD_MESSAGE>
    <LOOKUP_NAME></LOOKUP_NAME>
    <IMAGE_URL></IMAGE_URL>
    <CONTROL_TOTAL></CONTROL_TOTAL>
    <TAB_INDEX>16</TAB_INDEX>
    <TEXT_TYPE></TEXT_TYPE>
    <ALLOWCHAR></ALLOWCHAR>
    <DATA_VALIDATE></DATA_VALIDATE>
  </WebFormDefinition>-->

  <!--END-->
</DataTable>