<DataTable>
  <!--View Account type-->
  <WebFormDefinition>
    <DETAIL_ID>1</DETAIL_ID>
    <FORM_ID>66</FORM_ID>
    <HTML_CONTROL_ID>AccountTypeName</HTML_CONTROL_ID>
    <DISPLAY_ORDER>1</DISPLAY_ORDER>
    <ASSEMBLY_NAME>HTML.Label</ASSEMBLY_NAME>
    <LABEL_CELL_TEXT>Account Type Name</LABEL_CELL_TEXT>
    <LABEL_CELL_CSSCLASS> formlabel</LABEL_CELL_CSSCLASS>
    <DATA_FIELDNAME>AccountTypeName</DATA_FIELDNAME>
    <DATA_FIELD_CSSCLASS></DATA_FIELD_CSSCLASS>
    <DATA_CELL_CSSCLASS>formInputcolumn</DATA_CELL_CSSCLASS>
    <ONCLICK_HANDLER></ONCLICK_HANDLER>
    <POSTBACK_URL></POSTBACK_URL>
    <CALLBACK_URL></CALLBACK_URL>
    <SKIN_ID></SKIN_ID>
    <TOOLTIP>Account Type Name</TOOLTIP>
    <BTN_USESUBMIT_BEHAVIOUR></BTN_USESUBMIT_BEHAVIOUR>
    <VISIBLE>true</VISIBLE>
    <READONLY>false</READONLY>
    <ENABLE_VIEWSTATE>true</ENABLE_VIEWSTATE>
    <MAXLENGTH></MAXLENGTH>
    <MULTILINE></MULTILINE>
    <WIDTH></WIDTH>
    <HEIGHT></HEIGHT>
    <SECTION_NAME>Account Type Information</SECTION_NAME>
    <ONKEY_HANDLER></ONKEY_HANDLER>
    <ONBLUR_HANDLER></ONBLUR_HANDLER>
    <ENABLE_REQUIREVALIDATION>false</ENABLE_REQUIREVALIDATION>
    <REQUIRED_FIELD_MESSAGE></REQUIRED_FIELD_MESSAGE>
    <LOOKUP_NAME></LOOKUP_NAME>
    <IMAGE_URL></IMAGE_URL>
    <CONTROL_TOTAL></CONTROL_TOTAL>
    <TAB_INDEX>1</TAB_INDEX>
    <TEXT_TYPE></TEXT_TYPE>
    <ALLOWCHAR></ALLOWCHAR>
    <DATA_VALIDATE></DATA_VALIDATE>
  </WebFormDefinition>
   <WebFormDefinition>
    <DETAIL_ID>2</DETAIL_ID>
    <FORM_ID>66</FORM_ID>
    <HTML_CONTROL_ID>PrefixCode</HTML_CONTROL_ID>
    <DISPLAY_ORDER>2</DISPLAY_ORDER>
    <ASSEMBLY_NAME>HTML.Label</ASSEMBLY_NAME>
    <LABEL_CELL_TEXT>Prefix Code</LABEL_CELL_TEXT>
    <LABEL_CELL_CSSCLASS> formlabel</LABEL_CELL_CSSCLASS>
    <DATA_FIELDNAME>PrefixCode</DATA_FIELDNAME>
    <DATA_FIELD_CSSCLASS></DATA_FIELD_CSSCLASS>
    <DATA_CELL_CSSCLASS>formInputcolumn</DATA_CELL_CSSCLASS>
    <ONCLICK_HANDLER></ONCLICK_HANDLER>
    <POSTBACK_URL></POSTBACK_URL>
    <CALLBACK_URL></CALLBACK_URL>
    <SKIN_ID></SKIN_ID>
    <TOOLTIP>PrefixCode</TOOLTIP>
    <BTN_USESUBMIT_BEHAVIOUR></BTN_USESUBMIT_BEHAVIOUR>
    <VISIBLE>true</VISIBLE>
    <READONLY>false</READONLY>
    <ENABLE_VIEWSTATE>true</ENABLE_VIEWSTATE>
    <MAXLENGTH></MAXLENGTH>
    <MULTILINE></MULTILINE>
    <WIDTH></WIDTH>
    <HEIGHT></HEIGHT>
    <SECTION_NAME></SECTION_NAME>
    <ONKEY_HANDLER></ONKEY_HANDLER>
    <ONBLUR_HANDLER></ONBLUR_HANDLER>
    <ENABLE_REQUIREVALIDATION>false</ENABLE_REQUIREVALIDATION>
    <REQUIRED_FIELD_MESSAGE></REQUIRED_FIELD_MESSAGE>
    <LOOKUP_NAME></LOOKUP_NAME>
    <IMAGE_URL></IMAGE_URL>
    <CONTROL_TOTAL></CONTROL_TOTAL>
    <TAB_INDEX>2</TAB_INDEX>
    <TEXT_TYPE></TEXT_TYPE>
    <ALLOWCHAR></ALLOWCHAR>
    <DATA_VALIDATE></DATA_VALIDATE>
  </WebFormDefinition>
   <WebFormDefinition>
    <DETAIL_ID>3</DETAIL_ID>
    <FORM_ID>66</FORM_ID>
    <HTML_CONTROL_ID>ProductSNo</HTML_CONTROL_ID>
    <DISPLAY_ORDER>3</DISPLAY_ORDER>
    <ASSEMBLY_NAME>HTML.Label</ASSEMBLY_NAME>
    <LABEL_CELL_TEXT>Product</LABEL_CELL_TEXT>
    <LABEL_CELL_CSSCLASS>formlabel</LABEL_CELL_CSSCLASS>
    <DATA_FIELDNAME>Text_ProductSNo</DATA_FIELDNAME>
    <DATA_FIELD_CSSCLASS></DATA_FIELD_CSSCLASS>
    <DATA_CELL_CSSCLASS>formInputcolumn</DATA_CELL_CSSCLASS>
    <ONCLICK_HANDLER></ONCLICK_HANDLER>
    <POSTBACK_URL></POSTBACK_URL>
    <CALLBACK_URL></CALLBACK_URL>
    <SKIN_ID></SKIN_ID>
    <TOOLTIP>Enter Product</TOOLTIP>
    <BTN_USESUBMIT_BEHAVIOUR></BTN_USESUBMIT_BEHAVIOUR>
    <VISIBLE>true</VISIBLE>
    <READONLY>false</READONLY>
    <ENABLE_VIEWSTATE>true</ENABLE_VIEWSTATE>
    <MAXLENGTH>50</MAXLENGTH>
    <MULTILINE></MULTILINE>
    <WIDTH>175</WIDTH>
    <HEIGHT></HEIGHT>
    <SECTION_NAME></SECTION_NAME>
    <ONKEY_HANDLER></ONKEY_HANDLER>
    <ONBLUR_HANDLER></ONBLUR_HANDLER>
    <ENABLE_REQUIREVALIDATION>false</ENABLE_REQUIREVALIDATION>
    <REQUIRED_FIELD_MESSAGE>ProductSNo can not be blank</REQUIRED_FIELD_MESSAGE>
    <LOOKUP_NAME></LOOKUP_NAME>
    <IMAGE_URL></IMAGE_URL>
    <CONTROL_TOTAL></CONTROL_TOTAL>
    <TAB_INDEX>3</TAB_INDEX>
    <DATA_VALIDATE></DATA_VALIDATE>
    <TEXT_TYPE>UPPERCASE</TEXT_TYPE>
    <ALLOWCHAR></ALLOWCHAR>
  </WebFormDefinition>
 
  <WebFormDefinition>
    <DETAIL_ID>4</DETAIL_ID>
    <FORM_ID>66</FORM_ID>
    <HTML_CONTROL_ID>IsAirline</HTML_CONTROL_ID>
    <DISPLAY_ORDER>4</DISPLAY_ORDER>
    <ASSEMBLY_NAME>HTML.Label</ASSEMBLY_NAME>
    <LABEL_CELL_TEXT>Airline</LABEL_CELL_TEXT>
    <LABEL_CELL_CSSCLASS> formlabel</LABEL_CELL_CSSCLASS>
    <DATA_FIELDNAME>Airline</DATA_FIELDNAME>
    <DATA_FIELD_CSSCLASS></DATA_FIELD_CSSCLASS>
    <DATA_CELL_CSSCLASS>formInputcolumn</DATA_CELL_CSSCLASS>
    <ONCLICK_HANDLER></ONCLICK_HANDLER>
    <POSTBACK_URL></POSTBACK_URL>
    <CALLBACK_URL></CALLBACK_URL>
    <SKIN_ID></SKIN_ID>
    <TOOLTIP></TOOLTIP>
    <BTN_USESUBMIT_BEHAVIOUR>true</BTN_USESUBMIT_BEHAVIOUR>
    <VISIBLE>true</VISIBLE>
    <READONLY>true</READONLY>
    <ENABLE_VIEWSTATE>false</ENABLE_VIEWSTATE>
    <MAXLENGTH></MAXLENGTH>
    <MULTILINE></MULTILINE>
    <WIDTH></WIDTH>
    <HEIGHT></HEIGHT>
    <SECTION_NAME></SECTION_NAME>
    <ONKEY_HANDLER></ONKEY_HANDLER>
    <ONBLUR_HANDLER></ONBLUR_HANDLER>
    <ENABLE_REQUIREVALIDATION></ENABLE_REQUIREVALIDATION>
    <REQUIRED_FIELD_MESSAGE></REQUIRED_FIELD_MESSAGE>
    <LOOKUP_NAME></LOOKUP_NAME>
    <IMAGE_URL></IMAGE_URL>
    <CONTROL_TOTAL></CONTROL_TOTAL>
    <TAB_INDEX>4</TAB_INDEX>
    <TEXT_TYPE></TEXT_TYPE>
    <ALLOWCHAR></ALLOWCHAR>
    <DATA_VALIDATE></DATA_VALIDATE>
  </WebFormDefinition>
  <WebFormDefinition>
    <DETAIL_ID>5</DETAIL_ID>
    <FORM_ID>66</FORM_ID>
    <HTML_CONTROL_ID>IsActive</HTML_CONTROL_ID>
    <DISPLAY_ORDER>5</DISPLAY_ORDER>
    <ASSEMBLY_NAME>HTML.Label</ASSEMBLY_NAME>
    <LABEL_CELL_TEXT>Active</LABEL_CELL_TEXT>
    <LABEL_CELL_CSSCLASS> formlabel</LABEL_CELL_CSSCLASS>
    <DATA_FIELDNAME>Active</DATA_FIELDNAME>
    <DATA_FIELD_CSSCLASS></DATA_FIELD_CSSCLASS>
    <DATA_CELL_CSSCLASS>formInputcolumn</DATA_CELL_CSSCLASS>
    <ONCLICK_HANDLER></ONCLICK_HANDLER>
    <POSTBACK_URL></POSTBACK_URL>
    <CALLBACK_URL></CALLBACK_URL>
    <SKIN_ID></SKIN_ID>
    <TOOLTIP></TOOLTIP>
    <BTN_USESUBMIT_BEHAVIOUR>true</BTN_USESUBMIT_BEHAVIOUR>
    <VISIBLE>true</VISIBLE>
    <READONLY>true</READONLY>
    <ENABLE_VIEWSTATE>false</ENABLE_VIEWSTATE>
    <MAXLENGTH></MAXLENGTH>
    <MULTILINE></MULTILINE>
    <WIDTH></WIDTH>
    <HEIGHT></HEIGHT>
    <SECTION_NAME></SECTION_NAME>
    <ONKEY_HANDLER></ONKEY_HANDLER>
    <ONBLUR_HANDLER></ONBLUR_HANDLER>
    <ENABLE_REQUIREVALIDATION></ENABLE_REQUIREVALIDATION>
    <REQUIRED_FIELD_MESSAGE></REQUIRED_FIELD_MESSAGE>
    <LOOKUP_NAME></LOOKUP_NAME>
    <IMAGE_URL></IMAGE_URL>
    <CONTROL_TOTAL></CONTROL_TOTAL>
    <TAB_INDEX>5</TAB_INDEX>
    <TEXT_TYPE></TEXT_TYPE>
    <ALLOWCHAR></ALLOWCHAR>
    <DATA_VALIDATE></DATA_VALIDATE>
  </WebFormDefinition>
   <WebFormDefinition>
    <DETAIL_ID>6</DETAIL_ID>
    <FORM_ID>66</FORM_ID>
    <HTML_CONTROL_ID></HTML_CONTROL_ID>
    <DISPLAY_ORDER>6</DISPLAY_ORDER>
    <ASSEMBLY_NAME>HTML.Label</ASSEMBLY_NAME>
    <LABEL_CELL_TEXT></LABEL_CELL_TEXT>
    <LABEL_CELL_CSSCLASS> formlabel</LABEL_CELL_CSSCLASS>
    <DATA_FIELDNAME></DATA_FIELDNAME>
    <DATA_FIELD_CSSCLASS></DATA_FIELD_CSSCLASS>
    <DATA_CELL_CSSCLASS>formlabel</DATA_CELL_CSSCLASS>
    <ONCLICK_HANDLER></ONCLICK_HANDLER>
    <POSTBACK_URL></POSTBACK_URL>
    <CALLBACK_URL></CALLBACK_URL>
    <SKIN_ID></SKIN_ID>
    <TOOLTIP></TOOLTIP>
    <BTN_USESUBMIT_BEHAVIOUR>true</BTN_USESUBMIT_BEHAVIOUR>
    <VISIBLE>true</VISIBLE>
    <READONLY>true</READONLY>
    <ENABLE_VIEWSTATE>true</ENABLE_VIEWSTATE>
    <MAXLENGTH></MAXLENGTH>
    <MULTILINE></MULTILINE>
    <WIDTH></WIDTH>
    <HEIGHT></HEIGHT>
    <SECTION_NAME></SECTION_NAME>
    <ONKEY_HANDLER></ONKEY_HANDLER>
    <ONBLUR_HANDLER></ONBLUR_HANDLER>
    <ENABLE_REQUIREVALIDATION>false</ENABLE_REQUIREVALIDATION>
    <REQUIRED_FIELD_MESSAGE></REQUIRED_FIELD_MESSAGE>
    <LOOKUP_NAME></LOOKUP_NAME>
    <IMAGE_URL></IMAGE_URL>
    <CONTROL_TOTAL></CONTROL_TOTAL>
    <TAB_INDEX>6</TAB_INDEX>
    <TEXT_TYPE></TEXT_TYPE>
    <ALLOWCHAR></ALLOWCHAR>
    <DATA_VALIDATE></DATA_VALIDATE>
  </WebFormDefinition>
  <WebFormDefinition>
    <DETAIL_ID>7</DETAIL_ID>
    <FORM_ID>66</FORM_ID>
    <HTML_CONTROL_ID>CreatedBy</HTML_CONTROL_ID>
    <DISPLAY_ORDER>7</DISPLAY_ORDER>
    <ASSEMBLY_NAME>HTML.Label</ASSEMBLY_NAME>
    <LABEL_CELL_TEXT>Created By</LABEL_CELL_TEXT>
    <LABEL_CELL_CSSCLASS> formlabel</LABEL_CELL_CSSCLASS>
    <DATA_FIELDNAME>CreatedBy</DATA_FIELDNAME>
    <DATA_FIELD_CSSCLASS></DATA_FIELD_CSSCLASS>
    <DATA_CELL_CSSCLASS>formInputcolumn</DATA_CELL_CSSCLASS>
    <ONCLICK_HANDLER></ONCLICK_HANDLER>
    <POSTBACK_URL></POSTBACK_URL>
    <CALLBACK_URL></CALLBACK_URL>
    <SKIN_ID></SKIN_ID>
    <TOOLTIP></TOOLTIP>
    <BTN_USESUBMIT_BEHAVIOUR></BTN_USESUBMIT_BEHAVIOUR>
    <VISIBLE>true</VISIBLE>
    <READONLY>false</READONLY>
    <ENABLE_VIEWSTATE>true</ENABLE_VIEWSTATE>
    <MAXLENGTH></MAXLENGTH>
    <MULTILINE></MULTILINE>
    <WIDTH></WIDTH>
    <HEIGHT></HEIGHT>
    <SECTION_NAME>User Action Information</SECTION_NAME>
    <ONKEY_HANDLER></ONKEY_HANDLER>
    <ONBLUR_HANDLER></ONBLUR_HANDLER>
    <ENABLE_REQUIREVALIDATION></ENABLE_REQUIREVALIDATION>
    <REQUIRED_FIELD_MESSAGE></REQUIRED_FIELD_MESSAGE>
    <LOOKUP_NAME></LOOKUP_NAME>
    <IMAGE_URL></IMAGE_URL>
    <CONTROL_TOTAL></CONTROL_TOTAL>
    <TAB_INDEX>7</TAB_INDEX>
    <TEXT_TYPE></TEXT_TYPE>
    <ALLOWCHAR></ALLOWCHAR>
    <DATA_VALIDATE></DATA_VALIDATE>
  </WebFormDefinition>
  <WebFormDefinition>
    <DETAIL_ID>8</DETAIL_ID>
    <FORM_ID>66</FORM_ID>
    <HTML_CONTROL_ID>UpdatedBy</HTML_CONTROL_ID>
    <DISPLAY_ORDER>8</DISPLAY_ORDER>
    <ASSEMBLY_NAME>HTML.Label</ASSEMBLY_NAME>
    <LABEL_CELL_TEXT>Updated By</LABEL_CELL_TEXT>
    <LABEL_CELL_CSSCLASS> formlabel</LABEL_CELL_CSSCLASS>
    <DATA_FIELDNAME>UpdatedBy</DATA_FIELDNAME>
    <DATA_FIELD_CSSCLASS></DATA_FIELD_CSSCLASS>
    <DATA_CELL_CSSCLASS>formInputcolumn</DATA_CELL_CSSCLASS>
    <ONCLICK_HANDLER></ONCLICK_HANDLER>
    <POSTBACK_URL></POSTBACK_URL>
    <CALLBACK_URL></CALLBACK_URL>
    <SKIN_ID></SKIN_ID>
    <TOOLTIP></TOOLTIP>
    <BTN_USESUBMIT_BEHAVIOUR></BTN_USESUBMIT_BEHAVIOUR>
    <VISIBLE>true</VISIBLE>
    <READONLY>false</READONLY>
    <ENABLE_VIEWSTATE>true</ENABLE_VIEWSTATE>
    <MAXLENGTH></MAXLENGTH>
    <MULTILINE></MULTILINE>
    <WIDTH></WIDTH>
    <HEIGHT></HEIGHT>
    <SECTION_NAME></SECTION_NAME>
    <ONKEY_HANDLER></ONKEY_HANDLER>
    <ONBLUR_HANDLER></ONBLUR_HANDLER>
    <ENABLE_REQUIREVALIDATION></ENABLE_REQUIREVALIDATION>
    <REQUIRED_FIELD_MESSAGE></REQUIRED_FIELD_MESSAGE>
    <LOOKUP_NAME></LOOKUP_NAME>
    <IMAGE_URL></IMAGE_URL>
    <CONTROL_TOTAL></CONTROL_TOTAL>
    <TAB_INDEX>8</TAB_INDEX>
    <TEXT_TYPE></TEXT_TYPE>
    <ALLOWCHAR></ALLOWCHAR>
    <DATA_VALIDATE></DATA_VALIDATE>
  </WebFormDefinition>
  
  <!--Edit Account type-->
  
  <WebFormDefinition>
    <DETAIL_ID>1</DETAIL_ID>
    <FORM_ID>67</FORM_ID>
    <HTML_CONTROL_ID>AccountTypeName</HTML_CONTROL_ID>
    <DISPLAY_ORDER>1</DISPLAY_ORDER>
    <ASSEMBLY_NAME>HTML.TextBox</ASSEMBLY_NAME>
    <LABEL_CELL_TEXT>Account Type Name</LABEL_CELL_TEXT>
    <LABEL_CELL_CSSCLASS>formlabel</LABEL_CELL_CSSCLASS>
    <DATA_FIELDNAME>AccountTypeName</DATA_FIELDNAME>
    <DATA_FIELD_CSSCLASS></DATA_FIELD_CSSCLASS>
    <DATA_CELL_CSSCLASS>formInputcolumn</DATA_CELL_CSSCLASS>
    <ONCLICK_HANDLER></ONCLICK_HANDLER>
    <POSTBACK_URL></POSTBACK_URL>
    <CALLBACK_URL></CALLBACK_URL>
    <SKIN_ID></SKIN_ID>
    <TOOLTIP>Account Type Name</TOOLTIP>
    <BTN_USESUBMIT_BEHAVIOUR></BTN_USESUBMIT_BEHAVIOUR>
    <VISIBLE>true</VISIBLE>
    <READONLY>false</READONLY>
    <ENABLE_VIEWSTATE>true</ENABLE_VIEWSTATE>
    <MAXLENGTH>48</MAXLENGTH>
    <MULTILINE></MULTILINE>
    <WIDTH>150</WIDTH>
    <HEIGHT></HEIGHT>
    <SECTION_NAME>Account Type Information</SECTION_NAME>
    <ONKEY_HANDLER></ONKEY_HANDLER>
    <ONBLUR_HANDLER></ONBLUR_HANDLER>
    <ENABLE_REQUIREVALIDATION>True</ENABLE_REQUIREVALIDATION>
    <REQUIRED_FIELD_MESSAGE>Account Type Name can not be blank</REQUIRED_FIELD_MESSAGE>
    <LOOKUP_NAME></LOOKUP_NAME>
    <IMAGE_URL></IMAGE_URL>
    <CONTROL_TOTAL></CONTROL_TOTAL>
    <TAB_INDEX>1</TAB_INDEX>
    <TEXT_TYPE>UPPERCASE</TEXT_TYPE>
    <ALLOWCHAR></ALLOWCHAR>
    <DATA_VALIDATE>required</DATA_VALIDATE>
  </WebFormDefinition>
   <WebFormDefinition>
    <DETAIL_ID>2</DETAIL_ID>
    <FORM_ID>67</FORM_ID>
    <HTML_CONTROL_ID>PrefixCode</HTML_CONTROL_ID>
    <DISPLAY_ORDER>2</DISPLAY_ORDER>
    <ASSEMBLY_NAME>HTML.TextBox</ASSEMBLY_NAME>
    <LABEL_CELL_TEXT>Prefix Code</LABEL_CELL_TEXT>
    <LABEL_CELL_CSSCLASS>formlabel</LABEL_CELL_CSSCLASS>
    <DATA_FIELDNAME>PrefixCode</DATA_FIELDNAME>
    <DATA_FIELD_CSSCLASS></DATA_FIELD_CSSCLASS>
    <DATA_CELL_CSSCLASS>formInputcolumn</DATA_CELL_CSSCLASS>
    <ONCLICK_HANDLER></ONCLICK_HANDLER>
    <POSTBACK_URL></POSTBACK_URL>
    <CALLBACK_URL></CALLBACK_URL>
    <SKIN_ID></SKIN_ID>
    <TOOLTIP>PrefixCode</TOOLTIP>
    <BTN_USESUBMIT_BEHAVIOUR></BTN_USESUBMIT_BEHAVIOUR>
    <VISIBLE>true</VISIBLE>
    <READONLY>false</READONLY>
    <ENABLE_VIEWSTATE>true</ENABLE_VIEWSTATE>
    <MAXLENGTH>2</MAXLENGTH>
    <MULTILINE></MULTILINE>
    <WIDTH>150</WIDTH>
    <HEIGHT></HEIGHT>
    <SECTION_NAME></SECTION_NAME>
    <ONKEY_HANDLER></ONKEY_HANDLER>
    <ONBLUR_HANDLER></ONBLUR_HANDLER>
    <ENABLE_REQUIREVALIDATION>True</ENABLE_REQUIREVALIDATION>
    <REQUIRED_FIELD_MESSAGE>Prefix Code can not be blank</REQUIRED_FIELD_MESSAGE>
    <LOOKUP_NAME></LOOKUP_NAME>
    <IMAGE_URL></IMAGE_URL>
    <CONTROL_TOTAL></CONTROL_TOTAL>
    <TAB_INDEX>2</TAB_INDEX>
    <TEXT_TYPE>UPPERCASE</TEXT_TYPE>
    <ALLOWCHAR></ALLOWCHAR>
    <DATA_VALIDATE>required</DATA_VALIDATE>
  </WebFormDefinition>
  
  <WebFormDefinition>
    <DETAIL_ID>3</DETAIL_ID>
    <FORM_ID>67</FORM_ID>
    <HTML_CONTROL_ID>ProductSNo</HTML_CONTROL_ID>
    <DISPLAY_ORDER>3</DISPLAY_ORDER>
    <ASSEMBLY_NAME>HTML.AutoCompleteTextBox</ASSEMBLY_NAME>
    <LABEL_CELL_TEXT>Product</LABEL_CELL_TEXT>
    <LABEL_CELL_CSSCLASS>formlabel</LABEL_CELL_CSSCLASS>
    <DATA_FIELDNAME>ProductSNo</DATA_FIELDNAME>
    <DATA_FIELD_CSSCLASS></DATA_FIELD_CSSCLASS>
    <DATA_CELL_CSSCLASS>formInputcolumn</DATA_CELL_CSSCLASS>
    <ONCLICK_HANDLER></ONCLICK_HANDLER>
    <POSTBACK_URL></POSTBACK_URL>
    <CALLBACK_URL></CALLBACK_URL>
    <SKIN_ID></SKIN_ID>
    <TOOLTIP>Enter Product</TOOLTIP>
    <BTN_USESUBMIT_BEHAVIOUR></BTN_USESUBMIT_BEHAVIOUR>
    <VISIBLE>true</VISIBLE>
    <READONLY>false</READONLY>
    <ENABLE_VIEWSTATE>true</ENABLE_VIEWSTATE>
    <MAXLENGTH>50</MAXLENGTH>
    <MULTILINE></MULTILINE>
    <WIDTH>175</WIDTH>
    <HEIGHT></HEIGHT>
    <SECTION_NAME></SECTION_NAME>
    <ONKEY_HANDLER></ONKEY_HANDLER>
    <ONBLUR_HANDLER></ONBLUR_HANDLER>
    <ENABLE_REQUIREVALIDATION>false</ENABLE_REQUIREVALIDATION>
    <REQUIRED_FIELD_MESSAGE>ProductSNo can not be blank</REQUIRED_FIELD_MESSAGE>
    <LOOKUP_NAME></LOOKUP_NAME>
    <IMAGE_URL></IMAGE_URL>
    <CONTROL_TOTAL></CONTROL_TOTAL>
    <TAB_INDEX>3</TAB_INDEX>
    <DATA_VALIDATE></DATA_VALIDATE>
    <TEXT_TYPE>UPPERCASE</TEXT_TYPE>
    <ALLOWCHAR></ALLOWCHAR>
  </WebFormDefinition>
  <WebFormDefinition>
    <DETAIL_ID>4</DETAIL_ID>
    <FORM_ID>67</FORM_ID>
    <HTML_CONTROL_ID>IsAirline</HTML_CONTROL_ID>
    <DISPLAY_ORDER>4</DISPLAY_ORDER>
    <ASSEMBLY_NAME>HTML.RadioButtonList</ASSEMBLY_NAME>
    <LABEL_CELL_TEXT>Airline</LABEL_CELL_TEXT>
    <LABEL_CELL_CSSCLASS>formlabel</LABEL_CELL_CSSCLASS>
    <DATA_FIELDNAME>IsAirline</DATA_FIELDNAME>
    <DATA_FIELD_CSSCLASS></DATA_FIELD_CSSCLASS>
    <DATA_CELL_CSSCLASS>formInputcolumn</DATA_CELL_CSSCLASS>
    <ONCLICK_HANDLER></ONCLICK_HANDLER>
    <POSTBACK_URL></POSTBACK_URL>
    <CALLBACK_URL></CALLBACK_URL>
    <SKIN_ID></SKIN_ID>
    <TOOLTIP>Airline</TOOLTIP>
    <BTN_USESUBMIT_BEHAVIOUR>true</BTN_USESUBMIT_BEHAVIOUR>
    <VISIBLE>true</VISIBLE>
    <READONLY>true</READONLY>
    <ENABLE_VIEWSTATE>true</ENABLE_VIEWSTATE>
    <MAXLENGTH></MAXLENGTH>
    <MULTILINE></MULTILINE>
    <WIDTH></WIDTH>
    <HEIGHT></HEIGHT>
    <SECTION_NAME></SECTION_NAME>
    <ONKEY_HANDLER></ONKEY_HANDLER>
    <ONBLUR_HANDLER></ONBLUR_HANDLER>
    <ENABLE_REQUIREVALIDATION>false</ENABLE_REQUIREVALIDATION>
    <REQUIRED_FIELD_MESSAGE>Airline can not be blank</REQUIRED_FIELD_MESSAGE>
    <LOOKUP_NAME></LOOKUP_NAME>
    <IMAGE_URL></IMAGE_URL>
    <CONTROL_TOTAL></CONTROL_TOTAL>
    <TAB_INDEX>4</TAB_INDEX>
    <TEXT_TYPE>ENUM.ACTIVE</TEXT_TYPE>
    <ALLOWCHAR></ALLOWCHAR>
    <DATA_VALIDATE></DATA_VALIDATE>
  </WebFormDefinition>
   <WebFormDefinition>
    <DETAIL_ID>5</DETAIL_ID>
    <FORM_ID>67</FORM_ID>
    <HTML_CONTROL_ID>IsActive</HTML_CONTROL_ID>
    <DISPLAY_ORDER>5</DISPLAY_ORDER>
    <ASSEMBLY_NAME>HTML.RadioButtonList</ASSEMBLY_NAME>
    <LABEL_CELL_TEXT>Active</LABEL_CELL_TEXT>
    <LABEL_CELL_CSSCLASS> formlabel</LABEL_CELL_CSSCLASS>
    <DATA_FIELDNAME>IsActive</DATA_FIELDNAME>
    <DATA_FIELD_CSSCLASS></DATA_FIELD_CSSCLASS>
    <DATA_CELL_CSSCLASS>formInputcolumn</DATA_CELL_CSSCLASS>
    <ONCLICK_HANDLER></ONCLICK_HANDLER>
    <POSTBACK_URL></POSTBACK_URL>
    <CALLBACK_URL></CALLBACK_URL>
    <SKIN_ID></SKIN_ID>
    <TOOLTIP>Active</TOOLTIP>
    <BTN_USESUBMIT_BEHAVIOUR>true</BTN_USESUBMIT_BEHAVIOUR>
    <VISIBLE>true</VISIBLE>
    <READONLY>true</READONLY>
    <ENABLE_VIEWSTATE>true</ENABLE_VIEWSTATE>
    <MAXLENGTH></MAXLENGTH>
    <MULTILINE></MULTILINE>
    <WIDTH></WIDTH>
    <HEIGHT></HEIGHT>
    <SECTION_NAME></SECTION_NAME>
    <ONKEY_HANDLER></ONKEY_HANDLER>
    <ONBLUR_HANDLER></ONBLUR_HANDLER>
    <ENABLE_REQUIREVALIDATION>false</ENABLE_REQUIREVALIDATION>
    <REQUIRED_FIELD_MESSAGE>Active can not be blank</REQUIRED_FIELD_MESSAGE>
    <LOOKUP_NAME></LOOKUP_NAME>
    <IMAGE_URL></IMAGE_URL>
    <CONTROL_TOTAL></CONTROL_TOTAL>
    <TAB_INDEX>5</TAB_INDEX>
    <TEXT_TYPE>ENUM.ACTIVE</TEXT_TYPE>
    <ALLOWCHAR></ALLOWCHAR>
    <DATA_VALIDATE></DATA_VALIDATE>
  </WebFormDefinition>
  <WebFormDefinition>
    <DETAIL_ID>6</DETAIL_ID>
    <FORM_ID>67</FORM_ID>
    <HTML_CONTROL_ID></HTML_CONTROL_ID>
    <DISPLAY_ORDER>6</DISPLAY_ORDER>
    <ASSEMBLY_NAME>HTML.Label</ASSEMBLY_NAME>
    <LABEL_CELL_TEXT></LABEL_CELL_TEXT>
    <LABEL_CELL_CSSCLASS> formlabel</LABEL_CELL_CSSCLASS>
    <DATA_FIELDNAME></DATA_FIELDNAME>
    <DATA_FIELD_CSSCLASS></DATA_FIELD_CSSCLASS>
    <DATA_CELL_CSSCLASS>formlabel</DATA_CELL_CSSCLASS>
    <ONCLICK_HANDLER></ONCLICK_HANDLER>
    <POSTBACK_URL></POSTBACK_URL>
    <CALLBACK_URL></CALLBACK_URL>
    <SKIN_ID></SKIN_ID>
    <TOOLTIP></TOOLTIP>
    <BTN_USESUBMIT_BEHAVIOUR>true</BTN_USESUBMIT_BEHAVIOUR>
    <VISIBLE>true</VISIBLE>
    <READONLY>true</READONLY>
    <ENABLE_VIEWSTATE>true</ENABLE_VIEWSTATE>
    <MAXLENGTH></MAXLENGTH>
    <MULTILINE></MULTILINE>
    <WIDTH></WIDTH>
    <HEIGHT></HEIGHT>
    <SECTION_NAME></SECTION_NAME>
    <ONKEY_HANDLER></ONKEY_HANDLER>
    <ONBLUR_HANDLER></ONBLUR_HANDLER>
    <ENABLE_REQUIREVALIDATION>false</ENABLE_REQUIREVALIDATION>
    <REQUIRED_FIELD_MESSAGE></REQUIRED_FIELD_MESSAGE>
    <LOOKUP_NAME></LOOKUP_NAME>
    <IMAGE_URL></IMAGE_URL>
    <CONTROL_TOTAL></CONTROL_TOTAL>
    <TAB_INDEX>6</TAB_INDEX>
    <TEXT_TYPE></TEXT_TYPE>
    <ALLOWCHAR></ALLOWCHAR>
    <DATA_VALIDATE></DATA_VALIDATE>
  </WebFormDefinition>
 
  <WebFormDefinition>
    <DETAIL_ID>7</DETAIL_ID>
    <FORM_ID>67</FORM_ID>
    <HTML_CONTROL_ID>CreatedBy</HTML_CONTROL_ID>
    <DISPLAY_ORDER>7</DISPLAY_ORDER>
    <ASSEMBLY_NAME>HTML.Label</ASSEMBLY_NAME>
    <LABEL_CELL_TEXT>Created By</LABEL_CELL_TEXT>
    <LABEL_CELL_CSSCLASS> formlabel</LABEL_CELL_CSSCLASS>
    <DATA_FIELDNAME>CreatedBy</DATA_FIELDNAME>
    <DATA_FIELD_CSSCLASS></DATA_FIELD_CSSCLASS>
    <DATA_CELL_CSSCLASS>formInputcolumn</DATA_CELL_CSSCLASS>
    <ONCLICK_HANDLER></ONCLICK_HANDLER>
    <POSTBACK_URL></POSTBACK_URL>
    <CALLBACK_URL></CALLBACK_URL>
    <SKIN_ID></SKIN_ID>
    <TOOLTIP></TOOLTIP>
    <BTN_USESUBMIT_BEHAVIOUR></BTN_USESUBMIT_BEHAVIOUR>
    <VISIBLE>true</VISIBLE>
    <READONLY>false</READONLY>
    <ENABLE_VIEWSTATE>true</ENABLE_VIEWSTATE>
    <MAXLENGTH></MAXLENGTH>
    <MULTILINE></MULTILINE>
    <WIDTH></WIDTH>
    <HEIGHT></HEIGHT>
    <SECTION_NAME>User Action Information</SECTION_NAME>
    <ONKEY_HANDLER></ONKEY_HANDLER>
    <ONBLUR_HANDLER></ONBLUR_HANDLER>
    <ENABLE_REQUIREVALIDATION></ENABLE_REQUIREVALIDATION>
    <REQUIRED_FIELD_MESSAGE></REQUIRED_FIELD_MESSAGE>
    <LOOKUP_NAME></LOOKUP_NAME>
    <IMAGE_URL></IMAGE_URL>
    <CONTROL_TOTAL></CONTROL_TOTAL>
    <TAB_INDEX>7</TAB_INDEX>
    <TEXT_TYPE></TEXT_TYPE>
    <ALLOWCHAR></ALLOWCHAR>
    <DATA_VALIDATE></DATA_VALIDATE>
  </WebFormDefinition>
  <WebFormDefinition>
    <DETAIL_ID>8</DETAIL_ID>
    <FORM_ID>67</FORM_ID>
    <HTML_CONTROL_ID>UpdatedBy</HTML_CONTROL_ID>
    <DISPLAY_ORDER>8</DISPLAY_ORDER>
    <ASSEMBLY_NAME>HTML.Label</ASSEMBLY_NAME>
    <LABEL_CELL_TEXT>Updated By</LABEL_CELL_TEXT>
    <LABEL_CELL_CSSCLASS> formlabel</LABEL_CELL_CSSCLASS>
    <DATA_FIELDNAME>UpdatedBy</DATA_FIELDNAME>
    <DATA_FIELD_CSSCLASS></DATA_FIELD_CSSCLASS>
    <DATA_CELL_CSSCLASS>formInputcolumn</DATA_CELL_CSSCLASS>
    <ONCLICK_HANDLER></ONCLICK_HANDLER>
    <POSTBACK_URL></POSTBACK_URL>
    <CALLBACK_URL></CALLBACK_URL>
    <SKIN_ID></SKIN_ID>
    <TOOLTIP></TOOLTIP>
    <BTN_USESUBMIT_BEHAVIOUR></BTN_USESUBMIT_BEHAVIOUR>
    <VISIBLE>true</VISIBLE>
    <READONLY>false</READONLY>
    <ENABLE_VIEWSTATE>true</ENABLE_VIEWSTATE>
    <MAXLENGTH></MAXLENGTH>
    <MULTILINE></MULTILINE>
    <WIDTH></WIDTH>
    <HEIGHT></HEIGHT>
    <SECTION_NAME></SECTION_NAME>
    <ONKEY_HANDLER></ONKEY_HANDLER>
    <ONBLUR_HANDLER></ONBLUR_HANDLER>
    <ENABLE_REQUIREVALIDATION></ENABLE_REQUIREVALIDATION>
    <REQUIRED_FIELD_MESSAGE></REQUIRED_FIELD_MESSAGE>
    <LOOKUP_NAME></LOOKUP_NAME>
    <IMAGE_URL></IMAGE_URL>
    <CONTROL_TOTAL></CONTROL_TOTAL>
    <TAB_INDEX>8</TAB_INDEX>
    <TEXT_TYPE></TEXT_TYPE>
    <ALLOWCHAR></ALLOWCHAR>
    <DATA_VALIDATE></DATA_VALIDATE>
  </WebFormDefinition>

  <!--New Account type-->
  
  <WebFormDefinition>
    <DETAIL_ID>1</DETAIL_ID>
    <FORM_ID>406</FORM_ID>
    <HTML_CONTROL_ID>AccountTypeName</HTML_CONTROL_ID>
    <DISPLAY_ORDER>1</DISPLAY_ORDER>
    <ASSEMBLY_NAME>HTML.TextBox</ASSEMBLY_NAME>
    <LABEL_CELL_TEXT>Account Type Name</LABEL_CELL_TEXT>
    <LABEL_CELL_CSSCLASS> formlabel</LABEL_CELL_CSSCLASS>
    <DATA_FIELDNAME>AccountTypeName</DATA_FIELDNAME>
    <DATA_FIELD_CSSCLASS></DATA_FIELD_CSSCLASS>
    <DATA_CELL_CSSCLASS>formInputcolumn</DATA_CELL_CSSCLASS>
    <ONCLICK_HANDLER></ONCLICK_HANDLER>
    <POSTBACK_URL></POSTBACK_URL>
    <CALLBACK_URL></CALLBACK_URL>
    <SKIN_ID></SKIN_ID>
    <TOOLTIP>Account Type Name</TOOLTIP>
    <BTN_USESUBMIT_BEHAVIOUR></BTN_USESUBMIT_BEHAVIOUR>
    <VISIBLE>true</VISIBLE>
    <READONLY>false</READONLY>
    <ENABLE_VIEWSTATE>true</ENABLE_VIEWSTATE>
    <MAXLENGTH>48</MAXLENGTH>
    <MULTILINE></MULTILINE>
    <WIDTH>150</WIDTH>
    <HEIGHT></HEIGHT>
    <SECTION_NAME>Account Type Information</SECTION_NAME>
    <ONKEY_HANDLER></ONKEY_HANDLER>
    <ONBLUR_HANDLER></ONBLUR_HANDLER>
    <ENABLE_REQUIREVALIDATION>true</ENABLE_REQUIREVALIDATION>
    <REQUIRED_FIELD_MESSAGE>Account Type Name can not be blank</REQUIRED_FIELD_MESSAGE>
    <LOOKUP_NAME></LOOKUP_NAME>
    <IMAGE_URL></IMAGE_URL>
    <CONTROL_TOTAL></CONTROL_TOTAL>
    <TAB_INDEX>1</TAB_INDEX>
    <TEXT_TYPE>UPPERCASE</TEXT_TYPE>
    <ALLOWCHAR></ALLOWCHAR>
    <DATA_VALIDATE>required</DATA_VALIDATE>
  </WebFormDefinition>
   <WebFormDefinition>
    <DETAIL_ID>2</DETAIL_ID>
    <FORM_ID>406</FORM_ID>
    <HTML_CONTROL_ID>PrefixCode</HTML_CONTROL_ID>
    <DISPLAY_ORDER>2</DISPLAY_ORDER>
    <ASSEMBLY_NAME>HTML.TextBox</ASSEMBLY_NAME>
    <LABEL_CELL_TEXT>Prefix Code</LABEL_CELL_TEXT>
    <LABEL_CELL_CSSCLASS> formlabel</LABEL_CELL_CSSCLASS>
    <DATA_FIELDNAME>PrefixCode</DATA_FIELDNAME>
    <DATA_FIELD_CSSCLASS></DATA_FIELD_CSSCLASS>
    <DATA_CELL_CSSCLASS>formInputcolumn</DATA_CELL_CSSCLASS>
    <ONCLICK_HANDLER></ONCLICK_HANDLER>
    <POSTBACK_URL></POSTBACK_URL>
    <CALLBACK_URL></CALLBACK_URL>
    <SKIN_ID></SKIN_ID>
    <TOOLTIP>Prefix Code</TOOLTIP>
    <BTN_USESUBMIT_BEHAVIOUR></BTN_USESUBMIT_BEHAVIOUR>
    <VISIBLE>true</VISIBLE>
    <READONLY>false</READONLY>
    <ENABLE_VIEWSTATE>true</ENABLE_VIEWSTATE>
    <MAXLENGTH>2</MAXLENGTH>
    <MULTILINE></MULTILINE>
    <WIDTH>150</WIDTH>
    <HEIGHT></HEIGHT>
    <SECTION_NAME></SECTION_NAME>
    <ONKEY_HANDLER></ONKEY_HANDLER>
    <ONBLUR_HANDLER></ONBLUR_HANDLER>
    <ENABLE_REQUIREVALIDATION>true</ENABLE_REQUIREVALIDATION>
    <REQUIRED_FIELD_MESSAGE>Prefix Code can not be blank</REQUIRED_FIELD_MESSAGE>
    <LOOKUP_NAME></LOOKUP_NAME>
    <IMAGE_URL></IMAGE_URL>
    <CONTROL_TOTAL></CONTROL_TOTAL>
    <TAB_INDEX>2</TAB_INDEX>
    <TEXT_TYPE>UPPERCASE</TEXT_TYPE>
    <ALLOWCHAR></ALLOWCHAR>
    <DATA_VALIDATE>required</DATA_VALIDATE>
  </WebFormDefinition>
 <WebFormDefinition>
    <DETAIL_ID>3</DETAIL_ID>
    <FORM_ID>406</FORM_ID>
    <HTML_CONTROL_ID>ProductSNo</HTML_CONTROL_ID>
    <DISPLAY_ORDER>3</DISPLAY_ORDER>
    <ASSEMBLY_NAME>HTML.AutoCompleteTextBox</ASSEMBLY_NAME>
    <LABEL_CELL_TEXT>Product</LABEL_CELL_TEXT>
    <LABEL_CELL_CSSCLASS>formlabel</LABEL_CELL_CSSCLASS>
    <DATA_FIELDNAME>ProductSNo</DATA_FIELDNAME>
    <DATA_FIELD_CSSCLASS></DATA_FIELD_CSSCLASS>
    <DATA_CELL_CSSCLASS>formInputcolumn</DATA_CELL_CSSCLASS>
    <ONCLICK_HANDLER></ONCLICK_HANDLER>
    <POSTBACK_URL></POSTBACK_URL>
    <CALLBACK_URL></CALLBACK_URL>
    <SKIN_ID></SKIN_ID>
    <TOOLTIP>Enter Product</TOOLTIP>
    <BTN_USESUBMIT_BEHAVIOUR></BTN_USESUBMIT_BEHAVIOUR>
    <VISIBLE>true</VISIBLE>
    <READONLY>false</READONLY>
    <ENABLE_VIEWSTATE>true</ENABLE_VIEWSTATE>
    <MAXLENGTH>50</MAXLENGTH>
    <MULTILINE></MULTILINE>
    <WIDTH>175</WIDTH>
    <HEIGHT></HEIGHT>
    <SECTION_NAME></SECTION_NAME>
    <ONKEY_HANDLER></ONKEY_HANDLER>
    <ONBLUR_HANDLER></ONBLUR_HANDLER>
    <ENABLE_REQUIREVALIDATION>false</ENABLE_REQUIREVALIDATION>
    <REQUIRED_FIELD_MESSAGE>ProductSNo can not be blank</REQUIRED_FIELD_MESSAGE>
    <LOOKUP_NAME></LOOKUP_NAME>
    <IMAGE_URL></IMAGE_URL>
    <CONTROL_TOTAL></CONTROL_TOTAL>
    <TAB_INDEX>3</TAB_INDEX>
    <DATA_VALIDATE></DATA_VALIDATE>
    <TEXT_TYPE>UPPERCASE</TEXT_TYPE>
    <ALLOWCHAR></ALLOWCHAR>
  </WebFormDefinition>

  <WebFormDefinition>
    <DETAIL_ID>4</DETAIL_ID>
    <FORM_ID>406</FORM_ID>
    <HTML_CONTROL_ID>IsAirline</HTML_CONTROL_ID>
    <DISPLAY_ORDER>4</DISPLAY_ORDER>
    <ASSEMBLY_NAME>HTML.RadioButtonList</ASSEMBLY_NAME>
    <LABEL_CELL_TEXT>Airline</LABEL_CELL_TEXT>
    <LABEL_CELL_CSSCLASS>formlabel</LABEL_CELL_CSSCLASS>
    <DATA_FIELDNAME>IsAirline</DATA_FIELDNAME>
    <DATA_FIELD_CSSCLASS></DATA_FIELD_CSSCLASS>
    <DATA_CELL_CSSCLASS>formInputcolumn</DATA_CELL_CSSCLASS>
    <ONCLICK_HANDLER></ONCLICK_HANDLER>
    <POSTBACK_URL></POSTBACK_URL>
    <CALLBACK_URL></CALLBACK_URL>
    <SKIN_ID></SKIN_ID>
    <TOOLTIP>Airline</TOOLTIP>
    <BTN_USESUBMIT_BEHAVIOUR>true</BTN_USESUBMIT_BEHAVIOUR>
    <VISIBLE>true</VISIBLE>
    <READONLY>true</READONLY>
    <ENABLE_VIEWSTATE>true</ENABLE_VIEWSTATE>
    <MAXLENGTH></MAXLENGTH>
    <MULTILINE></MULTILINE>
    <WIDTH></WIDTH>
    <HEIGHT></HEIGHT>
    <SECTION_NAME></SECTION_NAME>
    <ONKEY_HANDLER></ONKEY_HANDLER>
    <ONBLUR_HANDLER></ONBLUR_HANDLER>
    <ENABLE_REQUIREVALIDATION>false</ENABLE_REQUIREVALIDATION>
    <REQUIRED_FIELD_MESSAGE>Airline can not be blank</REQUIRED_FIELD_MESSAGE>
    <LOOKUP_NAME></LOOKUP_NAME>
    <IMAGE_URL></IMAGE_URL>
    <CONTROL_TOTAL></CONTROL_TOTAL>
    <TAB_INDEX>4</TAB_INDEX>
    <TEXT_TYPE>ENUM.ACTIVE</TEXT_TYPE>
    <ALLOWCHAR></ALLOWCHAR>
    <DATA_VALIDATE></DATA_VALIDATE>
  </WebFormDefinition>
  <WebFormDefinition>
    <DETAIL_ID>5</DETAIL_ID>
    <FORM_ID>406</FORM_ID>
    <HTML_CONTROL_ID>IsActive</HTML_CONTROL_ID>
    <DISPLAY_ORDER>5</DISPLAY_ORDER>
    <ASSEMBLY_NAME>HTML.RadioButtonList</ASSEMBLY_NAME>
    <LABEL_CELL_TEXT>Active</LABEL_CELL_TEXT>
    <LABEL_CELL_CSSCLASS> formlabel</LABEL_CELL_CSSCLASS>
    <DATA_FIELDNAME>IsActive</DATA_FIELDNAME>
    <DATA_FIELD_CSSCLASS></DATA_FIELD_CSSCLASS>
    <DATA_CELL_CSSCLASS>formInputcolumn</DATA_CELL_CSSCLASS>
    <ONCLICK_HANDLER></ONCLICK_HANDLER>
    <POSTBACK_URL></POSTBACK_URL>
    <CALLBACK_URL></CALLBACK_URL>
    <SKIN_ID></SKIN_ID>
    <TOOLTIP>Active</TOOLTIP>
    <BTN_USESUBMIT_BEHAVIOUR>true</BTN_USESUBMIT_BEHAVIOUR>
    <VISIBLE>true</VISIBLE>
    <READONLY>true</READONLY>
    <ENABLE_VIEWSTATE>true</ENABLE_VIEWSTATE>
    <MAXLENGTH></MAXLENGTH>
    <MULTILINE></MULTILINE>
    <WIDTH></WIDTH>
    <HEIGHT></HEIGHT>
    <SECTION_NAME></SECTION_NAME>
    <ONKEY_HANDLER></ONKEY_HANDLER>
    <ONBLUR_HANDLER></ONBLUR_HANDLER>
    <ENABLE_REQUIREVALIDATION>false</ENABLE_REQUIREVALIDATION>
    <REQUIRED_FIELD_MESSAGE>Active can not be blank</REQUIRED_FIELD_MESSAGE>
    <LOOKUP_NAME></LOOKUP_NAME>
    <IMAGE_URL></IMAGE_URL>
    <CONTROL_TOTAL></CONTROL_TOTAL>
    <TAB_INDEX>3</TAB_INDEX>
    <TEXT_TYPE>ENUM.ACTIVE</TEXT_TYPE>
    <ALLOWCHAR></ALLOWCHAR>
    <DATA_VALIDATE></DATA_VALIDATE>
  </WebFormDefinition>
 
</DataTable>