<DataTable>


  <!--6th start SPHC-->
  <WebFormDefinition>
    <DETAIL_ID>1</DETAIL_ID>
    <FORM_ID>32</FORM_ID>
    <HTML_CONTROL_ID>SPHC</HTML_CONTROL_ID>
    <DISPLAY_ORDER>1</DISPLAY_ORDER>
    <ASSEMBLY_NAME>HTML.AutoCompleteTextBox</ASSEMBLY_NAME>
    <LABEL_CELL_TEXT>IMP</LABEL_CELL_TEXT>
    <LABEL_CELL_CSSCLASS>formtHeaderLabel</LABEL_CELL_CSSCLASS>
    <DATA_FIELDNAME>SPHC</DATA_FIELDNAME>
    <DATA_FIELD_CSSCLASS></DATA_FIELD_CSSCLASS>
    <DATA_CELL_CSSCLASS>formHeaderTranscolumn</DATA_CELL_CSSCLASS>
    <ONCLICK_HANDLER></ONCLICK_HANDLER>
    <POSTBACK_URL></POSTBACK_URL>
    <CALLBACK_URL></CALLBACK_URL>
    <SKIN_ID></SKIN_ID>
    <TOOLTIP>Enter Special Handling Code</TOOLTIP>
    <BTN_USESUBMIT_BEHAVIOUR></BTN_USESUBMIT_BEHAVIOUR>
    <VISIBLE>true</VISIBLE>
    <READONLY>false</READONLY>
    <ENABLE_VIEWSTATE>true</ENABLE_VIEWSTATE>
    <MAXLENGTH>10</MAXLENGTH>
    <MULTILINE></MULTILINE>
    <WIDTH>50</WIDTH>
    <HEIGHT></HEIGHT>
    <TAB_ID></TAB_ID>
    <TAB_NAME></TAB_NAME>
    <SECTION_ID></SECTION_ID>
    <SECTION_NAME></SECTION_NAME>
    <ONKEY_HANDLER></ONKEY_HANDLER>
    <ONBLUR_HANDLER></ONBLUR_HANDLER>
    <ENABLE_REQUIREVALIDATION></ENABLE_REQUIREVALIDATION>
    <REQUIRED_FIELD_MESSAGE></REQUIRED_FIELD_MESSAGE>
    <LOOKUP_NAME></LOOKUP_NAME>
    <IMAGE_URL></IMAGE_URL>
    <CONTROL_TOTAL></CONTROL_TOTAL>
    <TAB_INDEX></TAB_INDEX>
    <DATA_VALIDATE></DATA_VALIDATE>
    <TEXT_TYPE>ALPHANUMERICUPPER</TEXT_TYPE>
    <ALLOWCHAR></ALLOWCHAR>
  </WebFormDefinition>
  <!--1. SPHC-->

  <WebFormDefinition>
    <DETAIL_ID>1</DETAIL_ID>
    <FORM_ID>32</FORM_ID>
    <HTML_CONTROL_ID>UnNo</HTML_CONTROL_ID>
    <DISPLAY_ORDER>2</DISPLAY_ORDER>
    <ASSEMBLY_NAME>HTML.AutoCompleteTextBox</ASSEMBLY_NAME>
    <LABEL_CELL_TEXT>UN(ID) No/Proper Shipping Name</LABEL_CELL_TEXT>
    <LABEL_CELL_CSSCLASS>formtHeaderLabel</LABEL_CELL_CSSCLASS>
    <DATA_FIELDNAME>UnNo</DATA_FIELDNAME>
    <DATA_FIELD_CSSCLASS></DATA_FIELD_CSSCLASS>
    <DATA_CELL_CSSCLASS>formHeaderTranscolumn</DATA_CELL_CSSCLASS>
    <ONCLICK_HANDLER></ONCLICK_HANDLER>
    <POSTBACK_URL></POSTBACK_URL>
    <CALLBACK_URL></CALLBACK_URL>
    <SKIN_ID></SKIN_ID>
    <TOOLTIP>Select UN(ID) No/Proper Shipping Name</TOOLTIP>
    <BTN_USESUBMIT_BEHAVIOUR></BTN_USESUBMIT_BEHAVIOUR>
    <VISIBLE>true</VISIBLE>
    <READONLY>false</READONLY>
    <ENABLE_VIEWSTATE>true</ENABLE_VIEWSTATE>
    <MAXLENGTH></MAXLENGTH>
    <MULTILINE></MULTILINE>
    <WIDTH>100</WIDTH>
    <HEIGHT></HEIGHT>
    <SECTION_NAME></SECTION_NAME>
    <ONKEY_HANDLER></ONKEY_HANDLER>
    <ONBLUR_HANDLER></ONBLUR_HANDLER>
    <ENABLE_REQUIREVALIDATION>false</ENABLE_REQUIREVALIDATION>
    <REQUIRED_FIELD_MESSAGE></REQUIRED_FIELD_MESSAGE>
    <LOOKUP_NAME></LOOKUP_NAME>
    <IMAGE_URL></IMAGE_URL>
    <CONTROL_TOTAL></CONTROL_TOTAL>
    <TAB_INDEX></TAB_INDEX>
    <TEXT_TYPE>ALPHANUMERICUPPER</TEXT_TYPE>
    <ALLOWCHAR></ALLOWCHAR>
    <DATA_VALIDATE></DATA_VALIDATE>
  </WebFormDefinition>
  <!--2. UnNo-->

  <!--<WebFormDefinition>
    <DETAIL_ID>1</DETAIL_ID>
    <FORM_ID>32</FORM_ID>
    <HTML_CONTROL_ID>ShippingName</HTML_CONTROL_ID>
    <DISPLAY_ORDER>3</DISPLAY_ORDER>
    <ASSEMBLY_NAME>HTML.AutoCompleteTextBox</ASSEMBLY_NAME>
    <LABEL_CELL_TEXT>Proper Shipping Name/Description</LABEL_CELL_TEXT>
    <LABEL_CELL_CSSCLASS>formtHeaderLabel</LABEL_CELL_CSSCLASS>
    <DATA_FIELDNAME>ShippingName</DATA_FIELDNAME>
    <DATA_FIELD_CSSCLASS></DATA_FIELD_CSSCLASS>
    <DATA_CELL_CSSCLASS>formHeaderTranscolumn</DATA_CELL_CSSCLASS>
    <ONCLICK_HANDLER></ONCLICK_HANDLER>
    <POSTBACK_URL></POSTBACK_URL>
    <CALLBACK_URL></CALLBACK_URL>
    <SKIN_ID></SKIN_ID>
    <TOOLTIP>Select Shipping Name/Description</TOOLTIP>
    <BTN_USESUBMIT_BEHAVIOUR></BTN_USESUBMIT_BEHAVIOUR>
    <VISIBLE>true</VISIBLE>
    <READONLY>false</READONLY>
    <ENABLE_VIEWSTATE>true</ENABLE_VIEWSTATE>
    <MAXLENGTH>500</MAXLENGTH>
    <MULTILINE></MULTILINE>
    <WIDTH>100</WIDTH>
    <HEIGHT></HEIGHT>
    <SECTION_NAME></SECTION_NAME>
    <ONKEY_HANDLER></ONKEY_HANDLER>
    <ONBLUR_HANDLER></ONBLUR_HANDLER>
    <ENABLE_REQUIREVALIDATION>false</ENABLE_REQUIREVALIDATION>
    <REQUIRED_FIELD_MESSAGE></REQUIRED_FIELD_MESSAGE>
    <LOOKUP_NAME></LOOKUP_NAME>
    <IMAGE_URL></IMAGE_URL>
    <CONTROL_TOTAL></CONTROL_TOTAL>
    <TAB_INDEX></TAB_INDEX>
    <TEXT_TYPE>ALPHANUMERICUPPER</TEXT_TYPE>
    <ALLOWCHAR></ALLOWCHAR>
    <DATA_VALIDATE></DATA_VALIDATE>
  </WebFormDefinition>-->
  <!--3. Shipping Name/Description-->

  <WebFormDefinition>
    <DETAIL_ID>1</DETAIL_ID>
    <FORM_ID>32</FORM_ID>
    <HTML_CONTROL_ID>DGRCommodity</HTML_CONTROL_ID>
    <DISPLAY_ORDER>4</DISPLAY_ORDER>
    <ASSEMBLY_NAME>HTML.TextBox</ASSEMBLY_NAME>
    <LABEL_CELL_TEXT>Commodity</LABEL_CELL_TEXT>
    <LABEL_CELL_CSSCLASS>formtHeaderLabel</LABEL_CELL_CSSCLASS>
    <DATA_FIELDNAME>DGRCommodity</DATA_FIELDNAME>
    <DATA_FIELD_CSSCLASS></DATA_FIELD_CSSCLASS>
    <DATA_CELL_CSSCLASS>formHeaderTranscolumn</DATA_CELL_CSSCLASS>
    <ONCLICK_HANDLER></ONCLICK_HANDLER>
    <POSTBACK_URL></POSTBACK_URL>
    <CALLBACK_URL></CALLBACK_URL>
    <SKIN_ID></SKIN_ID>
    <TOOLTIP>Enter Commodity</TOOLTIP>
    <BTN_USESUBMIT_BEHAVIOUR></BTN_USESUBMIT_BEHAVIOUR>
    <VISIBLE>true</VISIBLE>
    <READONLY>false</READONLY>
    <ENABLE_VIEWSTATE>true</ENABLE_VIEWSTATE>
    <MAXLENGTH>200</MAXLENGTH>
    <MULTILINE>Yes</MULTILINE>
    <WIDTH>120</WIDTH>
    <HEIGHT></HEIGHT>
    <SECTION_NAME></SECTION_NAME>
    <ONKEY_HANDLER></ONKEY_HANDLER>
    <ONBLUR_HANDLER></ONBLUR_HANDLER>
    <ENABLE_REQUIREVALIDATION>false</ENABLE_REQUIREVALIDATION>
    <REQUIRED_FIELD_MESSAGE></REQUIRED_FIELD_MESSAGE>
    <LOOKUP_NAME></LOOKUP_NAME>
    <IMAGE_URL></IMAGE_URL>
    <CONTROL_TOTAL></CONTROL_TOTAL>
    <TAB_INDEX></TAB_INDEX>
    <TEXT_TYPE>default</TEXT_TYPE>
    <ALLOWCHAR></ALLOWCHAR>
    <DATA_VALIDATE></DATA_VALIDATE>
  </WebFormDefinition>
  <!--4. Commodity  -->

  <WebFormDefinition>
    <DETAIL_ID>1</DETAIL_ID>
    <FORM_ID>32</FORM_ID>
    <HTML_CONTROL_ID>Class</HTML_CONTROL_ID>
    <DISPLAY_ORDER>5</DISPLAY_ORDER>
    <ASSEMBLY_NAME>HTML.AutoCompleteTextBox</ASSEMBLY_NAME>
    <LABEL_CELL_TEXT>CLASS</LABEL_CELL_TEXT>
    <LABEL_CELL_CSSCLASS>formtHeaderLabel</LABEL_CELL_CSSCLASS>
    <DATA_FIELDNAME>Class</DATA_FIELDNAME>
    <DATA_FIELD_CSSCLASS></DATA_FIELD_CSSCLASS>
    <DATA_CELL_CSSCLASS>formHeaderTranscolumn</DATA_CELL_CSSCLASS>
    <ONCLICK_HANDLER></ONCLICK_HANDLER>
    <POSTBACK_URL></POSTBACK_URL>
    <CALLBACK_URL></CALLBACK_URL>
    <SKIN_ID></SKIN_ID>
    <TOOLTIP>Select Class</TOOLTIP>
    <BTN_USESUBMIT_BEHAVIOUR></BTN_USESUBMIT_BEHAVIOUR>
    <VISIBLE>true</VISIBLE>
    <READONLY>false</READONLY>
    <ENABLE_VIEWSTATE>true</ENABLE_VIEWSTATE>
    <MAXLENGTH>10</MAXLENGTH>
    <MULTILINE></MULTILINE>
    <WIDTH>100</WIDTH>
    <HEIGHT></HEIGHT>
    <SECTION_NAME></SECTION_NAME>
    <ONKEY_HANDLER></ONKEY_HANDLER>
    <ONBLUR_HANDLER></ONBLUR_HANDLER>
    <ENABLE_REQUIREVALIDATION>false</ENABLE_REQUIREVALIDATION>
    <REQUIRED_FIELD_MESSAGE>
    </REQUIRED_FIELD_MESSAGE>
    <LOOKUP_NAME></LOOKUP_NAME>
    <IMAGE_URL></IMAGE_URL>
    <CONTROL_TOTAL></CONTROL_TOTAL>
    <TAB_INDEX></TAB_INDEX>
    <TEXT_TYPE>ALPHANUMERICUPPER</TEXT_TYPE>
    <ALLOWCHAR></ALLOWCHAR>
    <DATA_VALIDATE></DATA_VALIDATE>
  </WebFormDefinition>
  <!--5. Class -->



  <!--<WebFormDefinition>
    <DETAIL_ID>1</DETAIL_ID>
    <FORM_ID>32</FORM_ID>
    <HTML_CONTROL_ID>TP</HTML_CONTROL_ID>
    <DISPLAY_ORDER>6</DISPLAY_ORDER>
    <ASSEMBLY_NAME>HTML.TextBox</ASSEMBLY_NAME>
    <LABEL_CELL_TEXT>Transport Index</LABEL_CELL_TEXT>
    <LABEL_CELL_CSSCLASS>formtHeaderLabel</LABEL_CELL_CSSCLASS>
    <DATA_FIELDNAME></DATA_FIELDNAME>
    <DATA_FIELD_CSSCLASS></DATA_FIELD_CSSCLASS>
    <DATA_CELL_CSSCLASS>formHeaderTranscolumn</DATA_CELL_CSSCLASS>
    <ONCLICK_HANDLER></ONCLICK_HANDLER>
    <POSTBACK_URL></POSTBACK_URL>
    <CALLBACK_URL></CALLBACK_URL>
    <SKIN_ID></SKIN_ID>
    <TOOLTIP>Enter Transport Index</TOOLTIP>
    <BTN_USESUBMIT_BEHAVIOUR></BTN_USESUBMIT_BEHAVIOUR>
    <VISIBLE>true</VISIBLE>
    <READONLY>false</READONLY>
    <ENABLE_VIEWSTATE>true</ENABLE_VIEWSTATE>
    <MAXLENGTH>200</MAXLENGTH>
    <MULTILINE>Yes</MULTILINE>
    <WIDTH>120</WIDTH>
    <HEIGHT></HEIGHT>
    <SECTION_NAME></SECTION_NAME>
    <ONKEY_HANDLER></ONKEY_HANDLER>
    <ONBLUR_HANDLER></ONBLUR_HANDLER>
    <ENABLE_REQUIREVALIDATION>false</ENABLE_REQUIREVALIDATION>
    <REQUIRED_FIELD_MESSAGE></REQUIRED_FIELD_MESSAGE>
    <LOOKUP_NAME></LOOKUP_NAME>
    <IMAGE_URL></IMAGE_URL>
    <CONTROL_TOTAL></CONTROL_TOTAL>
    <TAB_INDEX></TAB_INDEX>
    <TEXT_TYPE>default</TEXT_TYPE>
    <ALLOWCHAR></ALLOWCHAR>
    <DATA_VALIDATE></DATA_VALIDATE>
  </WebFormDefinition>-->
  <!--6. Transport Index -->
  
  
  
  
  
  
  
  
  
  <WebFormDefinition>
    <DETAIL_ID>1</DETAIL_ID>
    <FORM_ID>32</FORM_ID>
    <HTML_CONTROL_ID>SubRisk</HTML_CONTROL_ID>
    <DISPLAY_ORDER>7</DISPLAY_ORDER>
    <ASSEMBLY_NAME>HTML.AutoCompleteTextBox</ASSEMBLY_NAME>
    <LABEL_CELL_TEXT>SUB RISK</LABEL_CELL_TEXT>
    <LABEL_CELL_CSSCLASS>formtHeaderLabel</LABEL_CELL_CSSCLASS>
    <DATA_FIELDNAME>SubRisk</DATA_FIELDNAME>
    <DATA_FIELD_CSSCLASS></DATA_FIELD_CSSCLASS>
    <DATA_CELL_CSSCLASS>formHeaderTranscolumn</DATA_CELL_CSSCLASS>
    <ONCLICK_HANDLER></ONCLICK_HANDLER>
    <POSTBACK_URL></POSTBACK_URL>
    <CALLBACK_URL></CALLBACK_URL>
    <SKIN_ID></SKIN_ID>
    <TOOLTIP>Select Sub Risk</TOOLTIP>
    <BTN_USESUBMIT_BEHAVIOUR></BTN_USESUBMIT_BEHAVIOUR>
    <VISIBLE>true</VISIBLE>
    <READONLY>false</READONLY>
    <ENABLE_VIEWSTATE>true</ENABLE_VIEWSTATE>
    <MAXLENGTH></MAXLENGTH>
    <MULTILINE></MULTILINE>
    <WIDTH>100</WIDTH>
    <HEIGHT></HEIGHT>
    <SECTION_NAME></SECTION_NAME>
    <ONKEY_HANDLER></ONKEY_HANDLER>
    <ONBLUR_HANDLER></ONBLUR_HANDLER>
    <ENABLE_REQUIREVALIDATION>false</ENABLE_REQUIREVALIDATION>
    <REQUIRED_FIELD_MESSAGE></REQUIRED_FIELD_MESSAGE>
    <LOOKUP_NAME></LOOKUP_NAME>
    <IMAGE_URL></IMAGE_URL>
    <CONTROL_TOTAL></CONTROL_TOTAL>
    <TAB_INDEX></TAB_INDEX>
    <TEXT_TYPE>ALPHANUMERICUPPER</TEXT_TYPE>
    <ALLOWCHAR></ALLOWCHAR>
    <DATA_VALIDATE></DATA_VALIDATE>
  </WebFormDefinition>
  <!--6. SubRisk -->

  <WebFormDefinition>
    <DETAIL_ID>1</DETAIL_ID>
    <FORM_ID>32</FORM_ID>
    <HTML_CONTROL_ID>PackingGroup</HTML_CONTROL_ID>
    <DISPLAY_ORDER>8</DISPLAY_ORDER>
    <ASSEMBLY_NAME>HTML.AutoCompleteTextBox</ASSEMBLY_NAME>
    <LABEL_CELL_TEXT>PACKING GROUP</LABEL_CELL_TEXT>
    <LABEL_CELL_CSSCLASS>formtHeaderLabel</LABEL_CELL_CSSCLASS>
    <DATA_FIELDNAME>PackingGroup</DATA_FIELDNAME>
    <DATA_FIELD_CSSCLASS></DATA_FIELD_CSSCLASS>
    <DATA_CELL_CSSCLASS>formHeaderTranscolumn</DATA_CELL_CSSCLASS>
    <ONCLICK_HANDLER></ONCLICK_HANDLER>
    <POSTBACK_URL></POSTBACK_URL>
    <CALLBACK_URL></CALLBACK_URL>
    <SKIN_ID></SKIN_ID>
    <TOOLTIP>Select Packing Group</TOOLTIP>
    <BTN_USESUBMIT_BEHAVIOUR></BTN_USESUBMIT_BEHAVIOUR>
    <VISIBLE>true</VISIBLE>
    <READONLY>false</READONLY>
    <ENABLE_VIEWSTATE>true</ENABLE_VIEWSTATE>
    <MAXLENGTH></MAXLENGTH>
    <MULTILINE></MULTILINE>
    <WIDTH>100</WIDTH>
    <HEIGHT></HEIGHT>
    <SECTION_NAME></SECTION_NAME>
    <ONKEY_HANDLER></ONKEY_HANDLER>
    <ONBLUR_HANDLER></ONBLUR_HANDLER>
    <ENABLE_REQUIREVALIDATION>false</ENABLE_REQUIREVALIDATION>
    <REQUIRED_FIELD_MESSAGE></REQUIRED_FIELD_MESSAGE>
    <LOOKUP_NAME></LOOKUP_NAME>
    <IMAGE_URL></IMAGE_URL>
    <CONTROL_TOTAL></CONTROL_TOTAL>
    <TAB_INDEX></TAB_INDEX>
    <TEXT_TYPE>ALPHANUMERICUPPER</TEXT_TYPE>
    <ALLOWCHAR></ALLOWCHAR>
    <DATA_VALIDATE></DATA_VALIDATE>
  </WebFormDefinition>
  <!--7. Packing Group -->

  <WebFormDefinition>
    <DETAIL_ID>1</DETAIL_ID>
    <FORM_ID>32</FORM_ID>
    <HTML_CONTROL_ID>DGRPieces</HTML_CONTROL_ID>
    <DISPLAY_ORDER>9</DISPLAY_ORDER>
    <ASSEMBLY_NAME>HTML.TextBox</ASSEMBLY_NAME>
    <LABEL_CELL_TEXT>PIECES</LABEL_CELL_TEXT>
    <LABEL_CELL_CSSCLASS>formtHeaderLabel</LABEL_CELL_CSSCLASS>
    <DATA_FIELDNAME>DGRPieces</DATA_FIELDNAME>
    <DATA_FIELD_CSSCLASS></DATA_FIELD_CSSCLASS>
    <DATA_CELL_CSSCLASS>formHeaderTranscolumn</DATA_CELL_CSSCLASS>
    <ONCLICK_HANDLER></ONCLICK_HANDLER>
    <POSTBACK_URL></POSTBACK_URL>
    <CALLBACK_URL></CALLBACK_URL>
    <SKIN_ID></SKIN_ID>
    <TOOLTIP>Enter Pieces</TOOLTIP>
    <BTN_USESUBMIT_BEHAVIOUR></BTN_USESUBMIT_BEHAVIOUR>
    <VISIBLE>true</VISIBLE>
    <READONLY>false</READONLY>
    <ENABLE_VIEWSTATE>true</ENABLE_VIEWSTATE>
    <MAXLENGTH></MAXLENGTH>
    <MULTILINE></MULTILINE>
    <WIDTH>50</WIDTH>
    <HEIGHT></HEIGHT>
    <SECTION_NAME></SECTION_NAME>
    <ONKEY_HANDLER></ONKEY_HANDLER>
    <ONBLUR_HANDLER>GetQty(this)</ONBLUR_HANDLER>
    <ENABLE_REQUIREVALIDATION>false</ENABLE_REQUIREVALIDATION>
    <REQUIRED_FIELD_MESSAGE></REQUIRED_FIELD_MESSAGE>
    <LOOKUP_NAME></LOOKUP_NAME>
    <IMAGE_URL></IMAGE_URL>
    <CONTROL_TOTAL></CONTROL_TOTAL>
    <TAB_INDEX></TAB_INDEX>
    <TEXT_TYPE>number</TEXT_TYPE>
    <ALLOWCHAR></ALLOWCHAR>
    <DATA_VALIDATE></DATA_VALIDATE>
  </WebFormDefinition>
  <!--8. Pieces -->

  <WebFormDefinition>
    <DETAIL_ID>1</DETAIL_ID>
    <FORM_ID>32</FORM_ID>
    <HTML_CONTROL_ID>NetQuantity</HTML_CONTROL_ID>
    <DISPLAY_ORDER>10</DISPLAY_ORDER>
    <ASSEMBLY_NAME>HTML.TextBox</ASSEMBLY_NAME>
    <LABEL_CELL_TEXT>NET QUANTITY</LABEL_CELL_TEXT>
    <LABEL_CELL_CSSCLASS>formtHeaderLabel</LABEL_CELL_CSSCLASS>
    <DATA_FIELDNAME>NetQuantity</DATA_FIELDNAME>
    <DATA_FIELD_CSSCLASS></DATA_FIELD_CSSCLASS>
    <DATA_CELL_CSSCLASS>formHeaderTranscolumn</DATA_CELL_CSSCLASS>
    <ONCLICK_HANDLER></ONCLICK_HANDLER>
    <POSTBACK_URL></POSTBACK_URL>
    <CALLBACK_URL></CALLBACK_URL>
    <SKIN_ID></SKIN_ID>
    <TOOLTIP>Enter Net Quantity</TOOLTIP>
    <BTN_USESUBMIT_BEHAVIOUR></BTN_USESUBMIT_BEHAVIOUR>
    <VISIBLE>true</VISIBLE>
    <READONLY>false</READONLY>
    <ENABLE_VIEWSTATE>true</ENABLE_VIEWSTATE>
    <MAXLENGTH>5</MAXLENGTH>
    <MULTILINE></MULTILINE>
    <WIDTH>50</WIDTH>
    <HEIGHT></HEIGHT>
    <SECTION_NAME></SECTION_NAME>
    <ONKEY_HANDLER></ONKEY_HANDLER>
    <ONBLUR_HANDLER>GetQty(this)</ONBLUR_HANDLER>
    <ENABLE_REQUIREVALIDATION>false</ENABLE_REQUIREVALIDATION>
    <REQUIRED_FIELD_MESSAGE></REQUIRED_FIELD_MESSAGE>
    <LOOKUP_NAME></LOOKUP_NAME>
    <IMAGE_URL></IMAGE_URL>
    <CONTROL_TOTAL></CONTROL_TOTAL>
    <TAB_INDEX></TAB_INDEX>
    <TEXT_TYPE>CONTACT</TEXT_TYPE>
    <ALLOWCHAR>.</ALLOWCHAR>
    <DATA_VALIDATE></DATA_VALIDATE>
  </WebFormDefinition>
  <!--9. Net Quantity -->

  <WebFormDefinition>
    <DETAIL_ID>1</DETAIL_ID>
    <FORM_ID>32</FORM_ID>
    <HTML_CONTROL_ID>Unit</HTML_CONTROL_ID>
    <DISPLAY_ORDER>11</DISPLAY_ORDER>
    <ASSEMBLY_NAME>HTML.AutoCompleteTextBox</ASSEMBLY_NAME>
    <LABEL_CELL_TEXT>UNIT</LABEL_CELL_TEXT>
    <LABEL_CELL_CSSCLASS>formtHeaderLabel</LABEL_CELL_CSSCLASS>
    <DATA_FIELDNAME>Unit</DATA_FIELDNAME>
    <DATA_FIELD_CSSCLASS></DATA_FIELD_CSSCLASS>
    <DATA_CELL_CSSCLASS>formHeaderTranscolumn</DATA_CELL_CSSCLASS>
    <ONCLICK_HANDLER></ONCLICK_HANDLER>
    <POSTBACK_URL></POSTBACK_URL>
    <CALLBACK_URL></CALLBACK_URL>
    <SKIN_ID></SKIN_ID>
    <TOOLTIP>Select Unit</TOOLTIP>
    <BTN_USESUBMIT_BEHAVIOUR></BTN_USESUBMIT_BEHAVIOUR>
    <VISIBLE>true</VISIBLE>
    <READONLY>false</READONLY>
    <ENABLE_VIEWSTATE>true</ENABLE_VIEWSTATE>
    <MAXLENGTH></MAXLENGTH>
    <MULTILINE></MULTILINE>
    <WIDTH>50</WIDTH>
    <HEIGHT></HEIGHT>
    <SECTION_NAME></SECTION_NAME>
    <ONKEY_HANDLER></ONKEY_HANDLER>
    <ONBLUR_HANDLER></ONBLUR_HANDLER>
    <ENABLE_REQUIREVALIDATION>false</ENABLE_REQUIREVALIDATION>
    <REQUIRED_FIELD_MESSAGE></REQUIRED_FIELD_MESSAGE>
    <LOOKUP_NAME></LOOKUP_NAME>
    <IMAGE_URL></IMAGE_URL>
    <CONTROL_TOTAL></CONTROL_TOTAL>
    <TAB_INDEX></TAB_INDEX>
    <TEXT_TYPE>ALPHANUMERICUPPER</TEXT_TYPE>
    <ALLOWCHAR></ALLOWCHAR>
    <DATA_VALIDATE></DATA_VALIDATE>
  </WebFormDefinition>
  <!--10. Unit-->

  <WebFormDefinition>
    <DETAIL_ID>1</DETAIL_ID>
    <FORM_ID>32</FORM_ID>
    <HTML_CONTROL_ID>Quantity</HTML_CONTROL_ID>
    <DISPLAY_ORDER>12</DISPLAY_ORDER>
    <ASSEMBLY_NAME>HTML.TextBox</ASSEMBLY_NAME>
    <LABEL_CELL_TEXT>Max Qty</LABEL_CELL_TEXT>
    <LABEL_CELL_CSSCLASS>formtHeaderLabel</LABEL_CELL_CSSCLASS>
    <DATA_FIELDNAME>Quantity</DATA_FIELDNAME>
    <DATA_FIELD_CSSCLASS></DATA_FIELD_CSSCLASS>
    <DATA_CELL_CSSCLASS>formHeaderTranscolumn</DATA_CELL_CSSCLASS>
    <ONCLICK_HANDLER></ONCLICK_HANDLER>
    <POSTBACK_URL></POSTBACK_URL>
    <CALLBACK_URL></CALLBACK_URL>
    <SKIN_ID></SKIN_ID>
    <TOOLTIP>Enter Quantity</TOOLTIP>
    <BTN_USESUBMIT_BEHAVIOUR></BTN_USESUBMIT_BEHAVIOUR>
    <VISIBLE>true</VISIBLE>
    <READONLY>false</READONLY>
    <ENABLE_VIEWSTATE>true</ENABLE_VIEWSTATE>
    <MAXLENGTH></MAXLENGTH>
    <MULTILINE></MULTILINE>
    <WIDTH>50</WIDTH>
    <HEIGHT></HEIGHT>
    <SECTION_NAME></SECTION_NAME>
    <ONKEY_HANDLER></ONKEY_HANDLER>
    <ONBLUR_HANDLER></ONBLUR_HANDLER>
    <ENABLE_REQUIREVALIDATION>false</ENABLE_REQUIREVALIDATION>
    <REQUIRED_FIELD_MESSAGE></REQUIRED_FIELD_MESSAGE>
    <LOOKUP_NAME></LOOKUP_NAME>
    <IMAGE_URL></IMAGE_URL>
    <CONTROL_TOTAL></CONTROL_TOTAL>
    <TAB_INDEX></TAB_INDEX>
    <TEXT_TYPE>ALPHANUMERICUPPER</TEXT_TYPE>
    <ALLOWCHAR></ALLOWCHAR>
    <DATA_VALIDATE></DATA_VALIDATE>
  </WebFormDefinition>
  <!--11. Quantity-->

  <WebFormDefinition>
    <DETAIL_ID>1</DETAIL_ID>
    <FORM_ID>32</FORM_ID>
    <HTML_CONTROL_ID>PackingInst</HTML_CONTROL_ID>
    <DISPLAY_ORDER>13</DISPLAY_ORDER>
    <ASSEMBLY_NAME>HTML.AutoCompleteTextBox</ASSEMBLY_NAME>
    <LABEL_CELL_TEXT>PACKING INST.</LABEL_CELL_TEXT>
    <LABEL_CELL_CSSCLASS>formtHeaderLabel</LABEL_CELL_CSSCLASS>
    <DATA_FIELDNAME>PackingInst</DATA_FIELDNAME>
    <DATA_FIELD_CSSCLASS></DATA_FIELD_CSSCLASS>
    <DATA_CELL_CSSCLASS>formHeaderTranscolumn</DATA_CELL_CSSCLASS>
    <ONCLICK_HANDLER></ONCLICK_HANDLER>
    <POSTBACK_URL></POSTBACK_URL>
    <CALLBACK_URL></CALLBACK_URL>
    <SKIN_ID></SKIN_ID>
    <TOOLTIP>Select Packing Inst.</TOOLTIP>
    <BTN_USESUBMIT_BEHAVIOUR></BTN_USESUBMIT_BEHAVIOUR>
    <VISIBLE>true</VISIBLE>
    <READONLY>false</READONLY>
    <ENABLE_VIEWSTATE>true</ENABLE_VIEWSTATE>
    <MAXLENGTH></MAXLENGTH>
    <MULTILINE></MULTILINE>
    <WIDTH>100</WIDTH>
    <HEIGHT></HEIGHT>
    <SECTION_NAME></SECTION_NAME>
    <ONKEY_HANDLER></ONKEY_HANDLER>
    <ONBLUR_HANDLER></ONBLUR_HANDLER>
    <ENABLE_REQUIREVALIDATION>false</ENABLE_REQUIREVALIDATION>
    <REQUIRED_FIELD_MESSAGE></REQUIRED_FIELD_MESSAGE>
    <LOOKUP_NAME></LOOKUP_NAME>
    <IMAGE_URL></IMAGE_URL>
    <CONTROL_TOTAL></CONTROL_TOTAL>
    <TAB_INDEX></TAB_INDEX>
    <TEXT_TYPE>ALPHANUMERICUPPER</TEXT_TYPE>
    <ALLOWCHAR></ALLOWCHAR>
    <DATA_VALIDATE></DATA_VALIDATE>
  </WebFormDefinition>
  <!--12. Packing Inst.-->

  <WebFormDefinition>
    <DETAIL_ID>1</DETAIL_ID>
    <FORM_ID>32</FORM_ID>
    <HTML_CONTROL_ID>RamCat</HTML_CONTROL_ID>
    <DISPLAY_ORDER>14</DISPLAY_ORDER>
    <ASSEMBLY_NAME>HTML.TextBox</ASSEMBLY_NAME>
    <LABEL_CELL_TEXT>RAM CATEGORY</LABEL_CELL_TEXT>
    <LABEL_CELL_CSSCLASS>formtHeaderLabel</LABEL_CELL_CSSCLASS>
    <DATA_FIELDNAME>ramcat</DATA_FIELDNAME>
    <DATA_FIELD_CSSCLASS></DATA_FIELD_CSSCLASS>
    <DATA_CELL_CSSCLASS>formHeaderTranscolumn</DATA_CELL_CSSCLASS>
    <ONCLICK_HANDLER></ONCLICK_HANDLER>
    <POSTBACK_URL></POSTBACK_URL>
    <CALLBACK_URL></CALLBACK_URL>
    <SKIN_ID></SKIN_ID>
    <TOOLTIP>Select RamCat</TOOLTIP>
    <BTN_USESUBMIT_BEHAVIOUR></BTN_USESUBMIT_BEHAVIOUR>
    <VISIBLE>true</VISIBLE>
    <READONLY>false</READONLY>
    <ENABLE_VIEWSTATE>true</ENABLE_VIEWSTATE>
    <MAXLENGTH></MAXLENGTH>
    <MULTILINE></MULTILINE>
    <WIDTH>100</WIDTH>
    <HEIGHT></HEIGHT>
    <SECTION_NAME></SECTION_NAME>
    <ONKEY_HANDLER></ONKEY_HANDLER>
    <ONBLUR_HANDLER></ONBLUR_HANDLER>
    <ENABLE_REQUIREVALIDATION>false</ENABLE_REQUIREVALIDATION>
    <REQUIRED_FIELD_MESSAGE></REQUIRED_FIELD_MESSAGE>
    <LOOKUP_NAME></LOOKUP_NAME>
    <IMAGE_URL></IMAGE_URL>
    <CONTROL_TOTAL></CONTROL_TOTAL>
    <TAB_INDEX></TAB_INDEX>
    <TEXT_TYPE>ALPHANUMERICUPPER</TEXT_TYPE>
    <ALLOWCHAR></ALLOWCHAR>
    <DATA_VALIDATE></DATA_VALIDATE>
  </WebFormDefinition>
  <!--13. RamCat-->

  <WebFormDefinition>
    <DETAIL_ID>1</DETAIL_ID>
    <FORM_ID>32</FORM_ID>
    <HTML_CONTROL_ID>ERG</HTML_CONTROL_ID>
    <DISPLAY_ORDER>15</DISPLAY_ORDER>
    <ASSEMBLY_NAME>HTML.AutoCompleteTextBox</ASSEMBLY_NAME>
    <LABEL_CELL_TEXT>ERG</LABEL_CELL_TEXT>
    <LABEL_CELL_CSSCLASS>formtHeaderLabel</LABEL_CELL_CSSCLASS>
    <DATA_FIELDNAME>ERG</DATA_FIELDNAME>
    <DATA_FIELD_CSSCLASS></DATA_FIELD_CSSCLASS>
    <DATA_CELL_CSSCLASS>formHeaderTranscolumn</DATA_CELL_CSSCLASS>
    <ONCLICK_HANDLER></ONCLICK_HANDLER>
    <POSTBACK_URL></POSTBACK_URL>
    <CALLBACK_URL></CALLBACK_URL>
    <SKIN_ID></SKIN_ID>
    <TOOLTIP>Select ERG</TOOLTIP>
    <BTN_USESUBMIT_BEHAVIOUR></BTN_USESUBMIT_BEHAVIOUR>
    <VISIBLE>true</VISIBLE>
    <READONLY>false</READONLY>
    <ENABLE_VIEWSTATE>true</ENABLE_VIEWSTATE>
    <MAXLENGTH></MAXLENGTH>
    <MULTILINE></MULTILINE>
    <WIDTH>100</WIDTH>
    <HEIGHT></HEIGHT>
    <SECTION_NAME></SECTION_NAME>
    <ONKEY_HANDLER></ONKEY_HANDLER>
    <ONBLUR_HANDLER></ONBLUR_HANDLER>
    <ENABLE_REQUIREVALIDATION>false</ENABLE_REQUIREVALIDATION>
    <REQUIRED_FIELD_MESSAGE></REQUIRED_FIELD_MESSAGE>
    <LOOKUP_NAME></LOOKUP_NAME>
    <IMAGE_URL></IMAGE_URL>
    <CONTROL_TOTAL></CONTROL_TOTAL>
    <TAB_INDEX></TAB_INDEX>
    <TEXT_TYPE>ALPHANUMERICUPPER</TEXT_TYPE>
    <ALLOWCHAR></ALLOWCHAR>
    <DATA_VALIDATE></DATA_VALIDATE>
  </WebFormDefinition>
  <!--14. ERG-->

  <!--6th end-->

</DataTable>